Workbook

Sheet LEIA-ME
A1: M1 — Modelo comparativo das quatro vias
B4: Identificação
B5: Projeto: Dra. Júlia Best (NIF 272180610) — cliente faturável: Gerir Saúde.
B6: Origem: ata de 18/08/2026 (MOD COO 007/1). Brief de entregáveis de 22/08/2026.
B7: Estatuto: ENTREGÁVEL INTERNO. Não sai para a cliente — a entrega do ficheiro está expressamente fora de âmbito (secção 5 do brief). O que sai são as tabelas do capítulo 3 e do anexo E2, sem fórmulas visíveis.
B8: Propriedade: ativo reutilizável VCLevel.
B9: Estado atual — ler antes de usar
B10: A cliente não forneceu nenhum dos oito inputs da secção 4 do brief. Todos os valores da folha Inputs são placeholders para testar o motor de cálculo.
B11: Nenhum número deste ficheiro pode ser citado no relatório, no deck ou perante a cliente antes de (i) os inputs reais entrarem, (ii) a folha Parâmetros ser confirmada para 2026 pela equipa de Fiscalidade, e (iii) a folha Validação estar assinada.
B12: Como está organizado
B13: Parâmetros — todas as taxas, escalões e limiares, cada um com a norma e o estado de validação. Nenhuma taxa é escrita dentro de uma fórmula noutra folha.
B14: Operacao — camada operacional: gabinetes, dias, duração da consulta, preço e utilização. É daqui que sai a faturação quando FONTE_FAT = 2. A linha de utilização diz se a projeção cabe fisicamente no espaço.
B15: Inputs — folha única de parâmetros do caso, em três cenários de faturação. Contém a alavanca MOD_COLAB, que alterna entre os dois modelos de colaboração da ata (1 = prestação de serviços, 2 = cedência de sala) e reconfigura toda a estrutura de receita e custo.
... B47: Este ficheiro é gerado por build_m1.py. Alterações estruturais fazem-se no script e regenera-se; alterações de valores fazem-se nas células amarelas.

Sheet Parametros
A1: M1 — Parâmetros fiscais e contributivos
A2: Todos os parâmetros do modelo vivem aqui. Nenhuma folha de cálculo pode conter uma taxa escrita dentro de uma fórmula. Coluna E indica o estado de validação pela equipa de Fiscalidade.
A4: Parâmetro | B4: Referência | C4: Valor | D4: Fonte normativa | E4: Estado de validação | F4: Por validar
A5: Segurança Social
A6: Indexante dos Apoios Sociais (mensal) | B6: IAS | C6: 522.5 | D6: Portaria de atualização anual do IAS | E6: A ATUALIZAR PARA 2026 | F6: 1
A7: TI — % da prestação de serviços que forma o rendimento relevante | B7: SS_TI_PCT | C7: 0.7 | D7: Art. 162.º n.º 1 Cód. Contributivo | E7: Confirmar | F7: 0
A8: TI — taxa contributiva | B8: SS_TI_TAXA | C8: 0.214 | D8: Art. 168.º n.º 1 Cód. Contributivo | E8: Confirmar | F8: 0
A9: TI — teto da base de incidência mensal (múltiplo do IAS) | B9: SS_TI_TETO | C9: 12 | D9: Art. 163.º n.º 2 Cód. Contributivo | E9: Confirmar | F9: 0
A10: TI — contribuição mensal mínima | B10: SS_TI_MIN | C10: 20 | D10: Regime dos trabalhadores independentes | E10: Confirmar | F10: 0
A11: MOE/gerência — taxa a cargo da entidade | B11: SS_MOE_ENT | C11: 0.2375 | D11: Art. 63.º e 168.º Cód. Contributivo | E11: CONFIRMAR (ver R1-12) | F11: 1
A12: MOE/gerência — taxa a cargo do beneficiário | B12: SS_MOE_BEN | C12: 0.11 | D12: Art. 63.º e 168.º Cód. Contributivo | E12: CONFIRMAR (ver R1-12) | F12: 1
A13: MOE — base de incidência mínima (múltiplo do IAS) | B13: SS_MOE_MIN | C13: 1 | D13: Art. 166.º Cód. Contributivo | E13: Confirmar | F13: 0
A14: Trabalhador por conta de outrem — taxa a cargo da entidade empregadora | B14: TSU_ENT | C14: 0.2375 | D14: Art. 53.º Cód. Contributivo | E14: Confirmar | F14: 0
A15: Trabalhador por conta de outrem — taxa a cargo do trabalhador | B15: TSU_TRAB | C15: 0.11 | D15: Art. 53.º Cód. Contributivo | E15: Confirmar | F15: 0
A16: Prazo de prescrição das contribuições (anos) | B16: PRESCR | C16: 5 | D16: Art. 187.º Cód. Contributivo | E16: CONFIRMAR (ver R1-37) | F16: 1
A17: Taxa anual de juros de mora aplicada às contribuições em falta | B17: JUROS_MORA | C17: 0.05 | D17: Regime dos juros de mora de dívidas ao Estado | E17: CONFIRMAR taxa em vigor | F17: 1
A18: Coima estimada, em % das contribuições devidas pela entidade | B18: COIMA_PCT | C18: 0.5 | D18: Moldura das contraordenações do Cód. Contributivo | E18: ESTIMATIVA GROSSEIRA — ver R1-38 | F18: 0
A19: Limiares operacionais de alerta
A20: Utilização acima da qual a projeção é impossível | B20: UTIL_MAX | C20: 1 | D20: Definição do modelo | E20: Validado | F20: 0
A21: Utilização acima da qual a operação é muito exigente | B21: UTIL_ALTA | C21: 0.85 | D21: Convenção de trabalho VCLevel | E21: Decisão de equipa | F21: 0
A22: Utilização abaixo da qual o espaço está subaproveitado | B22: UTIL_BAIXA | C22: 0.3 | D22: Convenção de trabalho VCLevel | E22: Decisão de equipa | F22: 0
A23: IRS — categoria B e regras de determinação
A24: Coeficiente do regime simplificado (atividades do art. 151.º) | B24: COEF | C24: 0.75 | D24: Art. 31.º n.º 1 al. b) CIRS — fisioterapeutas constam da tabela do art. 151.º | E24: Validado | F24: 0
A25: Limiar de justificação de despesas | B25: LIM_JUST | C25: 0.15 | D25: Art. 31.º n.º 13 CIRS | E25: Validado | F25: 0
A26: Dedução específica considerada na justificação de despesas | B26: DED_ESP | C26: 4104 | D26: Art. 31.º n.º 13 al. a) CIRS | E26: Confirmar valor em vigor | F26: 0
A27: Contribuições SS — dedutíveis na parte que excede esta % do rendimento bruto | B27: LIM_CONTRIB | C27: 0.1 | D27: Art. 31.º n.º 2 CIRS | E27: Confirmar | F27: 0
A28: Limiar de permanência no regime simplificado (rendimento bruto) | B28: LIM_SIMPL | C28: 200000 | D28: Art. 28.º n.º 2 CIRS | E28: Confirmar | F28: 0
A29: Período mínimo de permanência na opção por contabilidade organizada (anos) | B29: PERM_OPCAO | C29: 3 | D29: Art. 28.º n.º 5 CIRS | E29: Confirmar | F29: 0
A30: Dedução específica da categoria A | B30: DED_CATA | C30: 4104 | D30: Art. 25.º n.º 1 al. a) CIRS | E30: Confirmar valor em vigor | F30: 0
A31: Coeficiente do simplificado aplicável à receita de cedência de espaço | B31: COEF_SALA | C31: 0.35 | D31: Art. 31.º n.º 1 al. c) CIRS — restantes prestações de serviços | E31: CONFIRMAR (ver R1-29). Depende de N1-04 | F31: 1
A32: IRC e tributação da distribuição
A33: IRC — taxa aplicável ao primeiro escalão (PME) | B33: IRC_PME | C33: 0.16 | D33: Art. 87.º n.º 2 CIRC | E33: CONFIRMAR TAXA 2026 (ver R1-11) | F33: 1
A34: IRC — limite da matéria coletável do primeiro escalão | B34: IRC_LIM | C34: 50000 | D34: Art. 87.º n.º 2 CIRC | E34: CONFIRMAR 2026 | F34: 1
A35: IRC — taxa geral | B35: IRC_GER | C35: 0.2 | D35: Art. 87.º n.º 1 CIRC | E35: CONFIRMAR TAXA 2026 (ver R1-11) | F35: 1
A36: Derrama municipal (município do Porto) | B36: DERRAMA | C36: 0.015 | D36: Art. 18.º Lei 73/2013 + deliberação municipal | E36: CONFIRMAR município e isenção PME | F36: 1
A37: Derrama incide sobre sociedade transparente? (1=sim / 0=não) | B37: DERR_TRANSP | C37: 0 | D37: Questão controvertida — art. 12.º CIRC vs. art. 18.º Lei 73/2013 | E37: EM ABERTO (ver R1-13) | F37: 1
A38: Dividendos — taxa liberatória | B38: DIV_LIB | C38: 0.28 | D38: Art. 71.º n.º 1 CIRS | E38: Confirmar | F38: 0
A39: Dividendos — % considerada em caso de englobamento | B39: DIV_ENG | C39: 0.5 | D39: Art. 40.º-A n.º 1 CIRS | E39: Confirmar | F39: 0
A40: IVA
A41: IVA — taxa normal (continente) | B41: IVA_NORM | C41: 0.23 | D41: Art. 18.º n.º 1 al. c) CIVA | E41: Validado | F41: 0
A42: IVA — taxa reduzida (continente) | B42: IVA_RED | C42: 0.06 | D42: Art. 18.º n.º 1 al. a) CIVA + Lista I | E42: Validado | F42: 0
A43: Amortizações (vias com contabilidade)
A44: Taxa de amortização — obras / benfeitorias em imóvel alheio | B44: AM_OBRAS | C44: 0.1 | D44: DR 25/2009 — ou período do contrato de arrendamento, se inferior | E44: CONFIRMAR código aplicável | F44: 1
A45: Taxa de amortização — equipamento clínico | B45: AM_EQUIP | C45: 0.2 | D45: DR 25/2009, tabela II | E45: CONFIRMAR código aplicável | F45: 1
A46: Taxa de amortização — software | B46: AM_SOFT | C46: 0.3333 | D46: DR 25/2009 | E46: CONFIRMAR | F46: 1
A47: Transparência fiscal — limiares do teste (usados na N1, não no cálculo)
A48: % mínima de capital detida por profissionais das atividades do art. 151.º | B48: TF_CAP | C48: 0.75 | D48: Art. 6.º n.º 4 al. b) subal. ii) CIRC | E48: Validado | F48: 0
A49: % mínima de rendimentos provenientes de atividades do art. 151.º | B49: TF_REND | C49: 0.75 | D49: Art. 6.º n.º 4 al. b) subal. ii) CIRC | E49: Validado | F49: 0
A50: N.º máximo de sócios para o teste da subal. ii) | B50: TF_SOCIOS | C50: 5 | D50: Art. 6.º n.º 4 al. b) subal. ii) CIRC | E50: Validado | F50: 0
A52: Escalões de IRS — taxas gerais
A53: Tabela em vigor: 2025 (Lei n.º 33-A/2025). ATUALIZAR para os escalões do OE2026 antes de qualquer número entrar no relatório. A coluna 'Delta' é a mecânica de cálculo (taxa do escalão menos taxa do anterior) e recalcula sozinha.
A54: Escalão | B54: Limite inferior | C54: Limite superior | D54: Taxa | E54: Delta (calculado)
A55: 1 | B55: 0 | C55: 8059 | D55: 0.125 | E55: =D55
A56: 2 | B56: 8059 | C56: 12160 | D56: 0.16 | E56: =D56-D55
A57: 3 | B57: 12160 | C57: 17233 | D57: 0.215 | E57: =D57-D56
A58: 4 | B58: 17233 | C58: 22306 | D58: 0.244 | E58: =D58-D57
A59: 5 | B59: 22306 | C59: 28400 | D59: 0.314 | E59: =D59-D58
A60: 6 | B60: 28400 | C60: 41629 | D60: 0.349 | E60: =D60-D59
A61: 7 | B61: 41629 | C61: 44987 | D61: 0.431 | E61: =D61-D60
A62: 8 | B62: 44987 | C62: 83696 | D62: 0.446 | E62: =D62-D61
A63: 9 | B63: 83696 | C63: sem limite | D63: 0.48 | E63: =D63-D62
A65: Taxa adicional de solidariedade (art. 68.º-A CIRS)
A66: Escalão | B66: Limite inferior | C66: Limite superior | D66: Taxa | E66: Delta (calculado)
A67: 1 | B67: 80000 | C67: 250000 | D67: 0.025 | E67: =D67
A68: 2 | B68: 250000 | C68: sem limite | D68: 0.05 | E68: =D68-D67
A70: Legenda: células a azul sobre fundo amarelo são de preenchimento; tudo o resto é fórmula. Nenhuma taxa deve ser escrita dentro de uma fórmula noutra folha — se faltar um parâmetro, acrescenta-se aqui.

Sheet Operacao
A1: M1 — Camada operacional: capacidade, utilização e faturação
A2: A faturação deixa de ser um palpite e passa a ser uma consequência. Gabinetes, dias de funcionamento, duração da consulta e preço determinam quanto é possível faturar — e a linha de utilização diz se a projeção cabe no espaço. Uma projeção que exija mais de 100% de utilização é impossível, não é otimista.
A4: Rubrica | B4: Ref. | C4: Baixo | D4: Base | E4: Alto | F4: Nota
A5: Espaço e horário
A6: N.º de gabinetes | B6: N_GAB | C6: 2 | D6: 2 | E6: 3 | F6: Input cliente 3 — EM FALTA. Ata, ponto 3: dois espaços em avaliação, 2 e 3 gabinetes. A comparação dedicada está na folha Espaco.
A7: Dias de funcionamento por ano | B7: DIAS_ANO | C7: 220 | D7: 220 | E7: 220 | F7: EM FALTA. 220 dias corresponde a semana de 5 dias com férias e feriados.
A8: Horas úteis por gabinete por dia | B8: HORAS_DIA | C8: 8 | D8: 8 | E8: 8 | F8: EM FALTA.
A9: Duração média da consulta (minutos) | B9: DUR_CONS | C9: 45 | D9: 45 | E9: 45 | F9: EM FALTA. Determina a capacidade. Sessões de 30 ou de 60 minutos mudam tudo o que vem abaixo.
A10: Atividade da Dra. Júlia
A11: Dias por ano em que atende | B11: DIAS_JUL | C11: 190 | D11: 200 | E11: 210 | F11: EM FALTA.
A12: Consultas por dia | B12: CONS_JUL | C12: 5 | D12: 6 | E12: 7 | F12: EM FALTA.
A13: Preço médio por consulta | B13: PRECO_JUL | C13: 45 | D13: 48 | E13: 50 | F13: Input cliente 2 — EM FALTA. Sai da tabela de preços, que a ata regista como inexistente.
A14: Fisioterapeutas a integrar
A15: N.º de fisioterapeutas | B15: N_FISIO | C15: 1 | D15: 1 | E15: 2 | F15: Ata, ponto 3.
A16: Dias por ano, por profissional | B16: DIAS_FIS | C16: 160 | D16: 180 | E16: 180 | F16: EM FALTA.
A17: Consultas por dia, por profissional | B17: CONS_FIS | C17: 4 | D17: 5 | E17: 4 | F17: EM FALTA.
A18: Preço médio por consulta | B18: PRECO_FIS | C18: 45 | D18: 48 | E18: 50 | F18: EM FALTA.
A19: Capacidade
A20: Capacidade diária por gabinete (consultas) | B20: CAP_DIA | C20: =$C$8*60/$C$9 | D20: =$D$8*60/$D$9 | E20: =$E$8*60/$E$9
A21: Capacidade anual instalada (consultas) | B21: CAP_ANO | C21: =$C$6*$C$7*$C$20 | D21: =$D$6*$D$7*$D$20 | E21: =$E$6*$E$7*$E$20
A22: Procura projetada
A23: Consultas anuais da Dra. Júlia | B23: CONS_JUL_A | C23: =$C$11*$C$12 | D23: =$D$11*$D$12 | E23: =$E$11*$E$12
A24: Consultas anuais dos colaboradores | B24: CONS_FIS_A | C24: =$C$15*$C$16*$C$17 | D24: =$D$15*$D$16*$D$17 | E24: =$E$15*$E$16*$E$17
A25: Consultas anuais totais | B25: CONS_TOT | C25: =$C$23+$C$24 | D25: =$D$23+$D$24 | E25: =$E$23+$E$24
A26: TAXA DE UTILIZAÇÃO DOS GABINETES | B26: UTILIZ | C26: =IF($C$21<=0,0,$C$25/$C$21) | D26: =IF($D$21<=0,0,$D$25/$D$21) | E26: =IF($E$21<=0,0,$E$25/$E$21) | F26: Acima de 100% a projeção é impossível: não há gabinetes para as consultas previstas. Acima de 85% é operacionalmente muito exigente. Ver folha Alertas.
A27: Leitura da utilização | B27: TESTE_CAP | C27: =IF($C$26>Parametros!$C$20,"IMPOSSÍVEL — a projeção não cabe no espaço",IF($C$26>Parametros!$C$21,"MUITO EXIGENTE — pouca folga operacional",IF($C$26<Parametros!$C$22,"FOLGA ELEVADA — capacidade subaproveitada","PLAUSÍVEL"))) | D27: =IF($D$26>Parametros!$C$20,"IMPOSSÍVEL — a projeção não cabe no espaço",IF($D$26>Parametros!$C$21,"MUITO EXIGENTE — pouca folga operacional",IF($D$26<Parametros!$C$22,"FOLGA ELEVADA — capacidade subaproveitada","PLAUSÍVEL"))) | E27: =IF($E$26>Parametros!$C$20,"IMPOSSÍVEL — a projeção não cabe no espaço",IF($E$26>Parametros!$C$21,"MUITO EXIGENTE — pouca folga operacional",IF($E$26<Parametros!$C$22,"FOLGA ELEVADA — capacidade subaproveitada","PLAUSÍVEL")))
A28: Faturação derivada
A29: Faturação anual da Dra. Júlia | B29: FAT_JUL | C29: =$C$23*$C$13 | D29: =$D$23*$D$13 | E29: =$E$23*$E$13
A30: Faturação anual gerada pelos colaboradores | B30: FAT_FIS | C30: =$C$24*$C$18 | D30: =$D$24*$D$18 | E30: =$E$24*$E$18
A31: Faturação anual total gerada | B31: FAT_TOT | C31: =$C$29+$C$30 | D31: =$D$29+$D$30 | E31: =$E$29+$E$30
A32: Unit economics
A33: Faturação por gabinete | B33: FAT_GAB | C33: =IF($C$6<=0,0,$C$31/$C$6) | D33: =IF($D$6<=0,0,$D$31/$D$6) | E33: =IF($E$6<=0,0,$E$31/$E$6)
A34: Consultas por gabinete | B34: CONS_GAB | C34: =IF($C$6<=0,0,$C$25/$C$6) | D34: =IF($D$6<=0,0,$D$25/$D$6) | E34: =IF($E$6<=0,0,$E$25/$E$6)
A35: Faturação por profissional | B35: FAT_PROF | C35: =$C$31/(1+$C$15) | D35: =$D$31/(1+$D$15) | E35: =$E$31/(1+$E$15)
A36: Faturação por hora de gabinete disponível | B36: FAT_HORA | C36: =IF($C$6*$C$7*$C$8<=0,0,$C$31/($C$6*$C$7*$C$8)) | D36: =IF($D$6*$D$7*$D$8<=0,0,$D$31/($D$6*$D$7*$D$8)) | E36: =IF($E$6*$E$7*$E$8<=0,0,$E$31/($E$6*$E$7*$E$8)) | F36: Indicador de eficiência do espaço, independente da estrutura fiscal.

Sheet Inputs
A1: M1 — Inputs (folha única de parâmetros do caso)
A2: ATENÇÃO: à data de 22/08/2026 a cliente não forneceu nenhum dos inputs da secção 4 do brief. Todos os valores abaixo são ILUSTRATIVOS, servem apenas para testar o motor de cálculo, e estão registados como pressupostos em R1. Nenhum número desta folha pode transitar para o relatório enquanto não for substituído por dados da cliente.
A4: Input | B4: Referência | C4: Baixo | D4: Base | E4: Alto | F4: Nota / origem | G4: Tipo | H4: Fonte | I4: Confiança
A5: Faturação — origem e modelo de colaboração
A6: ORIGEM DA FATURAÇÃO: 1 = valores manuais · 2 = derivada da capacidade (folha Operacao) | B6: FONTE_FAT | C6: 2 | D6: 2 | E6: 2 | F6: ALAVANCA. Em 2, a faturação é uma consequência de gabinetes, dias, duração e preço, e é verificável contra a capacidade instalada. Em 1, é um número que alguém escreveu. | G6: ESTIMATIVA_VCLEVEL | H6: VCLevel | I6: Alta | J6: 0
A7: Faturação anual da Dra. Júlia — valor manual | B7: FAT_PROP_MAN | C7: 52000 | D7: 65000 | E7: 85000 | F7: Só usado se FONTE_FAT = 1. | G7: A_VALIDAR | H7: cliente | I7: Baixa | J7: 1
A8: Faturação dos colaboradores — valor manual | B8: FAT_COLAB_MAN | C8: 18000 | D8: 30000 | E8: 45000 | F8: Só usado se FONTE_FAT = 1. | G8: A_VALIDAR | H8: cliente | I8: Baixa | J8: 1
A9: Faturação anual da própria Dra. Júlia (isenta, art. 9.º CIVA) | B9: FAT_PROP | C9: =IF(Inputs!$C$6=1,Inputs!$C$7,Operacao!$C$29) | D9: =IF(Inputs!$D$6=1,Inputs!$D$7,Operacao!$D$29) | E9: =IF(Inputs!$E$6=1,Inputs!$E$7,Operacao!$E$29) | F9: Doentes próprios, independentemente do modelo de colaboração. | G9: DERIVADO | H9: modelo | I9: n/a | J9: 0
A10: Faturação anual gerada pelos fisioterapeutas a integrar | B10: FAT_COLAB | C10: =IF(Inputs!$C$6=1,Inputs!$C$8,Operacao!$C$30) | D10: =IF(Inputs!$D$6=1,Inputs!$D$8,Operacao!$D$30) | E10: =IF(Inputs!$E$6=1,Inputs!$E$8,Operacao!$E$30) | F10: No modelo 1 é faturada pela clínica; no modelo 2 é faturada diretamente pelos profissionais e nunca passa pela clínica. | G10: DERIVADO | H10: modelo | I10: n/a | J10: 0
A11: MODELO DE COLABORAÇÃO: 1 = prestação de serviços · 2 = cedência de sala | B11: MOD_COLAB | C11: 1 | D11: 1 | E11: 1 | F11: ALAVANCA. Ata, ponto 4. Alterna toda a estrutura de receita e custo. Sustenta a exposição E2.6. AVISO: a qualificação jurídica e fiscal depende da configuração contratual e operacional concreta, não do nome comercial do modelo. Ver N1-04 e R1-31. | G11: A_VALIDAR | H11: cliente | I11: Baixa | J11: 1
A12: Modelo 1 — honorários em % da faturação que o colaborador gera | B12: PCT_HONOR | C12: 0.7 | D12: 0.7 | E12: 0.7 | F12: Input cliente 5 — EM FALTA. Variável de sensibilidade: é o que separa faturação de margem. | G12: A_VALIDAR | H12: cliente | I12: Baixa | J12: 1
A13: Modelo 1 — honorários anuais a pagar aos fisioterapeutas | B13: HONOR | C13: =Inputs!$C$10*Inputs!$C$12 | D13: =Inputs!$D$10*Inputs!$D$12 | E13: =Inputs!$E$10*Inputs!$E$12 | F13: Ignorado no modelo 2. | G13: DERIVADO | H13: modelo | I13: n/a | J13: 0
A14: Modelo 2 — renda em % da faturação que o colaborador gera | B14: PCT_SALA | C14: 0.3 | D14: 0.3 | E14: 0.3 | F14: Input cliente 5 — EM FALTA. Se a renda for fixa e não percentual, introduzir o valor equivalente. | G14: A_VALIDAR | H14: cliente | I14: Baixa | J14: 1
A15: Modelo 2 — receita anual de cedência de sala | B15: REC_SALA | C15: =Inputs!$C$10*Inputs!$C$14 | D15: =Inputs!$D$10*Inputs!$D$14 | E15: =Inputs!$E$10*Inputs!$E$14 | F15: Ignorado no modelo 1. | G15: DERIVADO | H15: modelo | I15: n/a | J15: 0
A16: Cedência de sala sujeita a IVA? (1 = sim / 0 = arrendamento isento) | B16: SALA_TRIB | C16: 0 | D16: 0 | E16: 0 | F16: Depende de N1-04: arrendamento isento (art. 9.º n.º 29 CIVA) ou prestação de serviços com disponibilização de meios, tributada. Não está resolvido. | G16: A_VALIDAR | H16: legislação | I16: Baixa | J16: 1
A17: Faturação anual sujeita a IVA dentro da sociedade (atividade do cônjuge) | B17: FAT_TRIB | C17: 0 | D17: 0 | E17: 0 | F17: Input cliente 6 — EM FALTA. Só relevante na via 4 e no cenário de sujeito passivo misto. | G17: A_VALIDAR | H17: cliente | I17: Baixa | J17: 1
A18: Custos operacionais anuais
A19: Renda do espaço | B19: RENDA | C19: 12000 | D19: 14400 | E19: 18000 | F19: Input cliente 3 — EM FALTA. Baixo/Base = 2 gabinetes; Alto = 3 gabinetes. | G19: A_VALIDAR | H19: contrato | I19: Baixa | J19: 1
A20: Condomínio e encargos do espaço | B20: CONDOM | C20: 1200 | D20: 1500 | E20: 1800 | F20: Input cliente 3 — EM FALTA. | G20: A_VALIDAR | H20: contrato | I20: Baixa | J20: 1
A21: Seguros (RC profissional, multirriscos) | B21: SEGUROS | C21: 900 | D21: 1100 | E21: 1400 | F21: EM FALTA. | G21: ESTIMATIVA_VCLEVEL | H21: VCLevel | I21: Baixa | J21: 0
A22: Software de gestão e faturação | B22: SOFTW | C22: 600 | D22: 900 | E22: 1200 | F22: EM FALTA. | G22: ESTIMATIVA_VCLEVEL | H22: VCLevel | I22: Baixa | J22: 0
A23: Consumíveis clínicos, em % da faturação da estrutura | B23: PCT_CONSUM | C23: 0.03 | D23: 0.03 | E23: 0.03 | F23: EM FALTA. Modelado como custo variável, o que é necessário para o break-even operacional. | G23: ESTIMATIVA_VCLEVEL | H23: benchmark | I23: Média | J23: 0
A24: Consumíveis clínicos | B24: CONSUM | C24: =(Inputs!$C$9+IF(Inputs!$C$11=1,Inputs!$C$10,0))*Inputs!$C$23 | D24: =(Inputs!$D$9+IF(Inputs!$D$11=1,Inputs!$D$10,0))*Inputs!$D$23 | E24: =(Inputs!$E$9+IF(Inputs!$E$11=1,Inputs!$E$10,0))*Inputs!$E$23 | F24: Custo variável: acompanha as consultas realizadas dentro da estrutura. | G24: DERIVADO | H24: modelo | I24: n/a | J24: 0
A25: Outros custos operacionais | B25: OUTROS | C25: 1500 | D25: 2000 | E25: 2500 | F25: EM FALTA. | G25: ESTIMATIVA_VCLEVEL | H25: VCLevel | I25: Baixa | J25: 0
A26: Investimento inicial (valores sem IVA)
A27: Obras e adaptação do espaço | B27: INV_OBRAS | C27: 15000 | D27: 25000 | E27: 40000 | F27: Input cliente 4 — EM FALTA. | G27: A_VALIDAR | H27: orçamento | I27: Baixa | J27: 1
A28: Equipamento clínico à taxa normal | B28: INV_EQUIP | C28: 12000 | D28: 20000 | E28: 30000 | F28: Input cliente 4 — EM FALTA. | G28: A_VALIDAR | H28: orçamento | I28: Baixa | J28: 1
A29: Equipamento clínico elegível para taxa reduzida | B29: INV_EQUIP_R | C29: 0 | D29: 0 | E29: 0 | F29: A confirmar contra as verbas 2.5 e 2.6 da Lista I do CIVA. Se houver elegibilidade, reduz a base do problema de IVA. | G29: A_VALIDAR | H29: legislação | I29: Baixa | J29: 1
A30: Software e sistemas | B30: INV_SOFT | C30: 1500 | D30: 2000 | E30: 3000 | F30: EM FALTA. | G30: A_VALIDAR | H30: orçamento | I30: Baixa | J30: 1
A31: Vias societárias (3 e 4)
A32: Remuneração anual bruta de gerência | B32: REM_GER | C32: 14000 | D32: 16800 | E32: 20000 | F32: Variável de decisão, não dado da cliente. Testar sensibilidade. | G32: ESTIMATIVA_VCLEVEL | H32: VCLevel | I32: Média | J32: 0
A33: Tributações autónomas estimadas (anual) | B33: TA_EST | C33: 500 | D33: 800 | E33: 1200 | F33: A quantificar pela Fiscalidade em função de viatura e despesas de representação. | G33: ESTIMATIVA_VCLEVEL | H33: VCLevel | I33: Baixa | J33: 0
A34: Política de distribuição de resultados (% do lucro após imposto) | B34: POL_DIST | C34: 1 | D34: 1 | E34: 1 | F34: ALAVANCA. Testar 0% / 50% / 100% — é aqui que se decide se afastar a transparência compensa. | G34: A_VALIDAR | H34: cliente | I34: Baixa | J34: 1
A35: % do capital social detida pelo cônjuge | B35: PCT_CONJ | C35: 0.26 | D35: 0.26 | E35: 0.26 | F35: Só via 4. Tem de exceder 25% para afastar o teste de capital do art. 6.º n.º 4 al. b) ii) CIRC. Ver N1. | G35: ESTIMATIVA_VCLEVEL | H35: VCLevel | I35: Média | J35: 0
A36: Agregado familiar (IRS)
A37: Rendimento anual do cônjuge fora da estrutura (líquido de deduções específicas) | B37: REND_CONJ | C37: 14000 | D37: 18000 | E37: 22000 | F37: Input cliente 6 e 7 — EM FALTA. | G37: A_VALIDAR | H37: cliente | I37: Baixa | J37: 1
A38: Opção por tributação conjunta (1 = sim / 0 = não) | B38: CONJUNTA | C38: 1 | D38: 1 | E38: 1 | F38: Input cliente 7 — EM FALTA. | G38: A_VALIDAR | H38: cliente | I38: Baixa | J38: 1
A39: N.º de dependentes | B39: N_DEP | C39: 0 | D39: 0 | E39: 0 | F39: Input cliente 7 — EM FALTA. | G39: A_VALIDAR | H39: cliente | I39: Baixa | J39: 1
A40: Deduções à coleta estimadas do agregado | B40: DED_COL | C40: 500 | D40: 500 | E40: 500 | F40: EM FALTA. Não afeta a comparação entre vias (cancela-se no diferencial), afeta o IRS total. | G40: ESTIMATIVA_VCLEVEL | H40: VCLevel | I40: Baixa | J40: 0
A41: Derivadas — não preencher, calculam-se a partir do modelo de colaboração
A42: Faturação isenta faturada pela estrutura | B42: FAT_ISENTA | C42: =Inputs!$C$9+IF(Inputs!$C$11=1,Inputs!$C$10,0) | D42: =Inputs!$D$9+IF(Inputs!$D$11=1,Inputs!$D$10,0) | E42: =Inputs!$E$9+IF(Inputs!$E$11=1,Inputs!$E$10,0) | F42: No modelo 1 a clínica fatura ao doente a totalidade; no modelo 2 fatura apenas os doentes próprios.
A43: Receita de cedência de espaço | B43: REC_NAOPROF | C43: =IF(Inputs!$C$11=2,Inputs!$C$15,0) | D43: =IF(Inputs!$D$11=2,Inputs!$D$15,0) | E43: =IF(Inputs!$E$11=2,Inputs!$E$15,0) | F43: Rendimento que NÃO provém de atividade da lista do art. 151.º CIRS. Ver linha PCT_PROF.
A44: Custo com os colaboradores | B44: CUSTO_COLAB | C44: =IF(Inputs!$C$11=1,Inputs!$C$13,0) | D44: =IF(Inputs!$D$11=1,Inputs!$D$13,0) | E44: =IF(Inputs!$E$11=1,Inputs!$E$13,0)
A45: MARGEM GERADA PELOS COLABORADORES | B45: MARGEM_COLAB | C45: =IF(Inputs!$C$11=1,Inputs!$C$10-Inputs!$C$13,Inputs!$C$15) | D45: =IF(Inputs!$D$11=1,Inputs!$D$10-Inputs!$D$13,Inputs!$D$15) | E45: =IF(Inputs!$E$11=1,Inputs!$E$10-Inputs!$E$13,Inputs!$E$15) | F45: Exposição E2.6. É a resposta à pergunta da ata: qual dos dois modelos deixa mais margem. Alternar MOD_COLAB entre 1 e 2 e comparar esta linha.
A46: Receita total da estrutura (incl. cônjuge, se aplicável) | B46: REC_TOTAL | C46: =Inputs!$C$42+Inputs!$C$43+Inputs!$C$17 | D46: =Inputs!$D$42+Inputs!$D$43+Inputs!$D$17 | E46: =Inputs!$E$42+Inputs!$E$43+Inputs!$E$17
A47: Receita sujeita a IVA (base do pro rata) | B47: REC_TRIB | C47: =Inputs!$C$17+IF(Inputs!$C$16=1,Inputs!$C$43,0) | D47: =Inputs!$D$17+IF(Inputs!$D$16=1,Inputs!$D$43,0) | E47: =Inputs!$E$17+IF(Inputs!$E$16=1,Inputs!$E$43,0) | F47: Depende de N1-04: se a cedência for arrendamento isento, não entra.
A48: % de rendimentos provenientes de atividades da lista do art. 151.º CIRS | B48: PCT_PROF | C48: =IF(Inputs!$C$46<=0,0,Inputs!$C$42/Inputs!$C$46) | D48: =IF(Inputs!$D$46<=0,0,Inputs!$D$42/Inputs!$D$46) | E48: =IF(Inputs!$E$46<=0,0,Inputs!$E$42/Inputs!$E$46) | F48: Teste de rendimentos do art. 6.º n.º 4 al. b) ii) CIRC. Pressupõe que nem a cedência de espaço nem a atividade do cônjuge constam da lista — o segundo ponto é o R1-14, por verificar.
A49: Receita de cedência necessária para FALHAR o teste de rendimentos | B49: REC_SALA_MIN | C49: =Inputs!$C$42*(1-Parametros!$C$49)/Parametros!$C$49 | D49: =Inputs!$D$42*(1-Parametros!$C$49)/Parametros!$C$49 | E49: =Inputs!$E$42*(1-Parametros!$C$49)/Parametros!$C$49 | F49: Álgebra do teste: para os rendimentos profissionais descerem a 75% ou menos, a receita não profissional tem de atingir um terço da faturação profissional. Comparar com a linha REC_NAOPROF antes de propor esta via em N1, secção 5.
A50: Teste de rendimentos do art. 6.º n.º 4 al. b) ii) CIRC | B50: TESTE_TF | C50: =IF(Inputs!$C$48>Parametros!$C$49,"VERIFICADO — transparência não é afastada por esta via","FALHADO — transparência afastada pelo critério de rendimentos") | D50: =IF(Inputs!$D$48>Parametros!$C$49,"VERIFICADO — transparência não é afastada por esta via","FALHADO — transparência afastada pelo critério de rendimentos") | E50: =IF(Inputs!$E$48>Parametros!$C$49,"VERIFICADO — transparência não é afastada por esta via","FALHADO — transparência afastada pelo critério de rendimentos") | F50: N1, secção 5. Falhar este teste afasta o regime sem ceder um único euro de capital ao cônjuge.
A52: Exemplo de preenchimento correto — linha ilustrativa
A53: Faturação anual da própria Dra. Júlia | C53: 52000 | D53: 65000 | E53: 85000 | F53: Formato esperado: valor anual, em euros, sem IVA, número puro sem texto.

Sheet V1_ENI_Simplificado
A1: Via 1 — ENI, regime simplificado (situação atual)
A2: Enquadramento atual da cliente (ata, ponto 2). O ponto em teste é o do art. 31.º n.º 13 CIRS: com custos reais elevados, o coeficiente deixa de cobrir as despesas e ainda há acréscimo por insuficiência de justificação.
A4: Rubrica | B4: Ref. | C4: Baixo | D4: Base | E4: Alto | F4: Nota / norma
A5: Categoria B — regime simplificado
A6: Faturação isenta (fisioterapia) | B6: FAT | C6: =Inputs!$C$42 | D6: =Inputs!$D$42 | E6: =Inputs!$E$42
A7: Receita de cedência de espaço | B7: REC_S | C7: =Inputs!$C$43 | D7: =Inputs!$D$43 | E7: =Inputs!$E$43 | F7: Zero no modelo de prestação de serviços. Ver a alavanca MOD_COLAB na folha Inputs.
A8: Rendimento bruto total da categoria B | B8: RB_TOT | C8: =$C$6+$C$7 | D8: =$D$6+$D$7 | E8: =$E$6+$E$7
A9: Coeficiente aplicável à fisioterapia | B9: COEF | C9: =Parametros!$C$24 | D9: =Parametros!$C$24 | E9: =Parametros!$C$24 | F9: Art. 31.º n.º 1 al. b) CIRS. Fisioterapeutas constam da tabela do art. 151.º — o coeficiente 0,35 não é aplicável a esta parcela.
A10: Coeficiente aplicável à cedência de espaço | B10: COEF_S | C10: =Parametros!$C$31 | D10: =Parametros!$C$31 | E10: =Parametros!$C$31 | F10: Coeficiente distinto, e por confirmar (R1-29). Depende de a cedência ser qualificada como prestação de serviços ou como rendimento predial — N1-04.
A11: Rendimento tributável pelos coeficientes | B11: RT_COEF | C11: =$C$6*$C$9+$C$7*$C$10 | D11: =$D$6*$D$9+$D$7*$D$10 | E11: =$E$6*$E$9+$E$7*$E$10
A12: Limiar de justificação de despesas (15% do rendimento bruto) | B12: LIMIAR | C12: =$C$8*Parametros!$C$25 | D12: =$D$8*Parametros!$C$25 | E12: =$E$8*Parametros!$C$25 | F12: Art. 31.º n.º 13 CIRS.
A13: Despesas justificáveis — dedução específica | B13: D_ESP | C13: =Parametros!$C$26 | D13: =Parametros!$C$26 | E13: =Parametros!$C$26
A14: Despesas justificáveis — rendas do imóvel afeto | B14: D_RENDA | C14: =Inputs!$C$19 | D14: =Inputs!$D$19 | E14: =Inputs!$E$19 | F14: Art. 31.º n.º 13 al. c) CIRS.
A15: Despesas justificáveis — aquisição de bens e serviços | B15: D_BENS | C15: =Inputs!$C$20+Inputs!$C$21+Inputs!$C$22+Inputs!$C$24+Inputs!$C$25+Inputs!$C$44 | D15: =Inputs!$D$20+Inputs!$D$21+Inputs!$D$22+Inputs!$D$24+Inputs!$D$25+Inputs!$D$44 | E15: =Inputs!$E$20+Inputs!$E$21+Inputs!$E$22+Inputs!$E$24+Inputs!$E$25+Inputs!$E$44 | F15: Art. 31.º n.º 13 al. e) CIRS. Inclui os honorários, quando o modelo de colaboração for o de prestação de serviços.
A16: Despesas justificáveis — aquisições de investimento do ano | B16: D_INV | C16: =Inputs!$C$27+Inputs!$C$28+Inputs!$C$29+Inputs!$C$30 | D16: =Inputs!$D$27+Inputs!$D$28+Inputs!$D$29+Inputs!$D$30 | E16: =Inputs!$E$27+Inputs!$E$28+Inputs!$E$29+Inputs!$E$30 | F16: A CONFIRMAR pela Fiscalidade: elegibilidade e grau de afetação das aquisições de investimento para efeitos do art. 31.º n.º 13 al. e). Efeito de ano 1 apenas. Ver R1-08.
A17: Total de despesas justificadas | B17: D_TOT | C17: =SUM($C$13:$C$16) | D17: =SUM($D$13:$D$16) | E17: =SUM($E$13:$E$16)
A18: Acréscimo por insuficiência de justificação | B18: ACRESC | C18: =MAX(0,$C$12-$C$17) | D18: =MAX(0,$D$12-$D$17) | E18: =MAX(0,$E$12-$E$17) | F18: Art. 31.º n.º 13 CIRS: acresce ao rendimento tributável a diferença positiva.
A19: Rendimento da categoria B antes da dedução de contribuições | B19: RB_CATB | C19: =$C$11+$C$18 | D19: =$D$11+$D$18 | E19: =$E$11+$E$18
A20: Segurança Social — trabalhador independente
A21: Rendimento relevante | B21: SS_REL | C21: =$C$8*Parametros!$C$7 | D21: =$D$8*Parametros!$C$7 | E21: =$E$8*Parametros!$C$7 | F21: Art. 162.º Cód. Contributivo: 70% do valor das prestações de serviços. A inclusão da receita de cedência de espaço depende de esta ser qualificada como prestação de serviços — N1-04.
A22: Base de incidência anual, limitada ao teto | B22: SS_BASE | C22: =MIN($C$21,Parametros!$C$6*Parametros!$C$9*12) | D22: =MIN($D$21,Parametros!$C$6*Parametros!$C$9*12) | E22: =MIN($E$21,Parametros!$C$6*Parametros!$C$9*12) | F22: Teto mensal de 12 x IAS.
A23: Contribuição anual para a Segurança Social | B23: SS_CONTR | C23: =MAX($C$22*Parametros!$C$8,Parametros!$C$10*12) | D23: =MAX($D$22*Parametros!$C$8,Parametros!$C$10*12) | E23: =MAX($E$22*Parametros!$C$8,Parametros!$C$10*12) | F23: Bloco ausente da ata. Na via 1 a base é a faturação bruta, não a margem — é aqui que está o maior diferencial entre as vias.
A24: Parte dedutível em IRS | B24: SS_DED | C24: =MAX(0,$C$23-$C$8*Parametros!$C$27) | D24: =MAX(0,$D$23-$D$8*Parametros!$C$27) | E24: =MAX(0,$E$23-$E$8*Parametros!$C$27) | F24: Art. 31.º n.º 2 CIRS: dedutível apenas na parte que excede 10% do rendimento bruto.
A25: Rendimento líquido da categoria B | B25: RL_CATB | C25: =$C$19-$C$24 | D25: =$D$19-$D$24 | E25: =$E$19-$E$24
A26: IRS do agregado
A27: Rendimento da sócia sujeito a englobamento | B27: R_JUL | C27: =$C$25 | D27: =$D$25 | E27: =$E$25 | F27: Só categoria B. Não há remuneração de gerência nesta via.
A28: Rendimento do cônjuge fora da estrutura | B28: R_CONJ | C28: =Inputs!$C$37 | D28: =Inputs!$D$37 | E28: =Inputs!$E$37
A29: Rendimento coletável do agregado — com a atividade | B29: RC_COM | C29: =$C$27+$C$28 | D29: =$D$27+$D$28 | E29: =$E$27+$E$28
A30: Rendimento coletável do agregado — sem a atividade | B30: RC_SEM | C30: =$C$28 | D30: =$D$28 | E30: =$E$28 | F30: Contrafactual. O diferencial entre as duas coletas é o IRS realmente imputável à atividade e é o que torna as quatro vias comparáveis.
A31: Fator do quociente conjugal | B31: FATOR | C31: =IF(Inputs!$C$38=1,2,1) | D31: =IF(Inputs!$D$38=1,2,1) | E31: =IF(Inputs!$E$38=1,2,1) | F31: Art. 69.º CIRS. Isolado numa linha para que as fórmulas de coleta caibam num ecrã.
A32: Rendimento coletável ajustado ao quociente — com a atividade | B32: RCQ_COM | C32: =$C$29/$C$31 | D32: =$D$29/$D$31 | E32: =$E$29/$E$31
A33: Rendimento coletável ajustado ao quociente — sem a atividade | B33: RCQ_SEM | C33: =$C$30/$C$31 | D33: =$D$30/$D$31 | E33: =$E$30/$E$31
A34: Coleta com a atividade (incl. taxa adicional de solidariedade) | B34: COL_COM | C34: =$C$31*(SUMPRODUCT(($C$32>Parametros!$B$55:$B$63)*($C$32-Parametros!$B$55:$B$63)*Parametros!$E$55:$E$63)+SUMPRODUCT(($C$32>Parametros!$B$67:$B$68)*($C$32-Parametros!$B$67:$B$68)*Parametros!$E$67:$E$68)) | D34: =$D$31*(SUMPRODUCT(($D$32>Parametros!$B$55:$B$63)*($D$32-Parametros!$B$55:$B$63)*Parametros!$E$55:$E$63)+SUMPRODUCT(($D$32>Parametros!$B$67:$B$68)*($D$32-Parametros!$B$67:$B$68)*Parametros!$E$67:$E$68)) | E34: =$E$31*(SUMPRODUCT(($E$32>Parametros!$B$55:$B$63)*($E$32-Parametros!$B$55:$B$63)*Parametros!$E$55:$E$63)+SUMPRODUCT(($E$32>Parametros!$B$67:$B$68)*($E$32-Parametros!$B$67:$B$68)*Parametros!$E$67:$E$68)) | F34: Escalões na folha Parâmetros. Art. 68.º, 68.º-A e 69.º CIRS.
A35: Coleta sem a atividade | B35: COL_SEM | C35: =$C$31*(SUMPRODUCT(($C$33>Parametros!$B$55:$B$63)*($C$33-Parametros!$B$55:$B$63)*Parametros!$E$55:$E$63)+SUMPRODUCT(($C$33>Parametros!$B$67:$B$68)*($C$33-Parametros!$B$67:$B$68)*Parametros!$E$67:$E$68)) | D35: =$D$31*(SUMPRODUCT(($D$33>Parametros!$B$55:$B$63)*($D$33-Parametros!$B$55:$B$63)*Parametros!$E$55:$E$63)+SUMPRODUCT(($D$33>Parametros!$B$67:$B$68)*($D$33-Parametros!$B$67:$B$68)*Parametros!$E$67:$E$68)) | E35: =$E$31*(SUMPRODUCT(($E$33>Parametros!$B$55:$B$63)*($E$33-Parametros!$B$55:$B$63)*Parametros!$E$55:$E$63)+SUMPRODUCT(($E$33>Parametros!$B$67:$B$68)*($E$33-Parametros!$B$67:$B$68)*Parametros!$E$67:$E$68))
A36: IRS imputável à atividade | B36: IRS_ATIV | C36: =$C$34-$C$35 | D36: =$D$34-$D$35 | E36: =$E$34-$E$35
A37: IRS total do agregado, após deduções à coleta (memória) | B37: IRS_TOT | C37: =MAX(0,$C$34-Inputs!$C$40) | D37: =MAX(0,$D$34-Inputs!$D$40) | E37: =MAX(0,$E$34-Inputs!$E$40) | F37: Não entra na comparação entre vias; serve para o enquadramento do capítulo 3.
A38: Resultado
A39: Caixa gerada pela atividade, antes de impostos e contribuições | B39: CAIXA | C39: =Inputs!$C$42+Inputs!$C$43+Inputs!$C$17-(Inputs!$C$19+Inputs!$C$20+Inputs!$C$21+Inputs!$C$22+Inputs!$C$24+Inputs!$C$25+Inputs!$C$44) | D39: =Inputs!$D$42+Inputs!$D$43+Inputs!$D$17-(Inputs!$D$19+Inputs!$D$20+Inputs!$D$21+Inputs!$D$22+Inputs!$D$24+Inputs!$D$25+Inputs!$D$44) | E39: =Inputs!$E$42+Inputs!$E$43+Inputs!$E$17-(Inputs!$E$19+Inputs!$E$20+Inputs!$E$21+Inputs!$E$22+Inputs!$E$24+Inputs!$E$25+Inputs!$E$44) | F39: Caixa gerada pela atividade, igual nas quatro vias por construção. Exclui o investimento inicial, que é um efeito de ano 1 e está isolado na folha IVA e na linha própria abaixo.
A40: Total de impostos e contribuições | B40: CARGA | C40: =$C$36+$C$23 | D40: =$D$36+$D$23 | E40: =$E$36+$E$23 | F40: IRS imputável à atividade + contribuições para a Segurança Social.
A41: Taxa de esforço efetiva sobre a caixa gerada | B41: TAXA_EF | C41: =IF($C$39<=0,0,$C$40/$C$39) | D41: =IF($D$39<=0,0,$D$40/$D$39) | E41: =IF($E$39<=0,0,$E$40/$E$39)
A42: Valor retido na sociedade (não disponibilizado à sócia) | B42: RETIDO | C42: =0 | D42: =0 | E42: =0
A43: Valor atribuído ao cônjuge por via de dividendos, líquido | B43: LIQ_CJ | C43: =0 | D43: =0 | E43: =0 | F43: Só via 4. É uma transferência real de rendimento dentro do agregado e tem de ser explicitada — não é indiferente à sócia.
A44: LÍQUIDO DISPONÍVEL PARA A SÓCIA | B44: LIQ_SOC | C44: =$C$39-$C$40-$C$42-$C$43 | D44: =$D$39-$D$40-$D$42-$D$43 | E44: =$E$39-$E$40-$E$42-$E$43
A45: LÍQUIDO DISPONÍVEL PARA O AGREGADO | B45: LIQ_AGR | C45: =$C$44+$C$43 | D45: =$D$44+$D$43 | E45: =$E$44+$E$43
A46: Memória — investimento e IVA não dedutível suportados no ano 1 | B46: INV_A1 | C46: =Inputs!$C$27+Inputs!$C$28+Inputs!$C$29+Inputs!$C$30 | D46: =Inputs!$D$27+Inputs!$D$28+Inputs!$D$29+Inputs!$D$30 | E46: =Inputs!$E$27+Inputs!$E$28+Inputs!$E$29+Inputs!$E$30 | F46: Excluído da comparação anual acima. Quantificação do IVA na folha IVA.

Sheet V2_ENI_ContOrg
A1: Via 2 — ENI com opção por contabilidade organizada
A2: Mantém o ENI e passa a deduzir os custos efetivos. Duas consequências que a ata não quantificou: a base de incidência da Segurança Social deixa de ser 70% da faturação e passa a ser o lucro tributável, e a opção vincula por 3 anos.
A4: Rubrica | B4: Ref. | C4: Baixo | D4: Base | E4: Alto | F4: Nota / norma
A5: Apuramento do lucro tributável
A6: Receita bruta (fisioterapia + cedência de espaço) | B6: FAT | C6: =Inputs!$C$42+Inputs!$C$43 | D6: =Inputs!$D$42+Inputs!$D$43 | E6: =Inputs!$E$42+Inputs!$E$43
A7: Custos operacionais dedutíveis (excl. honorários) | B7: C_OP | C7: =Inputs!$C$19+Inputs!$C$20+Inputs!$C$21+Inputs!$C$22+Inputs!$C$24+Inputs!$C$25 | D7: =Inputs!$D$19+Inputs!$D$20+Inputs!$D$21+Inputs!$D$22+Inputs!$D$24+Inputs!$D$25 | E7: =Inputs!$E$19+Inputs!$E$20+Inputs!$E$21+Inputs!$E$22+Inputs!$E$24+Inputs!$E$25
A8: Custo com os colaboradores | B8: C_HON | C8: =Inputs!$C$44 | D8: =Inputs!$D$44 | E8: =Inputs!$E$44 | F8: Dedutíveis como custo da atividade (ata, ponto 4). Sujeitos ao risco de requalificação tratado na fase 2 do P1.
A9: Amortizações do exercício | B9: AMORT | C9: =Inputs!$C$27*Parametros!$C$44+(Inputs!$C$28+Inputs!$C$29)*Parametros!$C$45+Inputs!$C$30*Parametros!$C$46 | D9: =Inputs!$D$27*Parametros!$C$44+(Inputs!$D$28+Inputs!$D$29)*Parametros!$C$45+Inputs!$D$30*Parametros!$C$46 | E9: =Inputs!$E$27*Parametros!$C$44+(Inputs!$E$28+Inputs!$E$29)*Parametros!$C$45+Inputs!$E$30*Parametros!$C$46 | F9: Taxas na folha Parâmetros. Obras em imóvel alheio: confirmar se o período do contrato de arrendamento é inferior ao decorrente da taxa.
A10: Lucro tributável antes de contribuições | B10: LT_ANTES | C10: =$C$6-$C$7-$C$8-$C$9 | D10: =$D$6-$D$7-$D$8-$D$9 | E10: =$E$6-$E$7-$E$8-$E$9
A11: Segurança Social — trabalhador independente com contabilidade organizada
A12: Base de incidência anual, limitada ao teto | B12: SS_BASE | C12: =MIN(MAX($C$10,0),Parametros!$C$6*Parametros!$C$9*12) | D12: =MIN(MAX($D$10,0),Parametros!$C$6*Parametros!$C$9*12) | E12: =MIN(MAX($E$10,0),Parametros!$C$6*Parametros!$C$9*12) | F12: Art. 162.º n.º 3 Cód. Contributivo: com contabilidade organizada o rendimento relevante é o lucro tributável, não 70% da faturação. CONFIRMAR (R1-12). Modelado em regime de cruzeiro: no primeiro ano a base é a declarada no início de atividade.
A13: Contribuição anual para a Segurança Social | B13: SS_CONTR | C13: =MAX($C$12*Parametros!$C$8,Parametros!$C$10*12) | D13: =MAX($D$12*Parametros!$C$8,Parametros!$C$10*12) | E13: =MAX($E$12*Parametros!$C$8,Parametros!$C$10*12)
A14: Lucro tributável após dedução das contribuições | B14: LT | C14: =MAX(0,$C$10-$C$13) | D14: =MAX(0,$D$10-$D$13) | E14: =MAX(0,$E$10-$E$13) | F14: Contribuições obrigatórias dedutíveis na totalidade nesta via, ao contrário do art. 31.º n.º 2.
A15: IRS do agregado
A16: Rendimento da sócia sujeito a englobamento | B16: R_JUL | C16: =$C$14 | D16: =$D$14 | E16: =$E$14 | F16: Lucro tributável real. Não há dedução específica de 4.104 € nesta via.
A17: Rendimento do cônjuge fora da estrutura | B17: R_CONJ | C17: =Inputs!$C$37 | D17: =Inputs!$D$37 | E17: =Inputs!$E$37
A18: Rendimento coletável do agregado — com a atividade | B18: RC_COM | C18: =$C$16+$C$17 | D18: =$D$16+$D$17 | E18: =$E$16+$E$17
A19: Rendimento coletável do agregado — sem a atividade | B19: RC_SEM | C19: =$C$17 | D19: =$D$17 | E19: =$E$17 | F19: Contrafactual. O diferencial entre as duas coletas é o IRS realmente imputável à atividade e é o que torna as quatro vias comparáveis.
A20: Fator do quociente conjugal | B20: FATOR | C20: =IF(Inputs!$C$38=1,2,1) | D20: =IF(Inputs!$D$38=1,2,1) | E20: =IF(Inputs!$E$38=1,2,1) | F20: Art. 69.º CIRS. Isolado numa linha para que as fórmulas de coleta caibam num ecrã.
A21: Rendimento coletável ajustado ao quociente — com a atividade | B21: RCQ_COM | C21: =$C$18/$C$20 | D21: =$D$18/$D$20 | E21: =$E$18/$E$20
A22: Rendimento coletável ajustado ao quociente — sem a atividade | B22: RCQ_SEM | C22: =$C$19/$C$20 | D22: =$D$19/$D$20 | E22: =$E$19/$E$20
A23: Coleta com a atividade (incl. taxa adicional de solidariedade) | B23: COL_COM | C23: =$C$20*(SUMPRODUCT(($C$21>Parametros!$B$55:$B$63)*($C$21-Parametros!$B$55:$B$63)*Parametros!$E$55:$E$63)+SUMPRODUCT(($C$21>Parametros!$B$67:$B$68)*($C$21-Parametros!$B$67:$B$68)*Parametros!$E$67:$E$68)) | D23: =$D$20*(SUMPRODUCT(($D$21>Parametros!$B$55:$B$63)*($D$21-Parametros!$B$55:$B$63)*Parametros!$E$55:$E$63)+SUMPRODUCT(($D$21>Parametros!$B$67:$B$68)*($D$21-Parametros!$B$67:$B$68)*Parametros!$E$67:$E$68)) | E23: =$E$20*(SUMPRODUCT(($E$21>Parametros!$B$55:$B$63)*($E$21-Parametros!$B$55:$B$63)*Parametros!$E$55:$E$63)+SUMPRODUCT(($E$21>Parametros!$B$67:$B$68)*($E$21-Parametros!$B$67:$B$68)*Parametros!$E$67:$E$68)) | F23: Escalões na folha Parâmetros. Art. 68.º, 68.º-A e 69.º CIRS.
A24: Coleta sem a atividade | B24: COL_SEM | C24: =$C$20*(SUMPRODUCT(($C$22>Parametros!$B$55:$B$63)*($C$22-Parametros!$B$55:$B$63)*Parametros!$E$55:$E$63)+SUMPRODUCT(($C$22>Parametros!$B$67:$B$68)*($C$22-Parametros!$B$67:$B$68)*Parametros!$E$67:$E$68)) | D24: =$D$20*(SUMPRODUCT(($D$22>Parametros!$B$55:$B$63)*($D$22-Parametros!$B$55:$B$63)*Parametros!$E$55:$E$63)+SUMPRODUCT(($D$22>Parametros!$B$67:$B$68)*($D$22-Parametros!$B$67:$B$68)*Parametros!$E$67:$E$68)) | E24: =$E$20*(SUMPRODUCT(($E$22>Parametros!$B$55:$B$63)*($E$22-Parametros!$B$55:$B$63)*Parametros!$E$55:$E$63)+SUMPRODUCT(($E$22>Parametros!$B$67:$B$68)*($E$22-Parametros!$B$67:$B$68)*Parametros!$E$67:$E$68))
A25: IRS imputável à atividade | B25: IRS_ATIV | C25: =$C$23-$C$24 | D25: =$D$23-$D$24 | E25: =$E$23-$E$24
A26: IRS total do agregado, após deduções à coleta (memória) | B26: IRS_TOT | C26: =MAX(0,$C$23-Inputs!$C$40) | D26: =MAX(0,$D$23-Inputs!$D$40) | E26: =MAX(0,$E$23-Inputs!$E$40) | F26: Não entra na comparação entre vias; serve para o enquadramento do capítulo 3.
A27: Resultado
A28: Caixa gerada pela atividade, antes de impostos e contribuições | B28: CAIXA | C28: =Inputs!$C$42+Inputs!$C$43+Inputs!$C$17-(Inputs!$C$19+Inputs!$C$20+Inputs!$C$21+Inputs!$C$22+Inputs!$C$24+Inputs!$C$25+Inputs!$C$44) | D28: =Inputs!$D$42+Inputs!$D$43+Inputs!$D$17-(Inputs!$D$19+Inputs!$D$20+Inputs!$D$21+Inputs!$D$22+Inputs!$D$24+Inputs!$D$25+Inputs!$D$44) | E28: =Inputs!$E$42+Inputs!$E$43+Inputs!$E$17-(Inputs!$E$19+Inputs!$E$20+Inputs!$E$21+Inputs!$E$22+Inputs!$E$24+Inputs!$E$25+Inputs!$E$44) | F28: Caixa gerada pela atividade, igual nas quatro vias por construção. Exclui o investimento inicial, que é um efeito de ano 1 e está isolado na folha IVA e na linha própria abaixo.
A29: Total de impostos e contribuições | B29: CARGA | C29: =$C$25+$C$13 | D29: =$D$25+$D$13 | E29: =$E$25+$E$13 | F29: IRS imputável à atividade + contribuições para a Segurança Social.
A30: Taxa de esforço efetiva sobre a caixa gerada | B30: TAXA_EF | C30: =IF($C$28<=0,0,$C$29/$C$28) | D30: =IF($D$28<=0,0,$D$29/$D$28) | E30: =IF($E$28<=0,0,$E$29/$E$28)
A31: Valor retido na sociedade (não disponibilizado à sócia) | B31: RETIDO | C31: =0 | D31: =0 | E31: =0
A32: Valor atribuído ao cônjuge por via de dividendos, líquido | B32: LIQ_CJ | C32: =0 | D32: =0 | E32: =0 | F32: Só via 4. É uma transferência real de rendimento dentro do agregado e tem de ser explicitada — não é indiferente à sócia.
A33: LÍQUIDO DISPONÍVEL PARA A SÓCIA | B33: LIQ_SOC | C33: =$C$28-$C$29-$C$31-$C$32 | D33: =$D$28-$D$29-$D$31-$D$32 | E33: =$E$28-$E$29-$E$31-$E$32
A34: LÍQUIDO DISPONÍVEL PARA O AGREGADO | B34: LIQ_AGR | C34: =$C$33+$C$32 | D34: =$D$33+$D$32 | E34: =$E$33+$E$32
A35: Memória — investimento e IVA não dedutível suportados no ano 1 | B35: INV_A1 | C35: =Inputs!$C$27+Inputs!$C$28+Inputs!$C$29+Inputs!$C$30 | D35: =Inputs!$D$27+Inputs!$D$28+Inputs!$D$29+Inputs!$D$30 | E35: =Inputs!$E$27+Inputs!$E$28+Inputs!$E$29+Inputs!$E$30 | F35: Excluído da comparação anual acima. Quantificação do IVA na folha IVA.

Sheet V3_Soc_Transparente
A1: Via 3 — Sociedade sujeita a transparência fiscal (art. 6.º CIRC)
A2: Sociedade detida a 100% pela Dra. Júlia. O lucro é imputado à sócia e tributado em IRS independentemente de distribuição (art. 6.º n.º 3 CIRC e art. 20.º CIRS). A sociedade não é tributada em IRC sobre o lucro, mas mantém-se sujeita a tributações autónomas (art. 12.º CIRC).
A4: Rubrica | B4: Ref. | C4: Baixo | D4: Base | E4: Alto | F4: Nota / norma
A5: Apuramento ao nível da sociedade
A6: Receita bruta (fisioterapia + cedência de espaço) | B6: FAT | C6: =Inputs!$C$42+Inputs!$C$43 | D6: =Inputs!$D$42+Inputs!$D$43 | E6: =Inputs!$E$42+Inputs!$E$43
A7: Custos operacionais (excl. honorários) | B7: C_OP | C7: =Inputs!$C$19+Inputs!$C$20+Inputs!$C$21+Inputs!$C$22+Inputs!$C$24+Inputs!$C$25 | D7: =Inputs!$D$19+Inputs!$D$20+Inputs!$D$21+Inputs!$D$22+Inputs!$D$24+Inputs!$D$25 | E7: =Inputs!$E$19+Inputs!$E$20+Inputs!$E$21+Inputs!$E$22+Inputs!$E$24+Inputs!$E$25
A8: Custo com os colaboradores | B8: C_HON | C8: =Inputs!$C$44 | D8: =Inputs!$D$44 | E8: =Inputs!$E$44
A9: Amortizações do exercício | B9: AMORT | C9: =Inputs!$C$27*Parametros!$C$44+(Inputs!$C$28+Inputs!$C$29)*Parametros!$C$45+Inputs!$C$30*Parametros!$C$46 | D9: =Inputs!$D$27*Parametros!$C$44+(Inputs!$D$28+Inputs!$D$29)*Parametros!$C$45+Inputs!$D$30*Parametros!$C$46 | E9: =Inputs!$E$27*Parametros!$C$44+(Inputs!$E$28+Inputs!$E$29)*Parametros!$C$45+Inputs!$E$30*Parametros!$C$46
A10: Remuneração bruta de gerência | B10: REM | C10: =Inputs!$C$32 | D10: =Inputs!$D$32 | E10: =Inputs!$E$32 | F10: Variável de decisão. É a única base de incidência contributiva nesta via.
A11: Base de incidência contributiva do MOE | B11: BASE_MOE | C11: =MAX($C$10,Parametros!$C$6*Parametros!$C$13*12) | D11: =MAX($D$10,Parametros!$C$6*Parametros!$C$13*12) | E11: =MAX($E$10,Parametros!$C$6*Parametros!$C$13*12) | F11: Base mínima de 1 x IAS por mês, mesmo com remuneração inferior ou nula.
A12: Contribuições a cargo da sociedade | B12: TSU_ENT | C12: =$C$11*Parametros!$C$11 | D12: =$D$11*Parametros!$C$11 | E12: =$E$11*Parametros!$C$11
A13: Lucro tributável | B13: LT | C13: =$C$6-$C$7-$C$8-$C$9-$C$10-$C$12 | D13: =$D$6-$D$7-$D$8-$D$9-$D$10-$D$12 | E13: =$E$6-$E$7-$E$8-$E$9-$E$10-$E$12
A14: Tributações autónomas | B14: TA | C14: =Inputs!$C$33 | D14: =Inputs!$D$33 | E14: =Inputs!$E$33 | F14: Devidas apesar da transparência fiscal — art. 12.º CIRC ressalva as tributações autónomas.
A15: Derrama municipal | B15: DERR | C15: =MAX($C$13,0)*Parametros!$C$36*Parametros!$C$37 | D15: =MAX($D$13,0)*Parametros!$C$36*Parametros!$C$37 | E15: =MAX($E$13,0)*Parametros!$C$36*Parametros!$C$37 | F15: Interruptor na folha Parâmetros, por defeito a 0. A incidência de derrama sobre sociedade transparente é questão controvertida — ver R1-13. Não afirmar no relatório sem decisão da Fiscalidade.
A16: Lucro imputável à sócia | B16: LUCRO_IMP | C16: =MAX($C$13,0) | D16: =MAX($D$13,0) | E16: =MAX($E$13,0) | F16: Imputado independentemente de distribuição. Prejuízo fiscal não é imputado — é reportado na esfera da sociedade.
A17: Esfera da sócia
A18: Contribuições a cargo da sócia (categoria A) | B18: SS_TRAB | C18: =$C$11*Parametros!$C$12 | D18: =$D$11*Parametros!$C$12 | E18: =$E$11*Parametros!$C$12
A19: Dedução específica da categoria A | B19: DED_A | C19: =MIN($C$10,MAX(Parametros!$C$30,$C$18)) | D19: =MIN($D$10,MAX(Parametros!$C$30,$D$18)) | E19: =MIN($E$10,MAX(Parametros!$C$30,$E$18)) | F19: Art. 25.º n.º 1 al. a) e n.º 2 CIRS: o maior entre 4.104 € e as contribuições, com o limite do próprio rendimento.
A20: Rendimento líquido da categoria A | B20: RL_CATA | C20: =MAX(0,$C$10-$C$19) | D20: =MAX(0,$D$10-$D$19) | E20: =MAX(0,$E$10-$E$19)
A21: IRS do agregado
A22: Rendimento da sócia sujeito a englobamento | B22: R_JUL | C22: =$C$20+$C$16 | D22: =$D$20+$D$16 | E22: =$E$20+$E$16 | F22: Categoria A (remuneração de gerência) + categoria B (lucro imputado, art. 20.º CIRS).
A23: Rendimento do cônjuge fora da estrutura | B23: R_CONJ | C23: =Inputs!$C$37 | D23: =Inputs!$D$37 | E23: =Inputs!$E$37
A24: Rendimento coletável do agregado — com a atividade | B24: RC_COM | C24: =$C$22+$C$23 | D24: =$D$22+$D$23 | E24: =$E$22+$E$23
A25: Rendimento coletável do agregado — sem a atividade | B25: RC_SEM | C25: =$C$23 | D25: =$D$23 | E25: =$E$23 | F25: Contrafactual. O diferencial entre as duas coletas é o IRS realmente imputável à atividade e é o que torna as quatro vias comparáveis.
A26: Fator do quociente conjugal | B26: FATOR | C26: =IF(Inputs!$C$38=1,2,1) | D26: =IF(Inputs!$D$38=1,2,1) | E26: =IF(Inputs!$E$38=1,2,1) | F26: Art. 69.º CIRS. Isolado numa linha para que as fórmulas de coleta caibam num ecrã.
A27: Rendimento coletável ajustado ao quociente — com a atividade | B27: RCQ_COM | C27: =$C$24/$C$26 | D27: =$D$24/$D$26 | E27: =$E$24/$E$26
A28: Rendimento coletável ajustado ao quociente — sem a atividade | B28: RCQ_SEM | C28: =$C$25/$C$26 | D28: =$D$25/$D$26 | E28: =$E$25/$E$26
A29: Coleta com a atividade (incl. taxa adicional de solidariedade) | B29: COL_COM | C29: =$C$26*(SUMPRODUCT(($C$27>Parametros!$B$55:$B$63)*($C$27-Parametros!$B$55:$B$63)*Parametros!$E$55:$E$63)+SUMPRODUCT(($C$27>Parametros!$B$67:$B$68)*($C$27-Parametros!$B$67:$B$68)*Parametros!$E$67:$E$68)) | D29: =$D$26*(SUMPRODUCT(($D$27>Parametros!$B$55:$B$63)*($D$27-Parametros!$B$55:$B$63)*Parametros!$E$55:$E$63)+SUMPRODUCT(($D$27>Parametros!$B$67:$B$68)*($D$27-Parametros!$B$67:$B$68)*Parametros!$E$67:$E$68)) | E29: =$E$26*(SUMPRODUCT(($E$27>Parametros!$B$55:$B$63)*($E$27-Parametros!$B$55:$B$63)*Parametros!$E$55:$E$63)+SUMPRODUCT(($E$27>Parametros!$B$67:$B$68)*($E$27-Parametros!$B$67:$B$68)*Parametros!$E$67:$E$68)) | F29: Escalões na folha Parâmetros. Art. 68.º, 68.º-A e 69.º CIRS.
A30: Coleta sem a atividade | B30: COL_SEM | C30: =$C$26*(SUMPRODUCT(($C$28>Parametros!$B$55:$B$63)*($C$28-Parametros!$B$55:$B$63)*Parametros!$E$55:$E$63)+SUMPRODUCT(($C$28>Parametros!$B$67:$B$68)*($C$28-Parametros!$B$67:$B$68)*Parametros!$E$67:$E$68)) | D30: =$D$26*(SUMPRODUCT(($D$28>Parametros!$B$55:$B$63)*($D$28-Parametros!$B$55:$B$63)*Parametros!$E$55:$E$63)+SUMPRODUCT(($D$28>Parametros!$B$67:$B$68)*($D$28-Parametros!$B$67:$B$68)*Parametros!$E$67:$E$68)) | E30: =$E$26*(SUMPRODUCT(($E$28>Parametros!$B$55:$B$63)*($E$28-Parametros!$B$55:$B$63)*Parametros!$E$55:$E$63)+SUMPRODUCT(($E$28>Parametros!$B$67:$B$68)*($E$28-Parametros!$B$67:$B$68)*Parametros!$E$67:$E$68))
A31: IRS imputável à atividade | B31: IRS_ATIV | C31: =$C$29-$C$30 | D31: =$D$29-$D$30 | E31: =$E$29-$E$30
A32: IRS total do agregado, após deduções à coleta (memória) | B32: IRS_TOT | C32: =MAX(0,$C$29-Inputs!$C$40) | D32: =MAX(0,$D$29-Inputs!$D$40) | E32: =MAX(0,$E$29-Inputs!$E$40) | F32: Não entra na comparação entre vias; serve para o enquadramento do capítulo 3.
A33: Resultado
A34: Caixa gerada pela atividade, antes de impostos e contribuições | B34: CAIXA | C34: =Inputs!$C$42+Inputs!$C$43+Inputs!$C$17-(Inputs!$C$19+Inputs!$C$20+Inputs!$C$21+Inputs!$C$22+Inputs!$C$24+Inputs!$C$25+Inputs!$C$44) | D34: =Inputs!$D$42+Inputs!$D$43+Inputs!$D$17-(Inputs!$D$19+Inputs!$D$20+Inputs!$D$21+Inputs!$D$22+Inputs!$D$24+Inputs!$D$25+Inputs!$D$44) | E34: =Inputs!$E$42+Inputs!$E$43+Inputs!$E$17-(Inputs!$E$19+Inputs!$E$20+Inputs!$E$21+Inputs!$E$22+Inputs!$E$24+Inputs!$E$25+Inputs!$E$44) | F34: Caixa gerada pela atividade, igual nas quatro vias por construção. Exclui o investimento inicial, que é um efeito de ano 1 e está isolado na folha IVA e na linha própria abaixo.
A35: Total de impostos e contribuições | B35: CARGA | C35: =$C$31+$C$18+$C$12+$C$14+$C$15 | D35: =$D$31+$D$18+$D$12+$D$14+$D$15 | E35: =$E$31+$E$18+$E$12+$E$14+$E$15 | F35: IRS imputável + contribuições da sócia + contribuições da sociedade + tributações autónomas + derrama. A distribuição do lucro já imputado não é novamente tributada.
A36: Taxa de esforço efetiva sobre a caixa gerada | B36: TAXA_EF | C36: =IF($C$34<=0,0,$C$35/$C$34) | D36: =IF($D$34<=0,0,$D$35/$D$34) | E36: =IF($E$34<=0,0,$E$35/$E$34)
A37: Valor retido na sociedade (não disponibilizado à sócia) | B37: RETIDO | C37: =MAX(0,(Inputs!$C$42+Inputs!$C$43+Inputs!$C$17-(Inputs!$C$19+Inputs!$C$20+Inputs!$C$21+Inputs!$C$22+Inputs!$C$24+Inputs!$C$25+Inputs!$C$44))-$C$10-$C$12-$C$14-$C$15)*(1-Inputs!$C$34) | D37: =MAX(0,(Inputs!$D$42+Inputs!$D$43+Inputs!$D$17-(Inputs!$D$19+Inputs!$D$20+Inputs!$D$21+Inputs!$D$22+Inputs!$D$24+Inputs!$D$25+Inputs!$D$44))-$D$10-$D$12-$D$14-$D$15)*(1-Inputs!$D$34) | E37: =MAX(0,(Inputs!$E$42+Inputs!$E$43+Inputs!$E$17-(Inputs!$E$19+Inputs!$E$20+Inputs!$E$21+Inputs!$E$22+Inputs!$E$24+Inputs!$E$25+Inputs!$E$44))-$E$10-$E$12-$E$14-$E$15)*(1-Inputs!$E$34)
A38: Valor atribuído ao cônjuge por via de dividendos, líquido | B38: LIQ_CJ | C38: =0 | D38: =0 | E38: =0 | F38: Só via 4. É uma transferência real de rendimento dentro do agregado e tem de ser explicitada — não é indiferente à sócia.
A39: LÍQUIDO DISPONÍVEL PARA A SÓCIA | B39: LIQ_SOC | C39: =$C$34-$C$35-$C$37-$C$38 | D39: =$D$34-$D$35-$D$37-$D$38 | E39: =$E$34-$E$35-$E$37-$E$38
A40: LÍQUIDO DISPONÍVEL PARA O AGREGADO | B40: LIQ_AGR | C40: =$C$39+$C$38 | D40: =$D$39+$D$38 | E40: =$E$39+$E$38
A41: Memória — investimento e IVA não dedutível suportados no ano 1 | B41: INV_A1 | C41: =Inputs!$C$27+Inputs!$C$28+Inputs!$C$29+Inputs!$C$30 | D41: =Inputs!$D$27+Inputs!$D$28+Inputs!$D$29+Inputs!$D$30 | E41: =Inputs!$E$27+Inputs!$E$28+Inputs!$E$29+Inputs!$E$30 | F41: Excluído da comparação anual acima. Quantificação do IVA na folha IVA.

Sheet V4_Soc_NaoTransparente
A1: Via 4 — Sociedade fora da transparência fiscal (entrada do cônjuge)
A2: Pressupõe que a entrada do cônjuge afasta o regime do art. 6.º CIRC (ver N1 para o teste). O lucro passa a ser tributado em IRC e a distribuição é tributada de novo na esfera dos sócios. A pergunta a que esta folha responde não é 'sai da transparência?' mas 'compensa sair?'.
A4: Rubrica | B4: Ref. | C4: Baixo | D4: Base | E4: Alto | F4: Nota / norma
A5: Apuramento ao nível da sociedade
A6: Receita isenta (fisioterapia + cedência de espaço, se isenta) | B6: FAT | C6: =Inputs!$C$42+IF(Inputs!$C$16=1,0,Inputs!$C$43) | D6: =Inputs!$D$42+IF(Inputs!$D$16=1,0,Inputs!$D$43) | E6: =Inputs!$E$42+IF(Inputs!$E$16=1,0,Inputs!$E$43)
A7: Receita sujeita a IVA (cônjuge e/ou cedência tributada) | B7: FAT_T | C7: =Inputs!$C$47 | D7: =Inputs!$D$47 | E7: =Inputs!$E$47
A8: Custos operacionais (excl. honorários) | B8: C_OP | C8: =Inputs!$C$19+Inputs!$C$20+Inputs!$C$21+Inputs!$C$22+Inputs!$C$24+Inputs!$C$25 | D8: =Inputs!$D$19+Inputs!$D$20+Inputs!$D$21+Inputs!$D$22+Inputs!$D$24+Inputs!$D$25 | E8: =Inputs!$E$19+Inputs!$E$20+Inputs!$E$21+Inputs!$E$22+Inputs!$E$24+Inputs!$E$25
A9: Custo com os colaboradores | B9: C_HON | C9: =Inputs!$C$44 | D9: =Inputs!$D$44 | E9: =Inputs!$E$44
A10: Amortizações do exercício | B10: AMORT | C10: =Inputs!$C$27*Parametros!$C$44+(Inputs!$C$28+Inputs!$C$29)*Parametros!$C$45+Inputs!$C$30*Parametros!$C$46 | D10: =Inputs!$D$27*Parametros!$C$44+(Inputs!$D$28+Inputs!$D$29)*Parametros!$C$45+Inputs!$D$30*Parametros!$C$46 | E10: =Inputs!$E$27*Parametros!$C$44+(Inputs!$E$28+Inputs!$E$29)*Parametros!$C$45+Inputs!$E$30*Parametros!$C$46
A11: Remuneração bruta de gerência | B11: REM | C11: =Inputs!$C$32 | D11: =Inputs!$D$32 | E11: =Inputs!$E$32
A12: Base de incidência contributiva do MOE | B12: BASE_MOE | C12: =MAX($C$11,Parametros!$C$6*Parametros!$C$13*12) | D12: =MAX($D$11,Parametros!$C$6*Parametros!$C$13*12) | E12: =MAX($E$11,Parametros!$C$6*Parametros!$C$13*12)
A13: Contribuições a cargo da sociedade | B13: TSU_ENT | C13: =$C$12*Parametros!$C$11 | D13: =$D$12*Parametros!$C$11 | E13: =$E$12*Parametros!$C$11
A14: Lucro tributável | B14: LT | C14: =$C$6+$C$7-$C$8-$C$9-$C$10-$C$11-$C$13 | D14: =$D$6+$D$7-$D$8-$D$9-$D$10-$D$11-$D$13 | E14: =$E$6+$E$7-$E$8-$E$9-$E$10-$E$11-$E$13
A15: IRC | B15: IRC | C15: =MIN(MAX($C$14,0),Parametros!$C$34)*Parametros!$C$33+MAX(0,MAX($C$14,0)-Parametros!$C$34)*Parametros!$C$35 | D15: =MIN(MAX($D$14,0),Parametros!$C$34)*Parametros!$C$33+MAX(0,MAX($D$14,0)-Parametros!$C$34)*Parametros!$C$35 | E15: =MIN(MAX($E$14,0),Parametros!$C$34)*Parametros!$C$33+MAX(0,MAX($E$14,0)-Parametros!$C$34)*Parametros!$C$35 | F15: Art. 87.º n.º 1 e 2 CIRC. Taxas de 2026 por confirmar — ver R1-11. O primeiro escalão só é aplicável se a sociedade qualificar como PME.
A16: Derrama municipal | B16: DERR | C16: =MAX($C$14,0)*Parametros!$C$36 | D16: =MAX($D$14,0)*Parametros!$C$36 | E16: =MAX($E$14,0)*Parametros!$C$36 | F16: Confirmar a taxa e eventual isenção do município para volume de negócios reduzido.
A17: Tributações autónomas | B17: TA | C17: =Inputs!$C$33 | D17: =Inputs!$D$33 | E17: =Inputs!$E$33
A18: Lucro após imposto | B18: LUCRO_LIQ | C18: =$C$14-$C$15-$C$16-$C$17 | D18: =$D$14-$D$15-$D$16-$D$17 | E18: =$E$14-$E$15-$E$16-$E$17
A19: Distribuição de resultados
A20: Caixa distribuível | B20: CX_DIST | C20: =MAX(0,(Inputs!$C$42+Inputs!$C$43+Inputs!$C$17-(Inputs!$C$19+Inputs!$C$20+Inputs!$C$21+Inputs!$C$22+Inputs!$C$24+Inputs!$C$25+Inputs!$C$44))-$C$11-$C$13-$C$15-$C$16-$C$17) | D20: =MAX(0,(Inputs!$D$42+Inputs!$D$43+Inputs!$D$17-(Inputs!$D$19+Inputs!$D$20+Inputs!$D$21+Inputs!$D$22+Inputs!$D$24+Inputs!$D$25+Inputs!$D$44))-$D$11-$D$13-$D$15-$D$16-$D$17) | E20: =MAX(0,(Inputs!$E$42+Inputs!$E$43+Inputs!$E$17-(Inputs!$E$19+Inputs!$E$20+Inputs!$E$21+Inputs!$E$22+Inputs!$E$24+Inputs!$E$25+Inputs!$E$44))-$E$11-$E$13-$E$15-$E$16-$E$17) | F20: Base de caixa: as amortizações não são saída de caixa, pelo que a caixa distribuível excede o lucro contabilístico enquanto o investimento estiver a ser amortizado.
A21: Política de distribuição | B21: POL | C21: =Inputs!$C$34 | D21: =Inputs!$D$34 | E21: =Inputs!$E$34 | F21: ALAVANCA PRINCIPAL desta via. A 0% de distribuição a via 4 domina; a 100% pode inverter-se.
A22: Montante distribuído | B22: DIST | C22: =$C$20*$C$21 | D22: =$D$20*$D$21 | E22: =$E$20*$E$21
A23: % do capital detida pelo cônjuge | B23: PCT_CJ | C23: =Inputs!$C$35 | D23: =Inputs!$D$35 | E23: =Inputs!$E$35
A24: Dividendo atribuído à sócia | B24: DIV_JUL | C24: =$C$22*(1-$C$23) | D24: =$D$22*(1-$D$23) | E24: =$E$22*(1-$E$23)
A25: Dividendo atribuído ao cônjuge | B25: DIV_CJ | C25: =$C$22*$C$23 | D25: =$D$22*$D$23 | E25: =$E$22*$E$23 | F25: Consequência não fiscal e frequentemente esquecida: a participação que afasta a transparência desloca essa fração do lucro para o cônjuge, em definitivo.
A26: Opção por englobamento dos dividendos (1 = sim / 0 = retenção liberatória) | B26: ENGLOB | C26: 0 | D26: 0 | E26: 0 | F26: ALAVANCA. Testar ambas. Art. 71.º n.º 6 e art. 40.º-A CIRS.
A27: Imposto sobre dividendos, por retenção liberatória | B27: IMP_DIV | C27: =IF($C$26=1,0,($C$24+$C$25)*Parametros!$C$38) | D27: =IF($D$26=1,0,($D$24+$D$25)*Parametros!$C$38) | E27: =IF($E$26=1,0,($E$24+$E$25)*Parametros!$C$38)
A28: IRS do agregado
A29: Rendimento da sócia sujeito a englobamento | B29: R_JUL | C29: =MAX(0,$C$11-MIN($C$11,MAX(Parametros!$C$30,$C$12*Parametros!$C$12)))+IF($C$26=1,$C$24*Parametros!$C$39,0) | D29: =MAX(0,$D$11-MIN($D$11,MAX(Parametros!$C$30,$D$12*Parametros!$C$12)))+IF($D$26=1,$D$24*Parametros!$C$39,0) | E29: =MAX(0,$E$11-MIN($E$11,MAX(Parametros!$C$30,$E$12*Parametros!$C$12)))+IF($E$26=1,$E$24*Parametros!$C$39,0) | F29: Categoria A líquida da dedução específica, mais 50% dos dividendos se houver englobamento (art. 40.º-A CIRS).
A30: Rendimento do cônjuge (incl. dividendos englobados, se aplicável) | B30: R_CONJ | C30: =Inputs!$C$37+IF($C$26=1,$C$25*Parametros!$C$39,0) | D30: =Inputs!$D$37+IF($D$26=1,$D$25*Parametros!$C$39,0) | E30: =Inputs!$E$37+IF($E$26=1,$E$25*Parametros!$C$39,0)
A31: Rendimento coletável do agregado — com a atividade | B31: RC_COM | C31: =$C$29+$C$30 | D31: =$D$29+$D$30 | E31: =$E$29+$E$30
A32: Rendimento coletável do agregado — sem a atividade | B32: RC_SEM | C32: =Inputs!$C$37 | D32: =Inputs!$D$37 | E32: =Inputs!$E$37 | F32: Contrafactual: apenas o rendimento do cônjuge fora da estrutura.
A33: Fator do quociente conjugal | B33: FATOR | C33: =IF(Inputs!$C$38=1,2,1) | D33: =IF(Inputs!$D$38=1,2,1) | E33: =IF(Inputs!$E$38=1,2,1)
A34: Rendimento coletável ajustado ao quociente — com a atividade | B34: RCQ_COM | C34: =$C$31/$C$33 | D34: =$D$31/$D$33 | E34: =$E$31/$E$33
A35: Rendimento coletável ajustado ao quociente — sem a atividade | B35: RCQ_SEM | C35: =$C$32/$C$33 | D35: =$D$32/$D$33 | E35: =$E$32/$E$33
A36: Coleta com a atividade (incl. taxa adicional de solidariedade) | B36: COL_COM | C36: =$C$33*(SUMPRODUCT(($C$34>Parametros!$B$55:$B$63)*($C$34-Parametros!$B$55:$B$63)*Parametros!$E$55:$E$63)+SUMPRODUCT(($C$34>Parametros!$B$67:$B$68)*($C$34-Parametros!$B$67:$B$68)*Parametros!$E$67:$E$68)) | D36: =$D$33*(SUMPRODUCT(($D$34>Parametros!$B$55:$B$63)*($D$34-Parametros!$B$55:$B$63)*Parametros!$E$55:$E$63)+SUMPRODUCT(($D$34>Parametros!$B$67:$B$68)*($D$34-Parametros!$B$67:$B$68)*Parametros!$E$67:$E$68)) | E36: =$E$33*(SUMPRODUCT(($E$34>Parametros!$B$55:$B$63)*($E$34-Parametros!$B$55:$B$63)*Parametros!$E$55:$E$63)+SUMPRODUCT(($E$34>Parametros!$B$67:$B$68)*($E$34-Parametros!$B$67:$B$68)*Parametros!$E$67:$E$68))
A37: Coleta sem a atividade | B37: COL_SEM | C37: =$C$33*(SUMPRODUCT(($C$35>Parametros!$B$55:$B$63)*($C$35-Parametros!$B$55:$B$63)*Parametros!$E$55:$E$63)+SUMPRODUCT(($C$35>Parametros!$B$67:$B$68)*($C$35-Parametros!$B$67:$B$68)*Parametros!$E$67:$E$68)) | D37: =$D$33*(SUMPRODUCT(($D$35>Parametros!$B$55:$B$63)*($D$35-Parametros!$B$55:$B$63)*Parametros!$E$55:$E$63)+SUMPRODUCT(($D$35>Parametros!$B$67:$B$68)*($D$35-Parametros!$B$67:$B$68)*Parametros!$E$67:$E$68)) | E37: =$E$33*(SUMPRODUCT(($E$35>Parametros!$B$55:$B$63)*($E$35-Parametros!$B$55:$B$63)*Parametros!$E$55:$E$63)+SUMPRODUCT(($E$35>Parametros!$B$67:$B$68)*($E$35-Parametros!$B$67:$B$68)*Parametros!$E$67:$E$68))
A38: IRS imputável à atividade | B38: IRS_ATIV | C38: =$C$36-$C$37 | D38: =$D$36-$D$37 | E38: =$E$36-$E$37
A39: IRS total do agregado, após deduções à coleta (memória) | B39: IRS_TOT | C39: =MAX(0,$C$36-Inputs!$C$40) | D39: =MAX(0,$D$36-Inputs!$D$40) | E39: =MAX(0,$E$36-Inputs!$E$40)
A40: Contribuições a cargo da sócia (memória) | B40: SS_TRAB | C40: =$C$12*Parametros!$C$12 | D40: =$D$12*Parametros!$C$12 | E40: =$E$12*Parametros!$C$12
A41: Resultado
A42: Caixa gerada pela atividade, antes de impostos e contribuições | B42: CAIXA | C42: =Inputs!$C$42+Inputs!$C$43+Inputs!$C$17-(Inputs!$C$19+Inputs!$C$20+Inputs!$C$21+Inputs!$C$22+Inputs!$C$24+Inputs!$C$25+Inputs!$C$44) | D42: =Inputs!$D$42+Inputs!$D$43+Inputs!$D$17-(Inputs!$D$19+Inputs!$D$20+Inputs!$D$21+Inputs!$D$22+Inputs!$D$24+Inputs!$D$25+Inputs!$D$44) | E42: =Inputs!$E$42+Inputs!$E$43+Inputs!$E$17-(Inputs!$E$19+Inputs!$E$20+Inputs!$E$21+Inputs!$E$22+Inputs!$E$24+Inputs!$E$25+Inputs!$E$44) | F42: Caixa gerada pela atividade, igual nas quatro vias por construção. Exclui o investimento inicial, que é um efeito de ano 1 e está isolado na folha IVA e na linha própria abaixo.
A43: Total de impostos e contribuições | B43: CARGA | C43: =$C$38+$C$40+$C$13+$C$15+$C$16+$C$17+$C$27 | D43: =$D$38+$D$40+$D$13+$D$15+$D$16+$D$17+$D$27 | E43: =$E$38+$E$40+$E$13+$E$15+$E$16+$E$17+$E$27 | F43: IRS imputável + contribuições da sócia e da sociedade + IRC + derrama + tributações autónomas + imposto sobre dividendos.
A44: Taxa de esforço efetiva sobre a caixa gerada | B44: TAXA_EF | C44: =IF($C$42<=0,0,$C$43/$C$42) | D44: =IF($D$42<=0,0,$D$43/$D$42) | E44: =IF($E$42<=0,0,$E$43/$E$42)
A45: Valor retido na sociedade (não disponibilizado à sócia) | B45: RETIDO | C45: =$C$20-$C$22 | D45: =$D$20-$D$22 | E45: =$E$20-$E$22
A46: Valor atribuído ao cônjuge por via de dividendos, líquido | B46: LIQ_CJ | C46: =$C$25-IF($C$26=1,0,$C$25*Parametros!$C$38) | D46: =$D$25-IF($D$26=1,0,$D$25*Parametros!$C$38) | E46: =$E$25-IF($E$26=1,0,$E$25*Parametros!$C$38) | F46: Só via 4. É uma transferência real de rendimento dentro do agregado e tem de ser explicitada — não é indiferente à sócia.
A47: LÍQUIDO DISPONÍVEL PARA A SÓCIA | B47: LIQ_SOC | C47: =$C$42-$C$43-$C$45-$C$46 | D47: =$D$42-$D$43-$D$45-$D$46 | E47: =$E$42-$E$43-$E$45-$E$46
A48: LÍQUIDO DISPONÍVEL PARA O AGREGADO | B48: LIQ_AGR | C48: =$C$47+$C$46 | D48: =$D$47+$D$46 | E48: =$E$47+$E$46
A49: Memória — investimento e IVA não dedutível suportados no ano 1 | B49: INV_A1 | C49: =Inputs!$C$27+Inputs!$C$28+Inputs!$C$29+Inputs!$C$30 | D49: =Inputs!$D$27+Inputs!$D$28+Inputs!$D$29+Inputs!$D$30 | E49: =Inputs!$E$27+Inputs!$E$28+Inputs!$E$29+Inputs!$E$30 | F49: Excluído da comparação anual acima. Quantificação do IVA na folha IVA.

Sheet IVA
A1: M1 — IVA sobre o investimento e custos correntes
A2: A fisioterapia é isenta pelo art. 9.º n.º 1 CIVA. É isenção incompleta: não confere direito à dedução. Todo o IVA suportado é custo. Esta folha quantifica o custo e testa as duas atenuantes: taxa reduzida em equipamento (Lista I) e sujeito passivo misto por entrada do cônjuge.
A4: Rubrica | B4: Ref. | C4: Baixo | D4: Base | E4: Alto | F4: Nota / norma
A5: IVA suportado no investimento inicial
A6: IVA nas obras | B6: I_OBRAS | C6: =Inputs!$C$27*Parametros!$C$41 | D6: =Inputs!$D$27*Parametros!$C$41 | E6: =Inputs!$E$27*Parametros!$C$41
A7: IVA no equipamento à taxa normal | B7: I_EQN | C7: =Inputs!$C$28*Parametros!$C$41 | D7: =Inputs!$D$28*Parametros!$C$41 | E7: =Inputs!$E$28*Parametros!$C$41
A8: IVA no equipamento à taxa reduzida | B8: I_EQR | C8: =Inputs!$C$29*Parametros!$C$42 | D8: =Inputs!$D$29*Parametros!$C$42 | E8: =Inputs!$E$29*Parametros!$C$42 | F8: Verbas 2.5 e 2.6 da Lista I do CIVA. A confirmar item a item contra o orçamento de equipamento — é a atenuante mais barata de obter e ninguém a verificou ainda.
A9: IVA no software | B9: I_SOFT | C9: =Inputs!$C$30*Parametros!$C$41 | D9: =Inputs!$D$30*Parametros!$C$41 | E9: =Inputs!$E$30*Parametros!$C$41
A10: Total de IVA suportado no investimento | B10: I_TOT | C10: =SUM($C$6:$C$9) | D10: =SUM($D$6:$D$9) | E10: =SUM($E$6:$E$9)
A11: Tratamento nas vias 1, 2 e 3 — atividade exclusivamente isenta
A12: IVA dedutível | B12: D_ISENTO | C12: =0 | D12: =0 | E12: =0 | F12: Art. 20.º n.º 1 CIVA a contrario: isenção do art. 9.º não confere direito à dedução.
A13: IVA perdido, convertido em custo do investimento | B13: P_ISENTO | C13: =$C$10 | D13: =$D$10 | E13: =$E$10 | F13: Este montante acresce ao custo de aquisição e é amortizado nas vias com contabilidade.
A14: Tratamento na via 4 — sujeito passivo misto
A15: Pro rata de dedução | B15: PRO_RATA | C15: =IF(Inputs!$C$46<=0,0,Inputs!$C$47/Inputs!$C$46) | D15: =IF(Inputs!$D$46<=0,0,Inputs!$D$47/Inputs!$D$46) | E15: =IF(Inputs!$E$46<=0,0,Inputs!$E$47/Inputs!$E$46) | F15: Art. 23.º n.º 4 CIVA: volume de negócios com direito a dedução sobre o total. Com FAT_TRIB a zero o pro rata é zero — só há dedução se o cônjuge faturar dentro da sociedade.
A16: % do investimento afeto exclusivamente à atividade tributada | B16: PCT_EXCL | C16: 0 | D16: 0 | E16: 0 | F16: Só relevante na afetação real. A preencher com base na planta do espaço e no orçamento de obras.
A17: IVA dedutível — método do pro rata | B17: D_PRORATA | C17: =$C$10*$C$15 | D17: =$D$10*$D$15 | E17: =$E$10*$E$15
A18: IVA dedutível — método da afetação real | B18: D_REAL | C18: =$C$10*$C$16+$C$10*(1-$C$16)*$C$15 | D18: =$D$10*$D$16+$D$10*(1-$D$16)*$D$15 | E18: =$E$10*$E$16+$E$10*(1-$E$16)*$E$15 | F18: Art. 23.º n.º 2 CIVA. Dedução integral na parte exclusivamente afeta a operações tributadas, pro rata nos custos comuns. Mais favorável, mas exige segregação documental permanente (ata, ponto 6).
A19: IVA recuperável na melhor hipótese | B19: D_MELHOR | C19: =MAX($C$17,$C$18) | D19: =MAX($D$17,$D$18) | E19: =MAX($E$17,$E$18)
A20: IVA perdido na via 4 | B20: P_MISTO | C20: =$C$10-$C$19 | D20: =$D$10-$D$19 | E20: =$E$10-$E$19
A21: Ganho de IVA atribuível à entrada do cônjuge | B21: GANHO | C21: =$C$13-$C$20 | D21: =$D$13-$D$20 | E21: =$E$13-$E$20 | F21: Comparar com o diferencial de IRS/IRC da folha Comparativo. A ata afirma que o efeito da transparência é 'materialmente superior' ao do IVA — esta linha é o teste dessa afirmação.
A22: Sensibilidade — elegibilidade para taxa reduzida
A23: % do equipamento que viesse a qualificar para a taxa reduzida | B23: SENS_PCT | C23: 0.3 | D23: 0.3 | E23: 0.3 | F23: Cenário de teste. Não é uma estimativa: substituir pela verificação item a item.
A24: Poupança de IVA nesse cenário | B24: SENS_GAN | C24: =Inputs!$C$28*$C$23*(Parametros!$C$41-Parametros!$C$42) | D24: =Inputs!$D$28*$D$23*(Parametros!$C$41-Parametros!$C$42) | E24: =Inputs!$E$28*$E$23*(Parametros!$C$41-Parametros!$C$42)
A25: IVA em custos correntes (anual, memória)
A26: Base dos custos correntes sujeitos a IVA | B26: C_CORR | C26: =Inputs!$C$22+Inputs!$C$24+Inputs!$C$25 | D26: =Inputs!$D$22+Inputs!$D$24+Inputs!$D$25 | E26: =Inputs!$E$22+Inputs!$E$24+Inputs!$E$25 | F26: Renda paga excluída: o arrendamento é isento salvo renúncia (art. 9.º n.º 29 CIVA). Honorários de fisioterapeutas excluídos: também isentos pelo art. 9.º n.º 1.
A27: IVA anual suportado e não dedutível (vias 1 a 3) | B27: C_IVA | C27: =$C$26*Parametros!$C$41 | D27: =$D$26*Parametros!$C$41 | E27: =$E$26*Parametros!$C$41

Sheet Comparativo
A1: M1 — Comparativo das quatro vias
A2: Output principal do modelo. Sustenta o capítulo 3 do relatório e o anexo E2. Cada bloco é um cenário de faturação. O indicador de decisão é o líquido disponível para a sócia, não a carga fiscal absoluta — uma via pode pagar menos imposto e entregar menos dinheiro.
A4: CENÁRIO BAIXO
A5: Indicador | C5: Via 1 — ENI simplificado | D5: Via 2 — ENI cont. organizada | E5: Via 3 — Soc. transparente | F5: Via 4 — Soc. não transparente | G5: Nota
A6: Caixa gerada pela atividade | C6: =V1_ENI_Simplificado!$C$39 | D6: =V2_ENI_ContOrg!$C$28 | E6: =V3_Soc_Transparente!$C$34 | F6: =V4_Soc_NaoTransparente!$C$42 | G6: Idêntica nas quatro vias, por construção.
A7: IRS imputável à atividade | C7: =V1_ENI_Simplificado!$C$36 | D7: =V2_ENI_ContOrg!$C$25 | E7: =V3_Soc_Transparente!$C$31 | F7: =V4_Soc_NaoTransparente!$C$38
A8: Segurança Social (todas as componentes) | C8: =V1_ENI_Simplificado!$C$23 | D8: =V2_ENI_ContOrg!$C$13 | E8: =V3_Soc_Transparente!$C$18+V3_Soc_Transparente!$C$12 | F8: =V4_Soc_NaoTransparente!$C$40+V4_Soc_NaoTransparente!$C$13 | G8: Vias 1 e 2: contribuição do trabalhador independente. Vias 3 e 4: contribuições do MOE, a cargo da sócia e da sociedade.
A9: IRC, derrama e tributações autónomas | C9: =0 | D9: =0 | E9: =V3_Soc_Transparente!$C$14+V3_Soc_Transparente!$C$15 | F9: =V4_Soc_NaoTransparente!$C$15+V4_Soc_NaoTransparente!$C$16+V4_Soc_NaoTransparente!$C$17
A10: Imposto sobre a distribuição | C10: =0 | D10: =0 | E10: =0 | F10: =V4_Soc_NaoTransparente!$C$27
A11: TOTAL DE IMPOSTOS E CONTRIBUIÇÕES | C11: =V1_ENI_Simplificado!$C$40 | D11: =V2_ENI_ContOrg!$C$29 | E11: =V3_Soc_Transparente!$C$35 | F11: =V4_Soc_NaoTransparente!$C$43
A12: Taxa de esforço sobre a caixa gerada | C12: =V1_ENI_Simplificado!$C$41 | D12: =V2_ENI_ContOrg!$C$30 | E12: =V3_Soc_Transparente!$C$36 | F12: =V4_Soc_NaoTransparente!$C$44
A13: Valor retido na sociedade | C13: =V1_ENI_Simplificado!$C$42 | D13: =V2_ENI_ContOrg!$C$31 | E13: =V3_Soc_Transparente!$C$37 | F13: =V4_Soc_NaoTransparente!$C$45 | G13: Não é perda, mas também não é liquidez da sócia. Tem de aparecer separado.
A14: Valor atribuído ao cônjuge | C14: =V1_ENI_Simplificado!$C$43 | D14: =V2_ENI_ContOrg!$C$32 | E14: =V3_Soc_Transparente!$C$38 | F14: =V4_Soc_NaoTransparente!$C$46
A15: LÍQUIDO DISPONÍVEL PARA A SÓCIA | C15: =V1_ENI_Simplificado!$C$44 | D15: =V2_ENI_ContOrg!$C$33 | E15: =V3_Soc_Transparente!$C$39 | F15: =V4_Soc_NaoTransparente!$C$47 | G15: Indicador de decisão.
A16: LÍQUIDO DISPONÍVEL PARA O AGREGADO | C16: =V1_ENI_Simplificado!$C$45 | D16: =V2_ENI_ContOrg!$C$34 | E16: =V3_Soc_Transparente!$C$40 | F16: =V4_Soc_NaoTransparente!$C$48
A17: Diferencial face à via 1 (líquido para a sócia) | C17: =C15-$C$15 | D17: =D15-$C$15 | E17: =E15-$C$15 | F17: =F15-$C$15
A18: Via com maior líquido para a sócia | C18: =INDEX($C$5:$F$5,1,MATCH(MAX($C$15:$F$15),$C$15:$F$15,0))
A21: CENÁRIO BASE
A22: Indicador | C22: Via 1 — ENI simplificado | D22: Via 2 — ENI cont. organizada | E22: Via 3 — Soc. transparente | F22: Via 4 — Soc. não transparente | G22: Nota
A23: Caixa gerada pela atividade | C23: =V1_ENI_Simplificado!$D$39 | D23: =V2_ENI_ContOrg!$D$28 | E23: =V3_Soc_Transparente!$D$34 | F23: =V4_Soc_NaoTransparente!$D$42 | G23: Idêntica nas quatro vias, por construção.
A24: IRS imputável à atividade | C24: =V1_ENI_Simplificado!$D$36 | D24: =V2_ENI_ContOrg!$D$25 | E24: =V3_Soc_Transparente!$D$31 | F24: =V4_Soc_NaoTransparente!$D$38
A25: Segurança Social (todas as componentes) | C25: =V1_ENI_Simplificado!$D$23 | D25: =V2_ENI_ContOrg!$D$13 | E25: =V3_Soc_Transparente!$D$18+V3_Soc_Transparente!$D$12 | F25: =V4_Soc_NaoTransparente!$D$40+V4_Soc_NaoTransparente!$D$13 | G25: Vias 1 e 2: contribuição do trabalhador independente. Vias 3 e 4: contribuições do MOE, a cargo da sócia e da sociedade.
A26: IRC, derrama e tributações autónomas | C26: =0 | D26: =0 | E26: =V3_Soc_Transparente!$D$14+V3_Soc_Transparente!$D$15 | F26: =V4_Soc_NaoTransparente!$D$15+V4_Soc_NaoTransparente!$D$16+V4_Soc_NaoTransparente!$D$17
A27: Imposto sobre a distribuição | C27: =0 | D27: =0 | E27: =0 | F27: =V4_Soc_NaoTransparente!$D$27
A28: TOTAL DE IMPOSTOS E CONTRIBUIÇÕES | C28: =V1_ENI_Simplificado!$D$40 | D28: =V2_ENI_ContOrg!$D$29 | E28: =V3_Soc_Transparente!$D$35 | F28: =V4_Soc_NaoTransparente!$D$43
A29: Taxa de esforço sobre a caixa gerada | C29: =V1_ENI_Simplificado!$D$41 | D29: =V2_ENI_ContOrg!$D$30 | E29: =V3_Soc_Transparente!$D$36 | F29: =V4_Soc_NaoTransparente!$D$44
A30: Valor retido na sociedade | C30: =V1_ENI_Simplificado!$D$42 | D30: =V2_ENI_ContOrg!$D$31 | E30: =V3_Soc_Transparente!$D$37 | F30: =V4_Soc_NaoTransparente!$D$45 | G30: Não é perda, mas também não é liquidez da sócia. Tem de aparecer separado.
A31: Valor atribuído ao cônjuge | C31: =V1_ENI_Simplificado!$D$43 | D31: =V2_ENI_ContOrg!$D$32 | E31: =V3_Soc_Transparente!$D$38 | F31: =V4_Soc_NaoTransparente!$D$46
A32: LÍQUIDO DISPONÍVEL PARA A SÓCIA | C32: =V1_ENI_Simplificado!$D$44 | D32: =V2_ENI_ContOrg!$D$33 | E32: =V3_Soc_Transparente!$D$39 | F32: =V4_Soc_NaoTransparente!$D$47 | G32: Indicador de decisão.
A33: LÍQUIDO DISPONÍVEL PARA O AGREGADO | C33: =V1_ENI_Simplificado!$D$45 | D33: =V2_ENI_ContOrg!$D$34 | E33: =V3_Soc_Transparente!$D$40 | F33: =V4_Soc_NaoTransparente!$D$48
A34: Diferencial face à via 1 (líquido para a sócia) | C34: =C32-$C$32 | D34: =D32-$C$32 | E34: =E32-$C$32 | F34: =F32-$C$32
A35: Via com maior líquido para a sócia | C35: =INDEX($C$22:$F$22,1,MATCH(MAX($C$32:$F$32),$C$32:$F$32,0))
A38: CENÁRIO ALTO
A39: Indicador | C39: Via 1 — ENI simplificado | D39: Via 2 — ENI cont. organizada | E39: Via 3 — Soc. transparente | F39: Via 4 — Soc. não transparente | G39: Nota
A40: Caixa gerada pela atividade | C40: =V1_ENI_Simplificado!$E$39 | D40: =V2_ENI_ContOrg!$E$28 | E40: =V3_Soc_Transparente!$E$34 | F40: =V4_Soc_NaoTransparente!$E$42 | G40: Idêntica nas quatro vias, por construção.
A41: IRS imputável à atividade | C41: =V1_ENI_Simplificado!$E$36 | D41: =V2_ENI_ContOrg!$E$25 | E41: =V3_Soc_Transparente!$E$31 | F41: =V4_Soc_NaoTransparente!$E$38
A42: Segurança Social (todas as componentes) | C42: =V1_ENI_Simplificado!$E$23 | D42: =V2_ENI_ContOrg!$E$13 | E42: =V3_Soc_Transparente!$E$18+V3_Soc_Transparente!$E$12 | F42: =V4_Soc_NaoTransparente!$E$40+V4_Soc_NaoTransparente!$E$13 | G42: Vias 1 e 2: contribuição do trabalhador independente. Vias 3 e 4: contribuições do MOE, a cargo da sócia e da sociedade.
A43: IRC, derrama e tributações autónomas | C43: =0 | D43: =0 | E43: =V3_Soc_Transparente!$E$14+V3_Soc_Transparente!$E$15 | F43: =V4_Soc_NaoTransparente!$E$15+V4_Soc_NaoTransparente!$E$16+V4_Soc_NaoTransparente!$E$17
A44: Imposto sobre a distribuição | C44: =0 | D44: =0 | E44: =0 | F44: =V4_Soc_NaoTransparente!$E$27
A45: TOTAL DE IMPOSTOS E CONTRIBUIÇÕES | C45: =V1_ENI_Simplificado!$E$40 | D45: =V2_ENI_ContOrg!$E$29 | E45: =V3_Soc_Transparente!$E$35 | F45: =V4_Soc_NaoTransparente!$E$43
A46: Taxa de esforço sobre a caixa gerada | C46: =V1_ENI_Simplificado!$E$41 | D46: =V2_ENI_ContOrg!$E$30 | E46: =V3_Soc_Transparente!$E$36 | F46: =V4_Soc_NaoTransparente!$E$44
A47: Valor retido na sociedade | C47: =V1_ENI_Simplificado!$E$42 | D47: =V2_ENI_ContOrg!$E$31 | E47: =V3_Soc_Transparente!$E$37 | F47: =V4_Soc_NaoTransparente!$E$45 | G47: Não é perda, mas também não é liquidez da sócia. Tem de aparecer separado.
A48: Valor atribuído ao cônjuge | C48: =V1_ENI_Simplificado!$E$43 | D48: =V2_ENI_ContOrg!$E$32 | E48: =V3_Soc_Transparente!$E$38 | F48: =V4_Soc_NaoTransparente!$E$46
A49: LÍQUIDO DISPONÍVEL PARA A SÓCIA | C49: =V1_ENI_Simplificado!$E$44 | D49: =V2_ENI_ContOrg!$E$33 | E49: =V3_Soc_Transparente!$E$39 | F49: =V4_Soc_NaoTransparente!$E$47 | G49: Indicador de decisão.
A50: LÍQUIDO DISPONÍVEL PARA O AGREGADO | C50: =V1_ENI_Simplificado!$E$45 | D50: =V2_ENI_ContOrg!$E$34 | E50: =V3_Soc_Transparente!$E$40 | F50: =V4_Soc_NaoTransparente!$E$48
A51: Diferencial face à via 1 (líquido para a sócia) | C51: =C49-$C$49 | D51: =D49-$C$49 | E51: =E49-$C$49 | F51: =F49-$C$49
A52: Via com maior líquido para a sócia | C52: =INDEX($C$39:$F$39,1,MATCH(MAX($C$49:$F$49),$C$49:$F$49,0))
A55: Leitura obrigatória antes de citar qualquer número: os inputs são placeholders. Estes resultados demonstram que o motor funciona e indicam a direção do efeito; não são conclusões sobre o caso da Dra. Júlia.
A57: AVISO DE COERÊNCIA — o ano 1 não é o ano de cruzeiro
A58: Receita usada nesta comparação (ano de cruzeiro) | C58: =BreakEven!$D$6 | G58: Pressupõe a clínica à ocupação de regime permanente desde o primeiro dia.
A59: Faturação real do ano 1, com rampa de arranque | C59: =Tesouraria!$O$15 | G59: Da folha Tesouraria, que modela a subida mês a mês.
A60: Diferença | C60: =IF($C$58<=0,0,$C$59/$C$58-1) | G60: É por esta percentagem que o líquido do ano 1 fica abaixo dos valores da tabela acima.
A62: Os valores da tabela acima são de ANO DE CRUZEIRO. O primeiro ano é mais pobre, porque a clínica não abre cheia, e é também o ano do investimento. Dizer à cliente «com esta estrutura fica com X por ano» sem esta ressalva é criar uma expectativa que o primeiro ano não cumpre. O número do ano 1 está na folha Tesouraria; o desta tabela é o que ela passa a ter quando a clínica estabilizar.

Sheet PontoViragem
A1: M1 — Ponto de viragem do regime simplificado
A2: Responde à pergunta que a ata deixou em aberto: a partir de que nível de custos reais é que o regime simplificado deixa de compensar. Faturação fixada no cenário Base; varia-se o peso dos custos reais dedutíveis. Comparam-se apenas as vias 1 e 2, que é onde a questão se põe.
A4: Rendimento bruto (cenário Base) | C4: =(Inputs!$D$42+Inputs!$D$43)
A5: Rendimento do cônjuge | C5: =Inputs!$D$37
A6: Fator do quociente conjugal | C6: =IF(Inputs!$D$38=1,2,1)
A7: Coleta do agregado sem a atividade (constante) | C7: =$C$6*(SUMPRODUCT((($C$5/$C$6)>Parametros!$B$55:$B$63)*(($C$5/$C$6)-Parametros!$B$55:$B$63)*Parametros!$E$55:$E$63)+SUMPRODUCT((($C$5/$C$6)>Parametros!$B$67:$B$68)*(($C$5/$C$6)-Parametros!$B$67:$B$68)*Parametros!$E$67:$E$68)) | E7: Calculada uma só vez. Antes era recalculada em cada linha da tabela, o que tornava cada fórmula ilegível. Ver A1, ponto 2.
A9: % custos | B9: Custos reais | C9: Rend. líq. cat. B (via 1) | D9: SS via 1 | E9: IRS via 1 | F9: Carga via 1 | G9: Lucro tribut. (via 2) | H9: SS via 2 | I9: IRS via 2 | J9: Carga via 2 | K9: Diferencial | L9: Viragem | M9: RC ajustado v1 | N9: RC ajustado v2
A10: 0.05 | B10: =$C$4*A10 | C10: =$C$4*Parametros!$C$24+MAX(0,$C$4*Parametros!$C$25-(Parametros!$C$26+B10))-MAX(0,D10-$C$4*Parametros!$C$27) | D10: =MAX(MIN($C$4*Parametros!$C$7,Parametros!$C$6*Parametros!$C$9*12)*Parametros!$C$8,Parametros!$C$10*12) | E10: =$C$6*(SUMPRODUCT((M10>Parametros!$B$55:$B$63)*(M10-Parametros!$B$55:$B$63)*Parametros!$E$55:$E$63)+SUMPRODUCT((M10>Parametros!$B$67:$B$68)*(M10-Parametros!$B$67:$B$68)*Parametros!$E$67:$E$68))-$C$7 | F10: =D10+E10 | G10: =MAX(0,$C$4-B10-H10) | H10: =MAX(MIN(MAX($C$4-B10,0),Parametros!$C$6*Parametros!$C$9*12)*Parametros!$C$8,Parametros!$C$10*12) | I10: =$C$6*(SUMPRODUCT((N10>Parametros!$B$55:$B$63)*(N10-Parametros!$B$55:$B$63)*Parametros!$E$55:$E$63)+SUMPRODUCT((N10>Parametros!$B$67:$B$68)*(N10-Parametros!$B$67:$B$68)*Parametros!$E$67:$E$68))-$C$7 | J10: =H10+I10 | K10: =F10-J10 | L10: =0 | M10: =(C10+$C$5)/$C$6 | N10: =(G10+$C$5)/$C$6
A11: 0.1 | B11: =$C$4*A11 | C11: =$C$4*Parametros!$C$24+MAX(0,$C$4*Parametros!$C$25-(Parametros!$C$26+B11))-MAX(0,D11-$C$4*Parametros!$C$27) | D11: =MAX(MIN($C$4*Parametros!$C$7,Parametros!$C$6*Parametros!$C$9*12)*Parametros!$C$8,Parametros!$C$10*12) | E11: =$C$6*(SUMPRODUCT((M11>Parametros!$B$55:$B$63)*(M11-Parametros!$B$55:$B$63)*Parametros!$E$55:$E$63)+SUMPRODUCT((M11>Parametros!$B$67:$B$68)*(M11-Parametros!$B$67:$B$68)*Parametros!$E$67:$E$68))-$C$7 | F11: =D11+E11 | G11: =MAX(0,$C$4-B11-H11) | H11: =MAX(MIN(MAX($C$4-B11,0),Parametros!$C$6*Parametros!$C$9*12)*Parametros!$C$8,Parametros!$C$10*12) | I11: =$C$6*(SUMPRODUCT((N11>Parametros!$B$55:$B$63)*(N11-Parametros!$B$55:$B$63)*Parametros!$E$55:$E$63)+SUMPRODUCT((N11>Parametros!$B$67:$B$68)*(N11-Parametros!$B$67:$B$68)*Parametros!$E$67:$E$68))-$C$7 | J11: =H11+I11 | K11: =F11-J11 | L11: =IF(AND(K11>=0,K10<0),A11,0) | M11: =(C11+$C$5)/$C$6 | N11: =(G11+$C$5)/$C$6
A12: 0.15 | B12: =$C$4*A12 | C12: =$C$4*Parametros!$C$24+MAX(0,$C$4*Parametros!$C$25-(Parametros!$C$26+B12))-MAX(0,D12-$C$4*Parametros!$C$27) | D12: =MAX(MIN($C$4*Parametros!$C$7,Parametros!$C$6*Parametros!$C$9*12)*Parametros!$C$8,Parametros!$C$10*12) | E12: =$C$6*(SUMPRODUCT((M12>Parametros!$B$55:$B$63)*(M12-Parametros!$B$55:$B$63)*Parametros!$E$55:$E$63)+SUMPRODUCT((M12>Parametros!$B$67:$B$68)*(M12-Parametros!$B$67:$B$68)*Parametros!$E$67:$E$68))-$C$7 | F12: =D12+E12 | G12: =MAX(0,$C$4-B12-H12) | H12: =MAX(MIN(MAX($C$4-B12,0),Parametros!$C$6*Parametros!$C$9*12)*Parametros!$C$8,Parametros!$C$10*12) | I12: =$C$6*(SUMPRODUCT((N12>Parametros!$B$55:$B$63)*(N12-Parametros!$B$55:$B$63)*Parametros!$E$55:$E$63)+SUMPRODUCT((N12>Parametros!$B$67:$B$68)*(N12-Parametros!$B$67:$B$68)*Parametros!$E$67:$E$68))-$C$7 | J12: =H12+I12 | K12: =F12-J12 | L12: =IF(AND(K12>=0,K11<0),A12,0) | M12: =(C12+$C$5)/$C$6 | N12: =(G12+$C$5)/$C$6
A13: 0.2 | B13: =$C$4*A13 | C13: =$C$4*Parametros!$C$24+MAX(0,$C$4*Parametros!$C$25-(Parametros!$C$26+B13))-MAX(0,D13-$C$4*Parametros!$C$27) | D13: =MAX(MIN($C$4*Parametros!$C$7,Parametros!$C$6*Parametros!$C$9*12)*Parametros!$C$8,Parametros!$C$10*12) | E13: =$C$6*(SUMPRODUCT((M13>Parametros!$B$55:$B$63)*(M13-Parametros!$B$55:$B$63)*Parametros!$E$55:$E$63)+SUMPRODUCT((M13>Parametros!$B$67:$B$68)*(M13-Parametros!$B$67:$B$68)*Parametros!$E$67:$E$68))-$C$7 | F13: =D13+E13 | G13: =MAX(0,$C$4-B13-H13) | H13: =MAX(MIN(MAX($C$4-B13,0),Parametros!$C$6*Parametros!$C$9*12)*Parametros!$C$8,Parametros!$C$10*12) | I13: =$C$6*(SUMPRODUCT((N13>Parametros!$B$55:$B$63)*(N13-Parametros!$B$55:$B$63)*Parametros!$E$55:$E$63)+SUMPRODUCT((N13>Parametros!$B$67:$B$68)*(N13-Parametros!$B$67:$B$68)*Parametros!$E$67:$E$68))-$C$7 | J13: =H13+I13 | K13: =F13-J13 | L13: =IF(AND(K13>=0,K12<0),A13,0) | M13: =(C13+$C$5)/$C$6 | N13: =(G13+$C$5)/$C$6
A14: 0.25 | B14: =$C$4*A14 | C14: =$C$4*Parametros!$C$24+MAX(0,$C$4*Parametros!$C$25-(Parametros!$C$26+B14))-MAX(0,D14-$C$4*Parametros!$C$27) | D14: =MAX(MIN($C$4*Parametros!$C$7,Parametros!$C$6*Parametros!$C$9*12)*Parametros!$C$8,Parametros!$C$10*12) | E14: =$C$6*(SUMPRODUCT((M14>Parametros!$B$55:$B$63)*(M14-Parametros!$B$55:$B$63)*Parametros!$E$55:$E$63)+SUMPRODUCT((M14>Parametros!$B$67:$B$68)*(M14-Parametros!$B$67:$B$68)*Parametros!$E$67:$E$68))-$C$7 | F14: =D14+E14 | G14: =MAX(0,$C$4-B14-H14) | H14: =MAX(MIN(MAX($C$4-B14,0),Parametros!$C$6*Parametros!$C$9*12)*Parametros!$C$8,Parametros!$C$10*12) | I14: =$C$6*(SUMPRODUCT((N14>Parametros!$B$55:$B$63)*(N14-Parametros!$B$55:$B$63)*Parametros!$E$55:$E$63)+SUMPRODUCT((N14>Parametros!$B$67:$B$68)*(N14-Parametros!$B$67:$B$68)*Parametros!$E$67:$E$68))-$C$7 | J14: =H14+I14 | K14: =F14-J14 | L14: =IF(AND(K14>=0,K13<0),A14,0) | M14: =(C14+$C$5)/$C$6 | N14: =(G14+$C$5)/$C$6
A15: 0.3 | B15: =$C$4*A15 | C15: =$C$4*Parametros!$C$24+MAX(0,$C$4*Parametros!$C$25-(Parametros!$C$26+B15))-MAX(0,D15-$C$4*Parametros!$C$27) | D15: =MAX(MIN($C$4*Parametros!$C$7,Parametros!$C$6*Parametros!$C$9*12)*Parametros!$C$8,Parametros!$C$10*12) | E15: =$C$6*(SUMPRODUCT((M15>Parametros!$B$55:$B$63)*(M15-Parametros!$B$55:$B$63)*Parametros!$E$55:$E$63)+SUMPRODUCT((M15>Parametros!$B$67:$B$68)*(M15-Parametros!$B$67:$B$68)*Parametros!$E$67:$E$68))-$C$7 | F15: =D15+E15 | G15: =MAX(0,$C$4-B15-H15) | H15: =MAX(MIN(MAX($C$4-B15,0),Parametros!$C$6*Parametros!$C$9*12)*Parametros!$C$8,Parametros!$C$10*12) | I15: =$C$6*(SUMPRODUCT((N15>Parametros!$B$55:$B$63)*(N15-Parametros!$B$55:$B$63)*Parametros!$E$55:$E$63)+SUMPRODUCT((N15>Parametros!$B$67:$B$68)*(N15-Parametros!$B$67:$B$68)*Parametros!$E$67:$E$68))-$C$7 | J15: =H15+I15 | K15: =F15-J15 | L15: =IF(AND(K15>=0,K14<0),A15,0) | M15: =(C15+$C$5)/$C$6 | N15: =(G15+$C$5)/$C$6
A16: 0.35 | B16: =$C$4*A16 | C16: =$C$4*Parametros!$C$24+MAX(0,$C$4*Parametros!$C$25-(Parametros!$C$26+B16))-MAX(0,D16-$C$4*Parametros!$C$27) | D16: =MAX(MIN($C$4*Parametros!$C$7,Parametros!$C$6*Parametros!$C$9*12)*Parametros!$C$8,Parametros!$C$10*12) | E16: =$C$6*(SUMPRODUCT((M16>Parametros!$B$55:$B$63)*(M16-Parametros!$B$55:$B$63)*Parametros!$E$55:$E$63)+SUMPRODUCT((M16>Parametros!$B$67:$B$68)*(M16-Parametros!$B$67:$B$68)*Parametros!$E$67:$E$68))-$C$7 | F16: =D16+E16 | G16: =MAX(0,$C$4-B16-H16) | H16: =MAX(MIN(MAX($C$4-B16,0),Parametros!$C$6*Parametros!$C$9*12)*Parametros!$C$8,Parametros!$C$10*12) | I16: =$C$6*(SUMPRODUCT((N16>Parametros!$B$55:$B$63)*(N16-Parametros!$B$55:$B$63)*Parametros!$E$55:$E$63)+SUMPRODUCT((N16>Parametros!$B$67:$B$68)*(N16-Parametros!$B$67:$B$68)*Parametros!$E$67:$E$68))-$C$7 | J16: =H16+I16 | K16: =F16-J16 | L16: =IF(AND(K16>=0,K15<0),A16,0) | M16: =(C16+$C$5)/$C$6 | N16: =(G16+$C$5)/$C$6
A17: 0.4 | B17: =$C$4*A17 | C17: =$C$4*Parametros!$C$24+MAX(0,$C$4*Parametros!$C$25-(Parametros!$C$26+B17))-MAX(0,D17-$C$4*Parametros!$C$27) | D17: =MAX(MIN($C$4*Parametros!$C$7,Parametros!$C$6*Parametros!$C$9*12)*Parametros!$C$8,Parametros!$C$10*12) | E17: =$C$6*(SUMPRODUCT((M17>Parametros!$B$55:$B$63)*(M17-Parametros!$B$55:$B$63)*Parametros!$E$55:$E$63)+SUMPRODUCT((M17>Parametros!$B$67:$B$68)*(M17-Parametros!$B$67:$B$68)*Parametros!$E$67:$E$68))-$C$7 | F17: =D17+E17 | G17: =MAX(0,$C$4-B17-H17) | H17: =MAX(MIN(MAX($C$4-B17,0),Parametros!$C$6*Parametros!$C$9*12)*Parametros!$C$8,Parametros!$C$10*12) | I17: =$C$6*(SUMPRODUCT((N17>Parametros!$B$55:$B$63)*(N17-Parametros!$B$55:$B$63)*Parametros!$E$55:$E$63)+SUMPRODUCT((N17>Parametros!$B$67:$B$68)*(N17-Parametros!$B$67:$B$68)*Parametros!$E$67:$E$68))-$C$7 | J17: =H17+I17 | K17: =F17-J17 | L17: =IF(AND(K17>=0,K16<0),A17,0) | M17: =(C17+$C$5)/$C$6 | N17: =(G17+$C$5)/$C$6
A18: 0.45 | B18: =$C$4*A18 | C18: =$C$4*Parametros!$C$24+MAX(0,$C$4*Parametros!$C$25-(Parametros!$C$26+B18))-MAX(0,D18-$C$4*Parametros!$C$27) | D18: =MAX(MIN($C$4*Parametros!$C$7,Parametros!$C$6*Parametros!$C$9*12)*Parametros!$C$8,Parametros!$C$10*12) | E18: =$C$6*(SUMPRODUCT((M18>Parametros!$B$55:$B$63)*(M18-Parametros!$B$55:$B$63)*Parametros!$E$55:$E$63)+SUMPRODUCT((M18>Parametros!$B$67:$B$68)*(M18-Parametros!$B$67:$B$68)*Parametros!$E$67:$E$68))-$C$7 | F18: =D18+E18 | G18: =MAX(0,$C$4-B18-H18) | H18: =MAX(MIN(MAX($C$4-B18,0),Parametros!$C$6*Parametros!$C$9*12)*Parametros!$C$8,Parametros!$C$10*12) | I18: =$C$6*(SUMPRODUCT((N18>Parametros!$B$55:$B$63)*(N18-Parametros!$B$55:$B$63)*Parametros!$E$55:$E$63)+SUMPRODUCT((N18>Parametros!$B$67:$B$68)*(N18-Parametros!$B$67:$B$68)*Parametros!$E$67:$E$68))-$C$7 | J18: =H18+I18 | K18: =F18-J18 | L18: =IF(AND(K18>=0,K17<0),A18,0) | M18: =(C18+$C$5)/$C$6 | N18: =(G18+$C$5)/$C$6
A19: 0.5 | B19: =$C$4*A19 | C19: =$C$4*Parametros!$C$24+MAX(0,$C$4*Parametros!$C$25-(Parametros!$C$26+B19))-MAX(0,D19-$C$4*Parametros!$C$27) | D19: =MAX(MIN($C$4*Parametros!$C$7,Parametros!$C$6*Parametros!$C$9*12)*Parametros!$C$8,Parametros!$C$10*12) | E19: =$C$6*(SUMPRODUCT((M19>Parametros!$B$55:$B$63)*(M19-Parametros!$B$55:$B$63)*Parametros!$E$55:$E$63)+SUMPRODUCT((M19>Parametros!$B$67:$B$68)*(M19-Parametros!$B$67:$B$68)*Parametros!$E$67:$E$68))-$C$7 | F19: =D19+E19 | G19: =MAX(0,$C$4-B19-H19) | H19: =MAX(MIN(MAX($C$4-B19,0),Parametros!$C$6*Parametros!$C$9*12)*Parametros!$C$8,Parametros!$C$10*12) | I19: =$C$6*(SUMPRODUCT((N19>Parametros!$B$55:$B$63)*(N19-Parametros!$B$55:$B$63)*Parametros!$E$55:$E$63)+SUMPRODUCT((N19>Parametros!$B$67:$B$68)*(N19-Parametros!$B$67:$B$68)*Parametros!$E$67:$E$68))-$C$7 | J19: =H19+I19 | K19: =F19-J19 | L19: =IF(AND(K19>=0,K18<0),A19,0) | M19: =(C19+$C$5)/$C$6 | N19: =(G19+$C$5)/$C$6
A20: 0.55 | B20: =$C$4*A20 | C20: =$C$4*Parametros!$C$24+MAX(0,$C$4*Parametros!$C$25-(Parametros!$C$26+B20))-MAX(0,D20-$C$4*Parametros!$C$27) | D20: =MAX(MIN($C$4*Parametros!$C$7,Parametros!$C$6*Parametros!$C$9*12)*Parametros!$C$8,Parametros!$C$10*12) | E20: =$C$6*(SUMPRODUCT((M20>Parametros!$B$55:$B$63)*(M20-Parametros!$B$55:$B$63)*Parametros!$E$55:$E$63)+SUMPRODUCT((M20>Parametros!$B$67:$B$68)*(M20-Parametros!$B$67:$B$68)*Parametros!$E$67:$E$68))-$C$7 | F20: =D20+E20 | G20: =MAX(0,$C$4-B20-H20) | H20: =MAX(MIN(MAX($C$4-B20,0),Parametros!$C$6*Parametros!$C$9*12)*Parametros!$C$8,Parametros!$C$10*12) | I20: =$C$6*(SUMPRODUCT((N20>Parametros!$B$55:$B$63)*(N20-Parametros!$B$55:$B$63)*Parametros!$E$55:$E$63)+SUMPRODUCT((N20>Parametros!$B$67:$B$68)*(N20-Parametros!$B$67:$B$68)*Parametros!$E$67:$E$68))-$C$7 | J20: =H20+I20 | K20: =F20-J20 | L20: =IF(AND(K20>=0,K19<0),A20,0) | M20: =(C20+$C$5)/$C$6 | N20: =(G20+$C$5)/$C$6
A21: 0.6 | B21: =$C$4*A21 | C21: =$C$4*Parametros!$C$24+MAX(0,$C$4*Parametros!$C$25-(Parametros!$C$26+B21))-MAX(0,D21-$C$4*Parametros!$C$27) | D21: =MAX(MIN($C$4*Parametros!$C$7,Parametros!$C$6*Parametros!$C$9*12)*Parametros!$C$8,Parametros!$C$10*12) | E21: =$C$6*(SUMPRODUCT((M21>Parametros!$B$55:$B$63)*(M21-Parametros!$B$55:$B$63)*Parametros!$E$55:$E$63)+SUMPRODUCT((M21>Parametros!$B$67:$B$68)*(M21-Parametros!$B$67:$B$68)*Parametros!$E$67:$E$68))-$C$7 | F21: =D21+E21 | G21: =MAX(0,$C$4-B21-H21) | H21: =MAX(MIN(MAX($C$4-B21,0),Parametros!$C$6*Parametros!$C$9*12)*Parametros!$C$8,Parametros!$C$10*12) | I21: =$C$6*(SUMPRODUCT((N21>Parametros!$B$55:$B$63)*(N21-Parametros!$B$55:$B$63)*Parametros!$E$55:$E$63)+SUMPRODUCT((N21>Parametros!$B$67:$B$68)*(N21-Parametros!$B$67:$B$68)*Parametros!$E$67:$E$68))-$C$7 | J21: =H21+I21 | K21: =F21-J21 | L21: =IF(AND(K21>=0,K20<0),A21,0) | M21: =(C21+$C$5)/$C$6 | N21: =(G21+$C$5)/$C$6
A22: 0.65 | B22: =$C$4*A22 | C22: =$C$4*Parametros!$C$24+MAX(0,$C$4*Parametros!$C$25-(Parametros!$C$26+B22))-MAX(0,D22-$C$4*Parametros!$C$27) | D22: =MAX(MIN($C$4*Parametros!$C$7,Parametros!$C$6*Parametros!$C$9*12)*Parametros!$C$8,Parametros!$C$10*12) | E22: =$C$6*(SUMPRODUCT((M22>Parametros!$B$55:$B$63)*(M22-Parametros!$B$55:$B$63)*Parametros!$E$55:$E$63)+SUMPRODUCT((M22>Parametros!$B$67:$B$68)*(M22-Parametros!$B$67:$B$68)*Parametros!$E$67:$E$68))-$C$7 | F22: =D22+E22 | G22: =MAX(0,$C$4-B22-H22) | H22: =MAX(MIN(MAX($C$4-B22,0),Parametros!$C$6*Parametros!$C$9*12)*Parametros!$C$8,Parametros!$C$10*12) | I22: =$C$6*(SUMPRODUCT((N22>Parametros!$B$55:$B$63)*(N22-Parametros!$B$55:$B$63)*Parametros!$E$55:$E$63)+SUMPRODUCT((N22>Parametros!$B$67:$B$68)*(N22-Parametros!$B$67:$B$68)*Parametros!$E$67:$E$68))-$C$7 | J22: =H22+I22 | K22: =F22-J22 | L22: =IF(AND(K22>=0,K21<0),A22,0) | M22: =(C22+$C$5)/$C$6 | N22: =(G22+$C$5)/$C$6
... A24: 0.75 | B24: =$C$4*A24 | C24: =$C$4*Parametros!$C$24+MAX(0,$C$4*Parametros!$C$25-(Parametros!$C$26+B24))-MAX(0,D24-$C$4*Parametros!$C$27) | D24: =MAX(MIN($C$4*Parametros!$C$7,Parametros!$C$6*Parametros!$C$9*12)*Parametros!$C$8,Parametros!$C$10*12) | E24: =$C$6*(SUMPRODUCT((M24>Parametros!$B$55:$B$63)*(M24-Parametros!$B$55:$B$63)*Parametros!$E$55:$E$63)+SUMPRODUCT((M24>Parametros!$B$67:$B$68)*(M24-Parametros!$B$67:$B$68)*Parametros!$E$67:$E$68))-$C$7 | F24: =D24+E24 | G24: =MAX(0,$C$4-B24-H24) | H24: =MAX(MIN(MAX($C$4-B24,0),Parametros!$C$6*Parametros!$C$9*12)*Parametros!$C$8,Parametros!$C$10*12) | I24: =$C$6*(SUMPRODUCT((N24>Parametros!$B$55:$B$63)*(N24-Parametros!$B$55:$B$63)*Parametros!$E$55:$E$63)+SUMPRODUCT((N24>Parametros!$B$67:$B$68)*(N24-Parametros!$B$67:$B$68)*Parametros!$E$67:$E$68))-$C$7 | J24: =H24+I24 | K24: =F24-J24 | L24: =IF(AND(K24>=0,K23<0),A24,0) | M24: =(C24+$C$5)/$C$6 | N24: =(G24+$C$5)/$C$6
A26: Ponto de viragem — peso dos custos reais | C26: =MAX(L10:L24) | E26: Acima deste peso de custos, a contabilidade organizada passa a entregar mais líquido. Resolução de 5 pontos percentuais — refinar por interpolação se o valor cair perto de um limite.
A27: Ponto de viragem — em euros de custos anuais | C27: =C26*$C$4
A29: Simplificação assumida nesta folha: os custos reais são simultaneamente dedutíveis na via 2 e justificáveis na via 1. No caso concreto as duas bases não coincidem exatamente (amortizações versus aquisições do ano). O ponto de viragem apurado é, por isso, conservador — a via 2 tende a virar mais cedo do que aqui aparece. Registado em R1-09.

Sheet BreakEven
A1: M1 — Break-even operacional e rendimento-alvo
A2: Três coisas diferentes que a mesma palavra designa. O break-even FISCAL, na folha PontoViragem, diz quando uma estrutura passa a ser melhor que outra. O break-even OPERACIONAL, aqui em cima, diz quando a clínica cobre os custos. O RENDIMENTO-ALVO, aqui em baixo, diz quanto é preciso faturar para a fundadora receber o que quer receber. Nunca misturar as três numa frase.
A4: Rubrica | B4: Ref. | C4: Baixo | D4: Base | E4: Alto | F4: Nota
A5: Break-even operacional
A6: Receita da estrutura | B6: REC | C6: =Inputs!$C$42+Inputs!$C$43 | D6: =Inputs!$D$42+Inputs!$D$43 | E6: =Inputs!$E$42+Inputs!$E$43
A7: Custos variáveis | B7: CV | C7: =Inputs!$C$24+Inputs!$C$44 | D7: =Inputs!$D$24+Inputs!$D$44 | E7: =Inputs!$E$24+Inputs!$E$44 | F7: Consumíveis e honorários dos colaboradores. Acompanham o volume.
A8: Margem de contribuição | B8: MC | C8: =$C$6-$C$7 | D8: =$D$6-$D$7 | E8: =$E$6-$E$7
A9: Margem de contribuição (%) | B9: MCP | C9: =IF($C$6<=0,0,$C$8/$C$6) | D9: =IF($D$6<=0,0,$D$8/$D$6) | E9: =IF($E$6<=0,0,$E$8/$E$6) | F9: É o denominador do break-even. No modelo de prestação de serviços, a % de honorários esmaga esta linha — e é por isso que a ata avisa que faturação não é margem.
A10: Custos fixos | B10: CF | C10: =Inputs!$C$19+Inputs!$C$20+Inputs!$C$21+Inputs!$C$22+Inputs!$C$25 | D10: =Inputs!$D$19+Inputs!$D$20+Inputs!$D$21+Inputs!$D$22+Inputs!$D$25 | E10: =Inputs!$E$19+Inputs!$E$20+Inputs!$E$21+Inputs!$E$22+Inputs!$E$25 | F10: Base de caixa: exclui amortizações, que não são saída de dinheiro.
A11: BREAK-EVEN OPERACIONAL (faturação anual) | B11: BE | C11: =IF($C$9<=0,0,$C$10/$C$9) | D11: =IF($D$9<=0,0,$D$10/$D$9) | E11: =IF($E$9<=0,0,$E$10/$E$9)
A12: Break-even operacional (faturação mensal) | B12: BE_MES | C12: =$C$11/12 | D12: =$D$11/12 | E12: =$E$11/12 | F12: É este o número para dizer à cliente. Ninguém pensa em faturação anual.
A13: Margem de segurança sobre a receita projetada | B13: MARG_SEG | C13: =IF($C$6<=0,0,($C$6-$C$11)/$C$6) | D13: =IF($D$6<=0,0,($D$6-$D$11)/$D$6) | E13: =IF($E$6<=0,0,($E$6-$E$11)/$E$6) | F13: Negativa significa que a projeção não cobre os custos fixos.
A14: Preço médio por consulta | B14: PRECO_M | C14: =IF(Operacao!$C$25<=0,0,Operacao!$C$31/Operacao!$C$25) | D14: =IF(Operacao!$D$25<=0,0,Operacao!$D$31/Operacao!$D$25) | E14: =IF(Operacao!$E$25<=0,0,Operacao!$E$31/Operacao!$E$25)
A15: Consultas anuais necessárias para o break-even | B15: CONS_BE | C15: =IF($C$14<=0,0,$C$11/$C$14) | D15: =IF($D$14<=0,0,$D$11/$D$14) | E15: =IF($E$14<=0,0,$E$11/$E$14)
A16: UTILIZAÇÃO DOS GABINETES NECESSÁRIA PARA O BREAK-EVEN | B16: UTIL_BE | C16: =IF(Operacao!$C$21<=0,0,$C$15/Operacao!$C$21) | D16: =IF(Operacao!$D$21<=0,0,$D$15/Operacao!$D$21) | E16: =IF(Operacao!$E$21<=0,0,$E$15/Operacao!$E$21) | F16: Acima de 100% significa que o espaço escolhido não permite cobrir os seus próprios custos fixos, seja qual for a estrutura fiscal. É a verificação de plausibilidade empresarial.
A18: Rendimento-alvo da fundadora
A19: Rendimento anual líquido pretendido pela fundadora | C19: 30000 | F19: Ação 0.8 do P1. É o input que a cliente não sabe que tem de dar, e é o que decide entre a via 3 e a via 4.
A21: Fator do quociente conjugal | C21: =IF(Inputs!$D$38=1,2,1)
A22: Coleta do agregado sem a atividade (constante) | C22: =$C$21*(SUMPRODUCT(((Inputs!$D$37/$C$21)>Parametros!$B$55:$B$63)*((Inputs!$D$37/$C$21)-Parametros!$B$55:$B$63)*Parametros!$E$55:$E$63)+SUMPRODUCT(((Inputs!$D$37/$C$21)>Parametros!$B$67:$B$68)*((Inputs!$D$37/$C$21)-Parametros!$B$67:$B$68)*Parametros!$E$67:$E$68))
A24: Faturação necessária para atingir o rendimento-alvo, por estrutura. Custos fixos e peso dos custos variáveis fixados no cenário Base. Resolução de 10.000 €.
A25: Faturação | B25: Custos | C25: Caixa | D25: Rend. cat. B (v1) | E25: SS v1 | F25: IRS v1 | G25: LÍQUIDO v1 | H25: Lucro trib. (v2) | I25: SS v2 | J25: IRS v2 | K25: LÍQUIDO v2 | L25: Lucro trib. (v3) | M25: Rend. sócia (v3) | N25: IRS v3 | O25: LÍQUIDO v3 | P25: Alvo v1 | Q25: Alvo v2 | R25: Alvo v3 | S25: RC ajust. v1 | T25: RC ajust. v2 | U25: RC ajust. v3
A26: 40000 | B26: =($D$10)+A26*(1-$D$9) | C26: =A26-B26 | D26: =A26*Parametros!$C$24+MAX(0,A26*Parametros!$C$25-B26)-MAX(0,E26-A26*Parametros!$C$27) | E26: =MAX(MIN(A26*Parametros!$C$7,Parametros!$C$6*Parametros!$C$9*12)*Parametros!$C$8,Parametros!$C$10*12) | F26: =$C$21*(SUMPRODUCT((S26>Parametros!$B$55:$B$63)*(S26-Parametros!$B$55:$B$63)*Parametros!$E$55:$E$63)+SUMPRODUCT((S26>Parametros!$B$67:$B$68)*(S26-Parametros!$B$67:$B$68)*Parametros!$E$67:$E$68))-$C$22 | G26: =C26-E26-F26 | H26: =MAX(0,A26-B26-(Inputs!$D$27*Parametros!$C$44+(Inputs!$D$28+Inputs!$D$29)*Parametros!$C$45+Inputs!$D$30*Parametros!$C$46)-I26) | I26: =MAX(MIN(MAX(A26-B26-(Inputs!$D$27*Parametros!$C$44+(Inputs!$D$28+Inputs!$D$29)*Parametros!$C$45+Inputs!$D$30*Parametros!$C$46),0),Parametros!$C$6*Parametros!$C$9*12)*Parametros!$C$8,Parametros!$C$10*12) | J26: =$C$21*(SUMPRODUCT((T26>Parametros!$B$55:$B$63)*(T26-Parametros!$B$55:$B$63)*Parametros!$E$55:$E$63)+SUMPRODUCT((T26>Parametros!$B$67:$B$68)*(T26-Parametros!$B$67:$B$68)*Parametros!$E$67:$E$68))-$C$22 | K26: =C26-I26-J26 | L26: =A26-B26-(Inputs!$D$27*Parametros!$C$44+(Inputs!$D$28+Inputs!$D$29)*Parametros!$C$45+Inputs!$D$30*Parametros!$C$46)-(Inputs!$D$32)-((MAX(Inputs!$D$32,Parametros!$C$6*Parametros!$C$13*12))*Parametros!$C$11) | M26: =MAX(0,(Inputs!$D$32)-MIN((Inputs!$D$32),MAX(Parametros!$C$30,(MAX(Inputs!$D$32,Parametros!$C$6*Parametros!$C$13*12))*Parametros!$C$12)))+MAX(L26,0) | N26: =$C$21*(SUMPRODUCT((U26>Parametros!$B$55:$B$63)*(U26-Parametros!$B$55:$B$63)*Parametros!$E$55:$E$63)+SUMPRODUCT((U26>Parametros!$B$67:$B$68)*(U26-Parametros!$B$67:$B$68)*Parametros!$E$67:$E$68))-$C$22 | O26: =C26-((MAX(Inputs!$D$32,Parametros!$C$6*Parametros!$C$13*12))*Parametros!$C$12)-((MAX(Inputs!$D$32,Parametros!$C$6*Parametros!$C$13*12))*Parametros!$C$11)-(Inputs!$D$33)-N26 | P26: =0 | Q26: =0 | R26: =0 | S26: =(D26+Inputs!$D$37)/$C$21 | T26: =(H26+Inputs!$D$37)/$C$21 | U26: =(M26+Inputs!$D$37)/$C$21
A27: 50000 | B27: =($D$10)+A27*(1-$D$9) | C27: =A27-B27 | D27: =A27*Parametros!$C$24+MAX(0,A27*Parametros!$C$25-B27)-MAX(0,E27-A27*Parametros!$C$27) | E27: =MAX(MIN(A27*Parametros!$C$7,Parametros!$C$6*Parametros!$C$9*12)*Parametros!$C$8,Parametros!$C$10*12) | F27: =$C$21*(SUMPRODUCT((S27>Parametros!$B$55:$B$63)*(S27-Parametros!$B$55:$B$63)*Parametros!$E$55:$E$63)+SUMPRODUCT((S27>Parametros!$B$67:$B$68)*(S27-Parametros!$B$67:$B$68)*Parametros!$E$67:$E$68))-$C$22 | G27: =C27-E27-F27 | H27: =MAX(0,A27-B27-(Inputs!$D$27*Parametros!$C$44+(Inputs!$D$28+Inputs!$D$29)*Parametros!$C$45+Inputs!$D$30*Parametros!$C$46)-I27) | I27: =MAX(MIN(MAX(A27-B27-(Inputs!$D$27*Parametros!$C$44+(Inputs!$D$28+Inputs!$D$29)*Parametros!$C$45+Inputs!$D$30*Parametros!$C$46),0),Parametros!$C$6*Parametros!$C$9*12)*Parametros!$C$8,Parametros!$C$10*12) | J27: =$C$21*(SUMPRODUCT((T27>Parametros!$B$55:$B$63)*(T27-Parametros!$B$55:$B$63)*Parametros!$E$55:$E$63)+SUMPRODUCT((T27>Parametros!$B$67:$B$68)*(T27-Parametros!$B$67:$B$68)*Parametros!$E$67:$E$68))-$C$22 | K27: =C27-I27-J27 | L27: =A27-B27-(Inputs!$D$27*Parametros!$C$44+(Inputs!$D$28+Inputs!$D$29)*Parametros!$C$45+Inputs!$D$30*Parametros!$C$46)-(Inputs!$D$32)-((MAX(Inputs!$D$32,Parametros!$C$6*Parametros!$C$13*12))*Parametros!$C$11) | M27: =MAX(0,(Inputs!$D$32)-MIN((Inputs!$D$32),MAX(Parametros!$C$30,(MAX(Inputs!$D$32,Parametros!$C$6*Parametros!$C$13*12))*Parametros!$C$12)))+MAX(L27,0) | N27: =$C$21*(SUMPRODUCT((U27>Parametros!$B$55:$B$63)*(U27-Parametros!$B$55:$B$63)*Parametros!$E$55:$E$63)+SUMPRODUCT((U27>Parametros!$B$67:$B$68)*(U27-Parametros!$B$67:$B$68)*Parametros!$E$67:$E$68))-$C$22 | O27: =C27-((MAX(Inputs!$D$32,Parametros!$C$6*Parametros!$C$13*12))*Parametros!$C$12)-((MAX(Inputs!$D$32,Parametros!$C$6*Parametros!$C$13*12))*Parametros!$C$11)-(Inputs!$D$33)-N27 | P27: =IF(AND(G27>=$C$19,G26<$C$19),A27,0) | Q27: =IF(AND(K27>=$C$19,K26<$C$19),A27,0) | R27: =IF(AND(O27>=$C$19,O26<$C$19),A27,0) | S27: =(D27+Inputs!$D$37)/$C$21 | T27: =(H27+Inputs!$D$37)/$C$21 | U27: =(M27+Inputs!$D$37)/$C$21
A28: 60000 | B28: =($D$10)+A28*(1-$D$9) | C28: =A28-B28 | D28: =A28*Parametros!$C$24+MAX(0,A28*Parametros!$C$25-B28)-MAX(0,E28-A28*Parametros!$C$27) | E28: =MAX(MIN(A28*Parametros!$C$7,Parametros!$C$6*Parametros!$C$9*12)*Parametros!$C$8,Parametros!$C$10*12) | F28: =$C$21*(SUMPRODUCT((S28>Parametros!$B$55:$B$63)*(S28-Parametros!$B$55:$B$63)*Parametros!$E$55:$E$63)+SUMPRODUCT((S28>Parametros!$B$67:$B$68)*(S28-Parametros!$B$67:$B$68)*Parametros!$E$67:$E$68))-$C$22 | G28: =C28-E28-F28 | H28: =MAX(0,A28-B28-(Inputs!$D$27*Parametros!$C$44+(Inputs!$D$28+Inputs!$D$29)*Parametros!$C$45+Inputs!$D$30*Parametros!$C$46)-I28) | I28: =MAX(MIN(MAX(A28-B28-(Inputs!$D$27*Parametros!$C$44+(Inputs!$D$28+Inputs!$D$29)*Parametros!$C$45+Inputs!$D$30*Parametros!$C$46),0),Parametros!$C$6*Parametros!$C$9*12)*Parametros!$C$8,Parametros!$C$10*12) | J28: =$C$21*(SUMPRODUCT((T28>Parametros!$B$55:$B$63)*(T28-Parametros!$B$55:$B$63)*Parametros!$E$55:$E$63)+SUMPRODUCT((T28>Parametros!$B$67:$B$68)*(T28-Parametros!$B$67:$B$68)*Parametros!$E$67:$E$68))-$C$22 | K28: =C28-I28-J28 | L28: =A28-B28-(Inputs!$D$27*Parametros!$C$44+(Inputs!$D$28+Inputs!$D$29)*Parametros!$C$45+Inputs!$D$30*Parametros!$C$46)-(Inputs!$D$32)-((MAX(Inputs!$D$32,Parametros!$C$6*Parametros!$C$13*12))*Parametros!$C$11) | M28: =MAX(0,(Inputs!$D$32)-MIN((Inputs!$D$32),MAX(Parametros!$C$30,(MAX(Inputs!$D$32,Parametros!$C$6*Parametros!$C$13*12))*Parametros!$C$12)))+MAX(L28,0) | N28: =$C$21*(SUMPRODUCT((U28>Parametros!$B$55:$B$63)*(U28-Parametros!$B$55:$B$63)*Parametros!$E$55:$E$63)+SUMPRODUCT((U28>Parametros!$B$67:$B$68)*(U28-Parametros!$B$67:$B$68)*Parametros!$E$67:$E$68))-$C$22 | O28: =C28-((MAX(Inputs!$D$32,Parametros!$C$6*Parametros!$C$13*12))*Parametros!$C$12)-((MAX(Inputs!$D$32,Parametros!$C$6*Parametros!$C$13*12))*Parametros!$C$11)-(Inputs!$D$33)-N28 | P28: =IF(AND(G28>=$C$19,G27<$C$19),A28,0) | Q28: =IF(AND(K28>=$C$19,K27<$C$19),A28,0) | R28: =IF(AND(O28>=$C$19,O27<$C$19),A28,0) | S28: =(D28+Inputs!$D$37)/$C$21 | T28: =(H28+Inputs!$D$37)/$C$21 | U28: =(M28+Inputs!$D$37)/$C$21
A29: 70000 | B29: =($D$10)+A29*(1-$D$9) | C29: =A29-B29 | D29: =A29*Parametros!$C$24+MAX(0,A29*Parametros!$C$25-B29)-MAX(0,E29-A29*Parametros!$C$27) | E29: =MAX(MIN(A29*Parametros!$C$7,Parametros!$C$6*Parametros!$C$9*12)*Parametros!$C$8,Parametros!$C$10*12) | F29: =$C$21*(SUMPRODUCT((S29>Parametros!$B$55:$B$63)*(S29-Parametros!$B$55:$B$63)*Parametros!$E$55:$E$63)+SUMPRODUCT((S29>Parametros!$B$67:$B$68)*(S29-Parametros!$B$67:$B$68)*Parametros!$E$67:$E$68))-$C$22 | G29: =C29-E29-F29 | H29: =MAX(0,A29-B29-(Inputs!$D$27*Parametros!$C$44+(Inputs!$D$28+Inputs!$D$29)*Parametros!$C$45+Inputs!$D$30*Parametros!$C$46)-I29) | I29: =MAX(MIN(MAX(A29-B29-(Inputs!$D$27*Parametros!$C$44+(Inputs!$D$28+Inputs!$D$29)*Parametros!$C$45+Inputs!$D$30*Parametros!$C$46),0),Parametros!$C$6*Parametros!$C$9*12)*Parametros!$C$8,Parametros!$C$10*12) | J29: =$C$21*(SUMPRODUCT((T29>Parametros!$B$55:$B$63)*(T29-Parametros!$B$55:$B$63)*Parametros!$E$55:$E$63)+SUMPRODUCT((T29>Parametros!$B$67:$B$68)*(T29-Parametros!$B$67:$B$68)*Parametros!$E$67:$E$68))-$C$22 | K29: =C29-I29-J29 | L29: =A29-B29-(Inputs!$D$27*Parametros!$C$44+(Inputs!$D$28+Inputs!$D$29)*Parametros!$C$45+Inputs!$D$30*Parametros!$C$46)-(Inputs!$D$32)-((MAX(Inputs!$D$32,Parametros!$C$6*Parametros!$C$13*12))*Parametros!$C$11) | M29: =MAX(0,(Inputs!$D$32)-MIN((Inputs!$D$32),MAX(Parametros!$C$30,(MAX(Inputs!$D$32,Parametros!$C$6*Parametros!$C$13*12))*Parametros!$C$12)))+MAX(L29,0) | N29: =$C$21*(SUMPRODUCT((U29>Parametros!$B$55:$B$63)*(U29-Parametros!$B$55:$B$63)*Parametros!$E$55:$E$63)+SUMPRODUCT((U29>Parametros!$B$67:$B$68)*(U29-Parametros!$B$67:$B$68)*Parametros!$E$67:$E$68))-$C$22 | O29: =C29-((MAX(Inputs!$D$32,Parametros!$C$6*Parametros!$C$13*12))*Parametros!$C$12)-((MAX(Inputs!$D$32,Parametros!$C$6*Parametros!$C$13*12))*Parametros!$C$11)-(Inputs!$D$33)-N29 | P29: =IF(AND(G29>=$C$19,G28<$C$19),A29,0) | Q29: =IF(AND(K29>=$C$19,K28<$C$19),A29,0) | R29: =IF(AND(O29>=$C$19,O28<$C$19),A29,0) | S29: =(D29+Inputs!$D$37)/$C$21 | T29: =(H29+Inputs!$D$37)/$C$21 | U29: =(M29+Inputs!$D$37)/$C$21
A30: 80000 | B30: =($D$10)+A30*(1-$D$9) | C30: =A30-B30 | D30: =A30*Parametros!$C$24+MAX(0,A30*Parametros!$C$25-B30)-MAX(0,E30-A30*Parametros!$C$27) | E30: =MAX(MIN(A30*Parametros!$C$7,Parametros!$C$6*Parametros!$C$9*12)*Parametros!$C$8,Parametros!$C$10*12) | F30: =$C$21*(SUMPRODUCT((S30>Parametros!$B$55:$B$63)*(S30-Parametros!$B$55:$B$63)*Parametros!$E$55:$E$63)+SUMPRODUCT((S30>Parametros!$B$67:$B$68)*(S30-Parametros!$B$67:$B$68)*Parametros!$E$67:$E$68))-$C$22 | G30: =C30-E30-F30 | H30: =MAX(0,A30-B30-(Inputs!$D$27*Parametros!$C$44+(Inputs!$D$28+Inputs!$D$29)*Parametros!$C$45+Inputs!$D$30*Parametros!$C$46)-I30) | I30: =MAX(MIN(MAX(A30-B30-(Inputs!$D$27*Parametros!$C$44+(Inputs!$D$28+Inputs!$D$29)*Parametros!$C$45+Inputs!$D$30*Parametros!$C$46),0),Parametros!$C$6*Parametros!$C$9*12)*Parametros!$C$8,Parametros!$C$10*12) | J30: =$C$21*(SUMPRODUCT((T30>Parametros!$B$55:$B$63)*(T30-Parametros!$B$55:$B$63)*Parametros!$E$55:$E$63)+SUMPRODUCT((T30>Parametros!$B$67:$B$68)*(T30-Parametros!$B$67:$B$68)*Parametros!$E$67:$E$68))-$C$22 | K30: =C30-I30-J30 | L30: =A30-B30-(Inputs!$D$27*Parametros!$C$44+(Inputs!$D$28+Inputs!$D$29)*Parametros!$C$45+Inputs!$D$30*Parametros!$C$46)-(Inputs!$D$32)-((MAX(Inputs!$D$32,Parametros!$C$6*Parametros!$C$13*12))*Parametros!$C$11) | M30: =MAX(0,(Inputs!$D$32)-MIN((Inputs!$D$32),MAX(Parametros!$C$30,(MAX(Inputs!$D$32,Parametros!$C$6*Parametros!$C$13*12))*Parametros!$C$12)))+MAX(L30,0) | N30: =$C$21*(SUMPRODUCT((U30>Parametros!$B$55:$B$63)*(U30-Parametros!$B$55:$B$63)*Parametros!$E$55:$E$63)+SUMPRODUCT((U30>Parametros!$B$67:$B$68)*(U30-Parametros!$B$67:$B$68)*Parametros!$E$67:$E$68))-$C$22 | O30: =C30-((MAX(Inputs!$D$32,Parametros!$C$6*Parametros!$C$13*12))*Parametros!$C$12)-((MAX(Inputs!$D$32,Parametros!$C$6*Parametros!$C$13*12))*Parametros!$C$11)-(Inputs!$D$33)-N30 | P30: =IF(AND(G30>=$C$19,G29<$C$19),A30,0) | Q30: =IF(AND(K30>=$C$19,K29<$C$19),A30,0) | R30: =IF(AND(O30>=$C$19,O29<$C$19),A30,0) | S30: =(D30+Inputs!$D$37)/$C$21 | T30: =(H30+Inputs!$D$37)/$C$21 | U30: =(M30+Inputs!$D$37)/$C$21
A31: 90000 | B31: =($D$10)+A31*(1-$D$9) | C31: =A31-B31 | D31: =A31*Parametros!$C$24+MAX(0,A31*Parametros!$C$25-B31)-MAX(0,E31-A31*Parametros!$C$27) | E31: =MAX(MIN(A31*Parametros!$C$7,Parametros!$C$6*Parametros!$C$9*12)*Parametros!$C$8,Parametros!$C$10*12) | F31: =$C$21*(SUMPRODUCT((S31>Parametros!$B$55:$B$63)*(S31-Parametros!$B$55:$B$63)*Parametros!$E$55:$E$63)+SUMPRODUCT((S31>Parametros!$B$67:$B$68)*(S31-Parametros!$B$67:$B$68)*Parametros!$E$67:$E$68))-$C$22 | G31: =C31-E31-F31 | H31: =MAX(0,A31-B31-(Inputs!$D$27*Parametros!$C$44+(Inputs!$D$28+Inputs!$D$29)*Parametros!$C$45+Inputs!$D$30*Parametros!$C$46)-I31) | I31: =MAX(MIN(MAX(A31-B31-(Inputs!$D$27*Parametros!$C$44+(Inputs!$D$28+Inputs!$D$29)*Parametros!$C$45+Inputs!$D$30*Parametros!$C$46),0),Parametros!$C$6*Parametros!$C$9*12)*Parametros!$C$8,Parametros!$C$10*12) | J31: =$C$21*(SUMPRODUCT((T31>Parametros!$B$55:$B$63)*(T31-Parametros!$B$55:$B$63)*Parametros!$E$55:$E$63)+SUMPRODUCT((T31>Parametros!$B$67:$B$68)*(T31-Parametros!$B$67:$B$68)*Parametros!$E$67:$E$68))-$C$22 | K31: =C31-I31-J31 | L31: =A31-B31-(Inputs!$D$27*Parametros!$C$44+(Inputs!$D$28+Inputs!$D$29)*Parametros!$C$45+Inputs!$D$30*Parametros!$C$46)-(Inputs!$D$32)-((MAX(Inputs!$D$32,Parametros!$C$6*Parametros!$C$13*12))*Parametros!$C$11) | M31: =MAX(0,(Inputs!$D$32)-MIN((Inputs!$D$32),MAX(Parametros!$C$30,(MAX(Inputs!$D$32,Parametros!$C$6*Parametros!$C$13*12))*Parametros!$C$12)))+MAX(L31,0) | N31: =$C$21*(SUMPRODUCT((U31>Parametros!$B$55:$B$63)*(U31-Parametros!$B$55:$B$63)*Parametros!$E$55:$E$63)+SUMPRODUCT((U31>Parametros!$B$67:$B$68)*(U31-Parametros!$B$67:$B$68)*Parametros!$E$67:$E$68))-$C$22 | O31: =C31-((MAX(Inputs!$D$32,Parametros!$C$6*Parametros!$C$13*12))*Parametros!$C$12)-((MAX(Inputs!$D$32,Parametros!$C$6*Parametros!$C$13*12))*Parametros!$C$11)-(Inputs!$D$33)-N31 | P31: =IF(AND(G31>=$C$19,G30<$C$19),A31,0) | Q31: =IF(AND(K31>=$C$19,K30<$C$19),A31,0) | R31: =IF(AND(O31>=$C$19,O30<$C$19),A31,0) | S31: =(D31+Inputs!$D$37)/$C$21 | T31: =(H31+Inputs!$D$37)/$C$21 | U31: =(M31+Inputs!$D$37)/$C$21
A32: 100000 | B32: =($D$10)+A32*(1-$D$9) | C32: =A32-B32 | D32: =A32*Parametros!$C$24+MAX(0,A32*Parametros!$C$25-B32)-MAX(0,E32-A32*Parametros!$C$27) | E32: =MAX(MIN(A32*Parametros!$C$7,Parametros!$C$6*Parametros!$C$9*12)*Parametros!$C$8,Parametros!$C$10*12) | F32: =$C$21*(SUMPRODUCT((S32>Parametros!$B$55:$B$63)*(S32-Parametros!$B$55:$B$63)*Parametros!$E$55:$E$63)+SUMPRODUCT((S32>Parametros!$B$67:$B$68)*(S32-Parametros!$B$67:$B$68)*Parametros!$E$67:$E$68))-$C$22 | G32: =C32-E32-F32 | H32: =MAX(0,A32-B32-(Inputs!$D$27*Parametros!$C$44+(Inputs!$D$28+Inputs!$D$29)*Parametros!$C$45+Inputs!$D$30*Parametros!$C$46)-I32) | I32: =MAX(MIN(MAX(A32-B32-(Inputs!$D$27*Parametros!$C$44+(Inputs!$D$28+Inputs!$D$29)*Parametros!$C$45+Inputs!$D$30*Parametros!$C$46),0),Parametros!$C$6*Parametros!$C$9*12)*Parametros!$C$8,Parametros!$C$10*12) | J32: =$C$21*(SUMPRODUCT((T32>Parametros!$B$55:$B$63)*(T32-Parametros!$B$55:$B$63)*Parametros!$E$55:$E$63)+SUMPRODUCT((T32>Parametros!$B$67:$B$68)*(T32-Parametros!$B$67:$B$68)*Parametros!$E$67:$E$68))-$C$22 | K32: =C32-I32-J32 | L32: =A32-B32-(Inputs!$D$27*Parametros!$C$44+(Inputs!$D$28+Inputs!$D$29)*Parametros!$C$45+Inputs!$D$30*Parametros!$C$46)-(Inputs!$D$32)-((MAX(Inputs!$D$32,Parametros!$C$6*Parametros!$C$13*12))*Parametros!$C$11) | M32: =MAX(0,(Inputs!$D$32)-MIN((Inputs!$D$32),MAX(Parametros!$C$30,(MAX(Inputs!$D$32,Parametros!$C$6*Parametros!$C$13*12))*Parametros!$C$12)))+MAX(L32,0) | N32: =$C$21*(SUMPRODUCT((U32>Parametros!$B$55:$B$63)*(U32-Parametros!$B$55:$B$63)*Parametros!$E$55:$E$63)+SUMPRODUCT((U32>Parametros!$B$67:$B$68)*(U32-Parametros!$B$67:$B$68)*Parametros!$E$67:$E$68))-$C$22 | O32: =C32-((MAX(Inputs!$D$32,Parametros!$C$6*Parametros!$C$13*12))*Parametros!$C$12)-((MAX(Inputs!$D$32,Parametros!$C$6*Parametros!$C$13*12))*Parametros!$C$11)-(Inputs!$D$33)-N32 | P32: =IF(AND(G32>=$C$19,G31<$C$19),A32,0) | Q32: =IF(AND(K32>=$C$19,K31<$C$19),A32,0) | R32: =IF(AND(O32>=$C$19,O31<$C$19),A32,0) | S32: =(D32+Inputs!$D$37)/$C$21 | T32: =(H32+Inputs!$D$37)/$C$21 | U32: =(M32+Inputs!$D$37)/$C$21
A33: 110000 | B33: =($D$10)+A33*(1-$D$9) | C33: =A33-B33 | D33: =A33*Parametros!$C$24+MAX(0,A33*Parametros!$C$25-B33)-MAX(0,E33-A33*Parametros!$C$27) | E33: =MAX(MIN(A33*Parametros!$C$7,Parametros!$C$6*Parametros!$C$9*12)*Parametros!$C$8,Parametros!$C$10*12) | F33: =$C$21*(SUMPRODUCT((S33>Parametros!$B$55:$B$63)*(S33-Parametros!$B$55:$B$63)*Parametros!$E$55:$E$63)+SUMPRODUCT((S33>Parametros!$B$67:$B$68)*(S33-Parametros!$B$67:$B$68)*Parametros!$E$67:$E$68))-$C$22 | G33: =C33-E33-F33 | H33: =MAX(0,A33-B33-(Inputs!$D$27*Parametros!$C$44+(Inputs!$D$28+Inputs!$D$29)*Parametros!$C$45+Inputs!$D$30*Parametros!$C$46)-I33) | I33: =MAX(MIN(MAX(A33-B33-(Inputs!$D$27*Parametros!$C$44+(Inputs!$D$28+Inputs!$D$29)*Parametros!$C$45+Inputs!$D$30*Parametros!$C$46),0),Parametros!$C$6*Parametros!$C$9*12)*Parametros!$C$8,Parametros!$C$10*12) | J33: =$C$21*(SUMPRODUCT((T33>Parametros!$B$55:$B$63)*(T33-Parametros!$B$55:$B$63)*Parametros!$E$55:$E$63)+SUMPRODUCT((T33>Parametros!$B$67:$B$68)*(T33-Parametros!$B$67:$B$68)*Parametros!$E$67:$E$68))-$C$22 | K33: =C33-I33-J33 | L33: =A33-B33-(Inputs!$D$27*Parametros!$C$44+(Inputs!$D$28+Inputs!$D$29)*Parametros!$C$45+Inputs!$D$30*Parametros!$C$46)-(Inputs!$D$32)-((MAX(Inputs!$D$32,Parametros!$C$6*Parametros!$C$13*12))*Parametros!$C$11) | M33: =MAX(0,(Inputs!$D$32)-MIN((Inputs!$D$32),MAX(Parametros!$C$30,(MAX(Inputs!$D$32,Parametros!$C$6*Parametros!$C$13*12))*Parametros!$C$12)))+MAX(L33,0) | N33: =$C$21*(SUMPRODUCT((U33>Parametros!$B$55:$B$63)*(U33-Parametros!$B$55:$B$63)*Parametros!$E$55:$E$63)+SUMPRODUCT((U33>Parametros!$B$67:$B$68)*(U33-Parametros!$B$67:$B$68)*Parametros!$E$67:$E$68))-$C$22 | O33: =C33-((MAX(Inputs!$D$32,Parametros!$C$6*Parametros!$C$13*12))*Parametros!$C$12)-((MAX(Inputs!$D$32,Parametros!$C$6*Parametros!$C$13*12))*Parametros!$C$11)-(Inputs!$D$33)-N33 | P33: =IF(AND(G33>=$C$19,G32<$C$19),A33,0) | Q33: =IF(AND(K33>=$C$19,K32<$C$19),A33,0) | R33: =IF(AND(O33>=$C$19,O32<$C$19),A33,0) | S33: =(D33+Inputs!$D$37)/$C$21 | T33: =(H33+Inputs!$D$37)/$C$21 | U33: =(M33+Inputs!$D$37)/$C$21
A34: 120000 | B34: =($D$10)+A34*(1-$D$9) | C34: =A34-B34 | D34: =A34*Parametros!$C$24+MAX(0,A34*Parametros!$C$25-B34)-MAX(0,E34-A34*Parametros!$C$27) | E34: =MAX(MIN(A34*Parametros!$C$7,Parametros!$C$6*Parametros!$C$9*12)*Parametros!$C$8,Parametros!$C$10*12) | F34: =$C$21*(SUMPRODUCT((S34>Parametros!$B$55:$B$63)*(S34-Parametros!$B$55:$B$63)*Parametros!$E$55:$E$63)+SUMPRODUCT((S34>Parametros!$B$67:$B$68)*(S34-Parametros!$B$67:$B$68)*Parametros!$E$67:$E$68))-$C$22 | G34: =C34-E34-F34 | H34: =MAX(0,A34-B34-(Inputs!$D$27*Parametros!$C$44+(Inputs!$D$28+Inputs!$D$29)*Parametros!$C$45+Inputs!$D$30*Parametros!$C$46)-I34) | I34: =MAX(MIN(MAX(A34-B34-(Inputs!$D$27*Parametros!$C$44+(Inputs!$D$28+Inputs!$D$29)*Parametros!$C$45+Inputs!$D$30*Parametros!$C$46),0),Parametros!$C$6*Parametros!$C$9*12)*Parametros!$C$8,Parametros!$C$10*12) | J34: =$C$21*(SUMPRODUCT((T34>Parametros!$B$55:$B$63)*(T34-Parametros!$B$55:$B$63)*Parametros!$E$55:$E$63)+SUMPRODUCT((T34>Parametros!$B$67:$B$68)*(T34-Parametros!$B$67:$B$68)*Parametros!$E$67:$E$68))-$C$22 | K34: =C34-I34-J34 | L34: =A34-B34-(Inputs!$D$27*Parametros!$C$44+(Inputs!$D$28+Inputs!$D$29)*Parametros!$C$45+Inputs!$D$30*Parametros!$C$46)-(Inputs!$D$32)-((MAX(Inputs!$D$32,Parametros!$C$6*Parametros!$C$13*12))*Parametros!$C$11) | M34: =MAX(0,(Inputs!$D$32)-MIN((Inputs!$D$32),MAX(Parametros!$C$30,(MAX(Inputs!$D$32,Parametros!$C$6*Parametros!$C$13*12))*Parametros!$C$12)))+MAX(L34,0) | N34: =$C$21*(SUMPRODUCT((U34>Parametros!$B$55:$B$63)*(U34-Parametros!$B$55:$B$63)*Parametros!$E$55:$E$63)+SUMPRODUCT((U34>Parametros!$B$67:$B$68)*(U34-Parametros!$B$67:$B$68)*Parametros!$E$67:$E$68))-$C$22 | O34: =C34-((MAX(Inputs!$D$32,Parametros!$C$6*Parametros!$C$13*12))*Parametros!$C$12)-((MAX(Inputs!$D$32,Parametros!$C$6*Parametros!$C$13*12))*Parametros!$C$11)-(Inputs!$D$33)-N34 | P34: =IF(AND(G34>=$C$19,G33<$C$19),A34,0) | Q34: =IF(AND(K34>=$C$19,K33<$C$19),A34,0) | R34: =IF(AND(O34>=$C$19,O33<$C$19),A34,0) | S34: =(D34+Inputs!$D$37)/$C$21 | T34: =(H34+Inputs!$D$37)/$C$21 | U34: =(M34+Inputs!$D$37)/$C$21
A35: 130000 | B35: =($D$10)+A35*(1-$D$9) | C35: =A35-B35 | D35: =A35*Parametros!$C$24+MAX(0,A35*Parametros!$C$25-B35)-MAX(0,E35-A35*Parametros!$C$27) | E35: =MAX(MIN(A35*Parametros!$C$7,Parametros!$C$6*Parametros!$C$9*12)*Parametros!$C$8,Parametros!$C$10*12) | F35: =$C$21*(SUMPRODUCT((S35>Parametros!$B$55:$B$63)*(S35-Parametros!$B$55:$B$63)*Parametros!$E$55:$E$63)+SUMPRODUCT((S35>Parametros!$B$67:$B$68)*(S35-Parametros!$B$67:$B$68)*Parametros!$E$67:$E$68))-$C$22 | G35: =C35-E35-F35 | H35: =MAX(0,A35-B35-(Inputs!$D$27*Parametros!$C$44+(Inputs!$D$28+Inputs!$D$29)*Parametros!$C$45+Inputs!$D$30*Parametros!$C$46)-I35) | I35: =MAX(MIN(MAX(A35-B35-(Inputs!$D$27*Parametros!$C$44+(Inputs!$D$28+Inputs!$D$29)*Parametros!$C$45+Inputs!$D$30*Parametros!$C$46),0),Parametros!$C$6*Parametros!$C$9*12)*Parametros!$C$8,Parametros!$C$10*12) | J35: =$C$21*(SUMPRODUCT((T35>Parametros!$B$55:$B$63)*(T35-Parametros!$B$55:$B$63)*Parametros!$E$55:$E$63)+SUMPRODUCT((T35>Parametros!$B$67:$B$68)*(T35-Parametros!$B$67:$B$68)*Parametros!$E$67:$E$68))-$C$22 | K35: =C35-I35-J35 | L35: =A35-B35-(Inputs!$D$27*Parametros!$C$44+(Inputs!$D$28+Inputs!$D$29)*Parametros!$C$45+Inputs!$D$30*Parametros!$C$46)-(Inputs!$D$32)-((MAX(Inputs!$D$32,Parametros!$C$6*Parametros!$C$13*12))*Parametros!$C$11) | M35: =MAX(0,(Inputs!$D$32)-MIN((Inputs!$D$32),MAX(Parametros!$C$30,(MAX(Inputs!$D$32,Parametros!$C$6*Parametros!$C$13*12))*Parametros!$C$12)))+MAX(L35,0) | N35: =$C$21*(SUMPRODUCT((U35>Parametros!$B$55:$B$63)*(U35-Parametros!$B$55:$B$63)*Parametros!$E$55:$E$63)+SUMPRODUCT((U35>Parametros!$B$67:$B$68)*(U35-Parametros!$B$67:$B$68)*Parametros!$E$67:$E$68))-$C$22 | O35: =C35-((MAX(Inputs!$D$32,Parametros!$C$6*Parametros!$C$13*12))*Parametros!$C$12)-((MAX(Inputs!$D$32,Parametros!$C$6*Parametros!$C$13*12))*Parametros!$C$11)-(Inputs!$D$33)-N35 | P35: =IF(AND(G35>=$C$19,G34<$C$19),A35,0) | Q35: =IF(AND(K35>=$C$19,K34<$C$19),A35,0) | R35: =IF(AND(O35>=$C$19,O34<$C$19),A35,0) | S35: =(D35+Inputs!$D$37)/$C$21 | T35: =(H35+Inputs!$D$37)/$C$21 | U35: =(M35+Inputs!$D$37)/$C$21
A36: 140000 | B36: =($D$10)+A36*(1-$D$9) | C36: =A36-B36 | D36: =A36*Parametros!$C$24+MAX(0,A36*Parametros!$C$25-B36)-MAX(0,E36-A36*Parametros!$C$27) | E36: =MAX(MIN(A36*Parametros!$C$7,Parametros!$C$6*Parametros!$C$9*12)*Parametros!$C$8,Parametros!$C$10*12) | F36: =$C$21*(SUMPRODUCT((S36>Parametros!$B$55:$B$63)*(S36-Parametros!$B$55:$B$63)*Parametros!$E$55:$E$63)+SUMPRODUCT((S36>Parametros!$B$67:$B$68)*(S36-Parametros!$B$67:$B$68)*Parametros!$E$67:$E$68))-$C$22 | G36: =C36-E36-F36 | H36: =MAX(0,A36-B36-(Inputs!$D$27*Parametros!$C$44+(Inputs!$D$28+Inputs!$D$29)*Parametros!$C$45+Inputs!$D$30*Parametros!$C$46)-I36) | I36: =MAX(MIN(MAX(A36-B36-(Inputs!$D$27*Parametros!$C$44+(Inputs!$D$28+Inputs!$D$29)*Parametros!$C$45+Inputs!$D$30*Parametros!$C$46),0),Parametros!$C$6*Parametros!$C$9*12)*Parametros!$C$8,Parametros!$C$10*12) | J36: =$C$21*(SUMPRODUCT((T36>Parametros!$B$55:$B$63)*(T36-Parametros!$B$55:$B$63)*Parametros!$E$55:$E$63)+SUMPRODUCT((T36>Parametros!$B$67:$B$68)*(T36-Parametros!$B$67:$B$68)*Parametros!$E$67:$E$68))-$C$22 | K36: =C36-I36-J36 | L36: =A36-B36-(Inputs!$D$27*Parametros!$C$44+(Inputs!$D$28+Inputs!$D$29)*Parametros!$C$45+Inputs!$D$30*Parametros!$C$46)-(Inputs!$D$32)-((MAX(Inputs!$D$32,Parametros!$C$6*Parametros!$C$13*12))*Parametros!$C$11) | M36: =MAX(0,(Inputs!$D$32)-MIN((Inputs!$D$32),MAX(Parametros!$C$30,(MAX(Inputs!$D$32,Parametros!$C$6*Parametros!$C$13*12))*Parametros!$C$12)))+MAX(L36,0) | N36: =$C$21*(SUMPRODUCT((U36>Parametros!$B$55:$B$63)*(U36-Parametros!$B$55:$B$63)*Parametros!$E$55:$E$63)+SUMPRODUCT((U36>Parametros!$B$67:$B$68)*(U36-Parametros!$B$67:$B$68)*Parametros!$E$67:$E$68))-$C$22 | O36: =C36-((MAX(Inputs!$D$32,Parametros!$C$6*Parametros!$C$13*12))*Parametros!$C$12)-((MAX(Inputs!$D$32,Parametros!$C$6*Parametros!$C$13*12))*Parametros!$C$11)-(Inputs!$D$33)-N36 | P36: =IF(AND(G36>=$C$19,G35<$C$19),A36,0) | Q36: =IF(AND(K36>=$C$19,K35<$C$19),A36,0) | R36: =IF(AND(O36>=$C$19,O35<$C$19),A36,0) | S36: =(D36+Inputs!$D$37)/$C$21 | T36: =(H36+Inputs!$D$37)/$C$21 | U36: =(M36+Inputs!$D$37)/$C$21
A37: 150000 | B37: =($D$10)+A37*(1-$D$9) | C37: =A37-B37 | D37: =A37*Parametros!$C$24+MAX(0,A37*Parametros!$C$25-B37)-MAX(0,E37-A37*Parametros!$C$27) | E37: =MAX(MIN(A37*Parametros!$C$7,Parametros!$C$6*Parametros!$C$9*12)*Parametros!$C$8,Parametros!$C$10*12) | F37: =$C$21*(SUMPRODUCT((S37>Parametros!$B$55:$B$63)*(S37-Parametros!$B$55:$B$63)*Parametros!$E$55:$E$63)+SUMPRODUCT((S37>Parametros!$B$67:$B$68)*(S37-Parametros!$B$67:$B$68)*Parametros!$E$67:$E$68))-$C$22 | G37: =C37-E37-F37 | H37: =MAX(0,A37-B37-(Inputs!$D$27*Parametros!$C$44+(Inputs!$D$28+Inputs!$D$29)*Parametros!$C$45+Inputs!$D$30*Parametros!$C$46)-I37) | I37: =MAX(MIN(MAX(A37-B37-(Inputs!$D$27*Parametros!$C$44+(Inputs!$D$28+Inputs!$D$29)*Parametros!$C$45+Inputs!$D$30*Parametros!$C$46),0),Parametros!$C$6*Parametros!$C$9*12)*Parametros!$C$8,Parametros!$C$10*12) | J37: =$C$21*(SUMPRODUCT((T37>Parametros!$B$55:$B$63)*(T37-Parametros!$B$55:$B$63)*Parametros!$E$55:$E$63)+SUMPRODUCT((T37>Parametros!$B$67:$B$68)*(T37-Parametros!$B$67:$B$68)*Parametros!$E$67:$E$68))-$C$22 | K37: =C37-I37-J37 | L37: =A37-B37-(Inputs!$D$27*Parametros!$C$44+(Inputs!$D$28+Inputs!$D$29)*Parametros!$C$45+Inputs!$D$30*Parametros!$C$46)-(Inputs!$D$32)-((MAX(Inputs!$D$32,Parametros!$C$6*Parametros!$C$13*12))*Parametros!$C$11) | M37: =MAX(0,(Inputs!$D$32)-MIN((Inputs!$D$32),MAX(Parametros!$C$30,(MAX(Inputs!$D$32,Parametros!$C$6*Parametros!$C$13*12))*Parametros!$C$12)))+MAX(L37,0) | N37: =$C$21*(SUMPRODUCT((U37>Parametros!$B$55:$B$63)*(U37-Parametros!$B$55:$B$63)*Parametros!$E$55:$E$63)+SUMPRODUCT((U37>Parametros!$B$67:$B$68)*(U37-Parametros!$B$67:$B$68)*Parametros!$E$67:$E$68))-$C$22 | O37: =C37-((MAX(Inputs!$D$32,Parametros!$C$6*Parametros!$C$13*12))*Parametros!$C$12)-((MAX(Inputs!$D$32,Parametros!$C$6*Parametros!$C$13*12))*Parametros!$C$11)-(Inputs!$D$33)-N37 | P37: =IF(AND(G37>=$C$19,G36<$C$19),A37,0) | Q37: =IF(AND(K37>=$C$19,K36<$C$19),A37,0) | R37: =IF(AND(O37>=$C$19,O36<$C$19),A37,0) | S37: =(D37+Inputs!$D$37)/$C$21 | T37: =(H37+Inputs!$D$37)/$C$21 | U37: =(M37+Inputs!$D$37)/$C$21
A38: 160000 | B38: =($D$10)+A38*(1-$D$9) | C38: =A38-B38 | D38: =A38*Parametros!$C$24+MAX(0,A38*Parametros!$C$25-B38)-MAX(0,E38-A38*Parametros!$C$27) | E38: =MAX(MIN(A38*Parametros!$C$7,Parametros!$C$6*Parametros!$C$9*12)*Parametros!$C$8,Parametros!$C$10*12) | F38: =$C$21*(SUMPRODUCT((S38>Parametros!$B$55:$B$63)*(S38-Parametros!$B$55:$B$63)*Parametros!$E$55:$E$63)+SUMPRODUCT((S38>Parametros!$B$67:$B$68)*(S38-Parametros!$B$67:$B$68)*Parametros!$E$67:$E$68))-$C$22 | G38: =C38-E38-F38 | H38: =MAX(0,A38-B38-(Inputs!$D$27*Parametros!$C$44+(Inputs!$D$28+Inputs!$D$29)*Parametros!$C$45+Inputs!$D$30*Parametros!$C$46)-I38) | I38: =MAX(MIN(MAX(A38-B38-(Inputs!$D$27*Parametros!$C$44+(Inputs!$D$28+Inputs!$D$29)*Parametros!$C$45+Inputs!$D$30*Parametros!$C$46),0),Parametros!$C$6*Parametros!$C$9*12)*Parametros!$C$8,Parametros!$C$10*12) | J38: =$C$21*(SUMPRODUCT((T38>Parametros!$B$55:$B$63)*(T38-Parametros!$B$55:$B$63)*Parametros!$E$55:$E$63)+SUMPRODUCT((T38>Parametros!$B$67:$B$68)*(T38-Parametros!$B$67:$B$68)*Parametros!$E$67:$E$68))-$C$22 | K38: =C38-I38-J38 | L38: =A38-B38-(Inputs!$D$27*Parametros!$C$44+(Inputs!$D$28+Inputs!$D$29)*Parametros!$C$45+Inputs!$D$30*Parametros!$C$46)-(Inputs!$D$32)-((MAX(Inputs!$D$32,Parametros!$C$6*Parametros!$C$13*12))*Parametros!$C$11) | M38: =MAX(0,(Inputs!$D$32)-MIN((Inputs!$D$32),MAX(Parametros!$C$30,(MAX(Inputs!$D$32,Parametros!$C$6*Parametros!$C$13*12))*Parametros!$C$12)))+MAX(L38,0) | N38: =$C$21*(SUMPRODUCT((U38>Parametros!$B$55:$B$63)*(U38-Parametros!$B$55:$B$63)*Parametros!$E$55:$E$63)+SUMPRODUCT((U38>Parametros!$B$67:$B$68)*(U38-Parametros!$B$67:$B$68)*Parametros!$E$67:$E$68))-$C$22 | O38: =C38-((MAX(Inputs!$D$32,Parametros!$C$6*Parametros!$C$13*12))*Parametros!$C$12)-((MAX(Inputs!$D$32,Parametros!$C$6*Parametros!$C$13*12))*Parametros!$C$11)-(Inputs!$D$33)-N38 | P38: =IF(AND(G38>=$C$19,G37<$C$19),A38,0) | Q38: =IF(AND(K38>=$C$19,K37<$C$19),A38,0) | R38: =IF(AND(O38>=$C$19,O37<$C$19),A38,0) | S38: =(D38+Inputs!$D$37)/$C$21 | T38: =(H38+Inputs!$D$37)/$C$21 | U38: =(M38+Inputs!$D$37)/$C$21
A40: Faturação necessária para o rendimento-alvo — Via 1 — ENI simplificado | C40: =IF(MAX(P26:P38)=0,"Fora do intervalo analisado",MAX(P26:P38))
A41: Faturação necessária para o rendimento-alvo — Via 2 — ENI cont. organizada | C41: =IF(MAX(Q26:Q38)=0,"Fora do intervalo analisado",MAX(Q26:Q38))
A42: Faturação necessária para o rendimento-alvo — Via 3 — Sociedade transparente | C42: =IF(MAX(R26:R38)=0,"Fora do intervalo analisado",MAX(R26:R38))
A46: Como o break-even se move com o peso dos colaboradores
A47: Quando a faturação vem da própria Dra. Júlia, quase toda ela é margem. Quando vem de um colaborador pago a uma percentagem da sessão, sobra a diferença. Esta tabela mostra o que acontece ao break-even à medida que o peso dos colaboradores sobe, mantendo a receita total constante. A subida não é proporcional: o break-even é os custos fixos a dividir pela margem, e quando a margem se aproxima de zero o break-even dispara para o infinito.
A48: Peso dos colaboradores na receita | B48: Margem de contribuição (%) | C48: Break-even anual | D48: Break-even mensal | E48: Utilização necessária | F48: Nota
A49: 0 | B49: =1-Inputs!$D$23-A49*Inputs!$D$12 | C49: =IF(B49<=0,"não atinge",$D$10/B49) | D49: =IF(B49<=0,"não atinge",C49/12) | E49: =IF(B49<=0,"n/a",C49/(BreakEven!$D$14*Operacao!$D$21))
A50: 0.1 | B50: =1-Inputs!$D$23-A50*Inputs!$D$12 | C50: =IF(B50<=0,"não atinge",$D$10/B50) | D50: =IF(B50<=0,"não atinge",C50/12) | E50: =IF(B50<=0,"n/a",C50/(BreakEven!$D$14*Operacao!$D$21))
A51: 0.2 | B51: =1-Inputs!$D$23-A51*Inputs!$D$12 | C51: =IF(B51<=0,"não atinge",$D$10/B51) | D51: =IF(B51<=0,"não atinge",C51/12) | E51: =IF(B51<=0,"n/a",C51/(BreakEven!$D$14*Operacao!$D$21))
A52: 0.3 | B52: =1-Inputs!$D$23-A52*Inputs!$D$12 | C52: =IF(B52<=0,"não atinge",$D$10/B52) | D52: =IF(B52<=0,"não atinge",C52/12) | E52: =IF(B52<=0,"n/a",C52/(BreakEven!$D$14*Operacao!$D$21))
A53: 0.4 | B53: =1-Inputs!$D$23-A53*Inputs!$D$12 | C53: =IF(B53<=0,"não atinge",$D$10/B53) | D53: =IF(B53<=0,"não atinge",C53/12) | E53: =IF(B53<=0,"n/a",C53/(BreakEven!$D$14*Operacao!$D$21))
A54: 0.5 | B54: =1-Inputs!$D$23-A54*Inputs!$D$12 | C54: =IF(B54<=0,"não atinge",$D$10/B54) | D54: =IF(B54<=0,"não atinge",C54/12) | E54: =IF(B54<=0,"n/a",C54/(BreakEven!$D$14*Operacao!$D$21))
A55: 0.6 | B55: =1-Inputs!$D$23-A55*Inputs!$D$12 | C55: =IF(B55<=0,"não atinge",$D$10/B55) | D55: =IF(B55<=0,"não atinge",C55/12) | E55: =IF(B55<=0,"n/a",C55/(BreakEven!$D$14*Operacao!$D$21))
A56: 0.7 | B56: =1-Inputs!$D$23-A56*Inputs!$D$12 | C56: =IF(B56<=0,"não atinge",$D$10/B56) | D56: =IF(B56<=0,"não atinge",C56/12) | E56: =IF(B56<=0,"n/a",C56/(BreakEven!$D$14*Operacao!$D$21))
A57: 0.8 | B57: =1-Inputs!$D$23-A57*Inputs!$D$12 | C57: =IF(B57<=0,"não atinge",$D$10/B57) | D57: =IF(B57<=0,"não atinge",C57/12) | E57: =IF(B57<=0,"n/a",C57/(BreakEven!$D$14*Operacao!$D$21))
A59: A ata regista, no ponto 6, que «se uma parte relevante da faturação corresponder a honorários de prestadores, a margem efetiva pode não justificar a alteração de estrutura». Esta tabela é essa frase em números — e mostra que o problema aparece muito antes de a margem chegar a zero.
A61: A via 4 não consta desta tabela: o líquido depende da política de distribuição e da opção de englobamento, que são decisões e não funções da faturação. Para a via 4, fixar essas alavancas na folha Inputs e ler o resultado na folha Comparativo.

Sheet Espaco
A1: M1 — Espaço: 2 versus 3 gabinetes
A2: A ata deixa a escolha em aberto e trata-a como uma questão de renda. Não é: o terceiro gabinete acrescenta capacidade e acrescenta custo fixo, e só compensa a partir de um nível de utilização. O output principal desta folha é esse nível.
A4: Rubrica | B4: Ref. | C4: Opção A — 2 gabinetes | D4: Opção B — 3 gabinetes | E4: Nota
A5: Características de cada espaço
A6: N.º de gabinetes | B6: N_GAB | C6: 2 | D6: 3
A7: Renda anual | B7: RENDA | C7: 14400 | D7: 19200 | E7: Input cliente 3 — EM FALTA, para os dois espaços.
A8: Condomínio e encargos anuais | B8: CONDOM | C8: 1500 | D8: 2000 | E8: EM FALTA.
A9: Obras de adaptação | B9: OBRAS | C9: 25000 | D9: 38000 | E9: Input cliente 4 — EM FALTA.
A10: Equipamento clínico | B10: EQUIP | C10: 20000 | D10: 26000 | E10: EM FALTA.
A11: Pressupostos comuns
A12: Taxa de utilização a testar | B12: UTIL | C12: 0.45 | D12: 0.45 | E12: ALAVANCA. Varrida na tabela em baixo. Aqui serve para a fotografia de um único ponto.
A13: Preço médio por consulta | B13: PRECO_M | C13: =BreakEven!$D$14 | D13: =BreakEven!$D$14
A14: Custos variáveis em % da receita | B14: PCT_VAR | C14: =1-BreakEven!$D$9 | D14: =1-BreakEven!$D$9
A15: Outros custos fixos (seguros, software, outros) | B15: CF_OUTROS | C15: =Inputs!$D$21+Inputs!$D$22+Inputs!$D$25 | D15: =Inputs!$D$21+Inputs!$D$22+Inputs!$D$25
A16: Taxa de esforço fiscal e contributiva aplicada | B16: TX_ESF | C16: =V2_ENI_ContOrg!$D$30 | D16: =V2_ENI_ContOrg!$D$30 | E16: Usa a taxa de esforço da via 2 no cenário Base. É uma aproximação assumida: a comparação entre espaços é operacional, e a estrutura fiscal é a mesma nos dois. Registado em R1-33.
A17: Capacidade e resultado ao nível de utilização testado
A18: Capacidade anual (consultas) | B18: CAP | C18: =$C$6*Operacao!$D$7*Operacao!$D$20 | D18: =$D$6*Operacao!$D$7*Operacao!$D$20
A19: Consultas ao nível de utilização testado | B19: CONS | C19: =$C$18*$C$12 | D19: =$D$18*$D$12
A20: Faturação potencial | B20: FAT | C20: =$C$19*$C$13 | D20: =$D$19*$D$13
A21: Margem de contribuição | B21: MC | C21: =$C$20*(1-$C$14) | D21: =$D$20*(1-$D$14)
A22: Custos fixos totais | B22: CF | C22: =$C$7+$C$8+$C$15 | D22: =$D$7+$D$8+$D$15
A23: Resultado operacional | B23: RES | C23: =$C$21-$C$22 | D23: =$D$21-$D$22
A24: Resultado líquido de impostos e contribuições | B24: RES_LIQ | C24: =$C$23*(1-$C$16) | D24: =$D$23*(1-$D$16)
A25: Investimento e recuperação
A26: IVA não dedutível sobre o investimento | B26: IVA_P | C26: =($C$9+$C$10)*Parametros!$C$41 | D26: =($D$9+$D$10)*Parametros!$C$41 | E26: Custo definitivo: a fisioterapia é isenta sem direito à dedução.
A27: INVESTIMENTO INICIAL TOTAL | B27: INV | C27: =$C$9+$C$10+$C$26 | D27: =$D$9+$D$10+$D$26
A28: PAYBACK (anos) | B28: PAYBACK | C28: =IF($C$24<=0,"Não recupera",$C$27/$C$24) | D28: =IF($D$24<=0,"Não recupera",$D$27/$D$24) | E28: Anos de resultado líquido necessários para recuperar o investimento, ao nível de utilização testado. Não desconta o valor do dinheiro no tempo — para esta dimensão, não compensa.
A29: Retorno anual sobre o investimento | B29: ROI | C29: =IF($C$27<=0,0,$C$24/$C$27) | D29: =IF($D$27<=0,0,$D$24/$D$27)
A30: Utilização necessária para o break-even operacional | B30: BE_UTIL | C30: =IF($C$18*$C$13*(1-$C$14)<=0,0,$C$22/($C$18*$C$13*(1-$C$14))) | D30: =IF($D$18*$D$13*(1-$D$14)<=0,0,$D$22/($D$18*$D$13*(1-$D$14))) | E30: Acima de 100%, o espaço não cobre os próprios custos fixos a lotação máxima.
A32: O custo do degrau — se o terceiro gabinete não encher
A33: Custo fixo adicional anual da opção B | C33: =$D$22-$C$22 | E33: Renda e condomínio a mais, todos os anos, independentemente de haver doentes para os ocupar.
A34: Custo do degrau, líquido de impostos | C34: =($D$22-$C$22)*(1-$C$16) | E34: É este o valor que a Dra. Júlia perde por ano se escolher três gabinetes e a procura não passar do que dois comportavam.
A35: Investimento adicional da opção B | C35: =$D$27-$C$27 | E35: Obras, equipamento e IVA irrecuperável a mais, de uma só vez.
A36: Consultas anuais adicionais necessárias para o degrau se pagar | C36: =IF($C$13*(1-$C$14)<=0,0,($D$22-$C$22)/($C$13*(1-$C$14))) | E36: Traduzido para a única unidade que a cliente controla: doentes.
A38: A partir de que procura compensa o terceiro gabinete
A39: O eixo é a PROCURA, em consultas por ano — não a taxa de utilização. Comparar as duas opções à mesma percentagem de utilização daria automaticamente mais 50% de consultas à opção de três gabinetes, e a comparação não significaria nada. À mesma procura, cada opção atende o que a sua capacidade permite, e o terceiro gabinete só vale alguma coisa quando a procura ultrapassa a capacidade de dois.
A40: Procura anual (consultas) | B40: Resultado líquido — 2 gabinetes | C40: Resultado líquido — 3 gabinetes | D40: Diferencial | E40: Viragem
A41: 1000 | B41: =(MIN(A41,$C$18)*$C$13*(1-$C$14)-$C$22)*(1-$C$16) | C41: =(MIN(A41,$D$18)*$D$13*(1-$D$14)-$D$22)*(1-$D$16) | D41: =C41-B41 | E41: =0
A42: 1400 | B42: =(MIN(A42,$C$18)*$C$13*(1-$C$14)-$C$22)*(1-$C$16) | C42: =(MIN(A42,$D$18)*$D$13*(1-$D$14)-$D$22)*(1-$D$16) | D42: =C42-B42 | E42: =IF(AND(D42>=0,D41<0),A42,0)
A43: 1800 | B43: =(MIN(A43,$C$18)*$C$13*(1-$C$14)-$C$22)*(1-$C$16) | C43: =(MIN(A43,$D$18)*$D$13*(1-$D$14)-$D$22)*(1-$D$16) | D43: =C43-B43 | E43: =IF(AND(D43>=0,D42<0),A43,0)
A44: 2200 | B44: =(MIN(A44,$C$18)*$C$13*(1-$C$14)-$C$22)*(1-$C$16) | C44: =(MIN(A44,$D$18)*$D$13*(1-$D$14)-$D$22)*(1-$D$16) | D44: =C44-B44 | E44: =IF(AND(D44>=0,D43<0),A44,0)
A45: 2600 | B45: =(MIN(A45,$C$18)*$C$13*(1-$C$14)-$C$22)*(1-$C$16) | C45: =(MIN(A45,$D$18)*$D$13*(1-$D$14)-$D$22)*(1-$D$16) | D45: =C45-B45 | E45: =IF(AND(D45>=0,D44<0),A45,0)
A46: 3000 | B46: =(MIN(A46,$C$18)*$C$13*(1-$C$14)-$C$22)*(1-$C$16) | C46: =(MIN(A46,$D$18)*$D$13*(1-$D$14)-$D$22)*(1-$D$16) | D46: =C46-B46 | E46: =IF(AND(D46>=0,D45<0),A46,0)
A47: 3400 | B47: =(MIN(A47,$C$18)*$C$13*(1-$C$14)-$C$22)*(1-$C$16) | C47: =(MIN(A47,$D$18)*$D$13*(1-$D$14)-$D$22)*(1-$D$16) | D47: =C47-B47 | E47: =IF(AND(D47>=0,D46<0),A47,0)
A48: 3800 | B48: =(MIN(A48,$C$18)*$C$13*(1-$C$14)-$C$22)*(1-$C$16) | C48: =(MIN(A48,$D$18)*$D$13*(1-$D$14)-$D$22)*(1-$D$16) | D48: =C48-B48 | E48: =IF(AND(D48>=0,D47<0),A48,0)
A49: 4200 | B49: =(MIN(A49,$C$18)*$C$13*(1-$C$14)-$C$22)*(1-$C$16) | C49: =(MIN(A49,$D$18)*$D$13*(1-$D$14)-$D$22)*(1-$D$16) | D49: =C49-B49 | E49: =IF(AND(D49>=0,D48<0),A49,0)
A50: 4600 | B50: =(MIN(A50,$C$18)*$C$13*(1-$C$14)-$C$22)*(1-$C$16) | C50: =(MIN(A50,$D$18)*$D$13*(1-$D$14)-$D$22)*(1-$D$16) | D50: =C50-B50 | E50: =IF(AND(D50>=0,D49<0),A50,0)
A51: 5000 | B51: =(MIN(A51,$C$18)*$C$13*(1-$C$14)-$C$22)*(1-$C$16) | C51: =(MIN(A51,$D$18)*$D$13*(1-$D$14)-$D$22)*(1-$D$16) | D51: =C51-B51 | E51: =IF(AND(D51>=0,D50<0),A51,0)
A52: 5400 | B52: =(MIN(A52,$C$18)*$C$13*(1-$C$14)-$C$22)*(1-$C$16) | C52: =(MIN(A52,$D$18)*$D$13*(1-$D$14)-$D$22)*(1-$D$16) | D52: =C52-B52 | E52: =IF(AND(D52>=0,D51<0),A52,0)
A53: 5800 | B53: =(MIN(A53,$C$18)*$C$13*(1-$C$14)-$C$22)*(1-$C$16) | C53: =(MIN(A53,$D$18)*$D$13*(1-$D$14)-$D$22)*(1-$D$16) | D53: =C53-B53 | E53: =IF(AND(D53>=0,D52<0),A53,0)
... A56: 7000 | B56: =(MIN(A56,$C$18)*$C$13*(1-$C$14)-$C$22)*(1-$C$16) | C56: =(MIN(A56,$D$18)*$D$13*(1-$D$14)-$D$22)*(1-$D$16) | D56: =C56-B56 | E56: =IF(AND(D56>=0,D55<0),A56,0)
A58: O TERCEIRO GABINETE COMPENSA A PARTIR DE (consultas/ano) | C58: =IF(MAX(E41:E56)=0,"Nunca compensa no intervalo analisado",MAX(E41:E56))
A59: …o que corresponde, no espaço de 2 gabinetes, a uma utilização de | C59: =IF(ISNUMBER($C$58),$C$58/$C$18,"n/a")
A60: Consultas por dia úteis implícitas nesse ponto | C60: =IF(ISNUMBER($C$58),$C$58/Operacao!$D$7,"n/a")
A62: Leitura: abaixo do ponto de viragem, o terceiro gabinete é renda e obras a mais sem receita adicional — a opção de dois gabinetes ganha por diferença de custo fixo. Acima, a opção de dois perde consultas por falta de espaço e a de três recupera o custo. A pergunta a fazer à cliente não é qual espaço prefere: é quantos doentes por dia espera atender no fim do segundo ano. Resolução do varrimento: 400 consultas por ano. O ponto de viragem real situa-se algures no intervalo anterior ao indicado — refinar por interpolação se a decisão ficar perto do limite. Registado em R1-34.

Sheet Validacao
A1: M1 — Validação
A2: Cada linha confronta o valor produzido pela folha de cálculo com um recálculo independente, escrito a partir das mesmas normas sem reutilizar nenhuma fórmula do modelo. Uma divergência significa que uma das duas implementações está errada. Nenhum número entra no relatório com esta folha vermelha, nem sem a assinatura das colunas H e I.
A4: Verificação | B4: Cenário | C4: Grandeza | D4: Valor do modelo | E4: Recálculo independente | F4: Diferença | G4: Estado | H4: Validado por (assinatura) | I4: Data
A5: V1 — ENI simplificado | B5: Base | C5: IRS imputável à atividade | D5: =V1_ENI_Simplificado!$D$36 | E5: 21022.94 | F5: =D5-E5 | G5: =IF(ABS(F5)<0.5,"OK","DIVERGE")
B6: Base | C6: Segurança Social (total) | D6: =V1_ENI_Simplificado!$D$23 | E6: 15099.84 | F6: =D6-E6 | G6: =IF(ABS(F6)<0.5,"OK","DIVERGE")
B7: Base | C7: Total impostos e contribuições | D7: =V1_ENI_Simplificado!$D$40 | E7: 36122.78 | F7: =D7-E7 | G7: =IF(ABS(F7)<0.5,"OK","DIVERGE")
B8: Base | C8: Líquido para a sócia | D8: =V1_ENI_Simplificado!$D$44 | E8: 11513.22 | F8: =D8-E8 | G8: =IF(ABS(F8)<0.5,"OK","DIVERGE")
A10: V2 — ENI cont. organizada | B10: Base | C10: IRS imputável à atividade | D10: =V2_ENI_ContOrg!$D$25 | E10: 7300.06 | F10: =D10-E10 | G10: =IF(ABS(F10)<0.5,"OK","DIVERGE")
B11: Base | C11: Segurança Social (total) | D11: =V2_ENI_ContOrg!$D$13 | E11: 8660.45 | F11: =D11-E11 | G11: =IF(ABS(F11)<0.5,"OK","DIVERGE")
B12: Base | C12: Total impostos e contribuições | D12: =V2_ENI_ContOrg!$D$29 | E12: 15960.51 | F12: =D12-E12 | G12: =IF(ABS(F12)<0.5,"OK","DIVERGE")
B13: Base | C13: Líquido para a sócia | D13: =V2_ENI_ContOrg!$D$33 | E13: 31675.49 | F13: =D13-E13 | G13: =IF(ABS(F13)<0.5,"OK","DIVERGE")
A15: V3 — Soc. transparente | B15: Base | C15: IRS imputável à atividade | D15: =V3_Soc_Transparente!$D$31 | E15: 7477.92 | F15: =D15-E15 | G15: =IF(ABS(F15)<0.5,"OK","DIVERGE")
B16: Base | C16: Segurança Social (total) | D16: =V3_Soc_Transparente!$D$18+V3_Soc_Transparente!$D$12 | E16: 5838 | F16: =D16-E16 | G16: =IF(ABS(F16)<0.5,"OK","DIVERGE")
B17: Base | C17: Total impostos e contribuições | D17: =V3_Soc_Transparente!$D$35 | E17: 14115.92 | F17: =D17-E17 | G17: =IF(ABS(F17)<0.5,"OK","DIVERGE")
B18: Base | C18: Líquido para a sócia | D18: =V3_Soc_Transparente!$D$39 | E18: 33520.08 | F18: =D18-E18 | G18: =IF(ABS(F18)<0.5,"OK","DIVERGE")
A20: V4 — Soc. não transparente | B20: Base | C20: IRS imputável à atividade | D20: =V4_Soc_NaoTransparente!$D$38 | E20: 2382.04 | F20: =D20-E20 | G20: =IF(ABS(F20)<0.5,"OK","DIVERGE")
B21: Base | C21: Segurança Social (total) | D21: =V4_Soc_NaoTransparente!$D$40+V4_Soc_NaoTransparente!$D$13 | E21: 5838 | F21: =D21-E21 | G21: =IF(ABS(F21)<0.5,"OK","DIVERGE")
B22: Base | C22: Total impostos e contribuições | D22: =V4_Soc_NaoTransparente!$D$43 | E22: 18792.52 | F22: =D22-E22 | G22: =IF(ABS(F22)<0.5,"OK","DIVERGE")
B23: Base | C23: Líquido para a sócia | D23: =V4_Soc_NaoTransparente!$D$47 | E23: 24612.36 | F23: =D23-E23 | G23: =IF(ABS(F23)<0.5,"OK","DIVERGE")
A25: V1 — ENI simplificado | B25: Alto | C25: IRS imputável à atividade | D25: =V1_ENI_Simplificado!$E$36 | E25: 38645.12 | F25: =D25-E25 | G25: =IF(ABS(F25)<0.5,"OK","DIVERGE")
B26: Alto | C26: Segurança Social (total) | D26: =V1_ENI_Simplificado!$E$23 | E26: 16101.36 | F26: =D26-E26 | G26: =IF(ABS(F26)<0.5,"OK","DIVERGE")
B27: Alto | C27: Total impostos e contribuições | D27: =V1_ENI_Simplificado!$E$40 | E27: 54746.48 | F27: =D27-E27 | G27: =IF(ABS(F27)<0.5,"OK","DIVERGE")
B28: Alto | C28: Líquido para a sócia | D28: =V1_ENI_Simplificado!$E$44 | E28: 11088.52 | F28: =D28-E28 | G28: =IF(ABS(F28)<0.5,"OK","DIVERGE")
A30: Estado global | D30: =IF(COUNTIF($G$6:$G$28,"DIVERGE")=0,"TODAS AS VERIFICAÇÕES OK","HÁ DIVERGÊNCIAS")
A32: O que esta folha NÃO valida: que os parâmetros da folha Parâmetros estejam corretos e em vigor para 2026, e que a leitura normativa esteja certa. Duas implementações da mesma leitura errada concordam perfeitamente. A validação normativa é da equipa de Fiscalidade e assina-se na coluna H.
A34: Bloco 2 — folhas operacionais, financeiras e de risco
A35: Acrescentado depois de a auditoria A1 ter apurado que 68% das fórmulas do ficheiro não tinham verificação independente, e que as folhas não verificadas eram precisamente as que sustentam a decisão.
A36: Operacao | B36: Base | C36: Capacidade anual instalada (consultas) | D36: =Operacao!$D$21 | E36: 4693.3333 | F36: =D36-E36 | G36: =IF(ABS(F36)<0.01,"OK","DIVERGE")
A37: Operacao | B37: Base | C37: Taxa de utilização dos gabinetes | D37: =Operacao!$D$26 | E37: 0.447443 | F37: =D37-E37 | G37: =IF(ABS(F37)<0.01,"OK","DIVERGE")
A38: Operacao | B38: Base | C38: Faturação anual total gerada | D38: =Operacao!$D$31 | E38: 100800 | F38: =D38-E38 | G38: =IF(ABS(F38)<0.01,"OK","DIVERGE")
A39: IVA | B39: Base | C39: IVA suportado no investimento | D39: =IVA!$D$10 | E39: 10810 | F39: =D39-E39 | G39: =IF(ABS(F39)<0.01,"OK","DIVERGE")
A40: BreakEven | B40: Base | C40: Margem de contribuição (%) | D40: =BreakEven!$D$9 | E40: 0.67 | F40: =D40-E40 | G40: =IF(ABS(F40)<0.01,"OK","DIVERGE")
A41: BreakEven | B41: Base | C41: Break-even operacional anual | D41: =BreakEven!$D$11 | E41: 29701.493 | F41: =D41-E41 | G41: =IF(ABS(F41)<0.01,"OK","DIVERGE")
A42: BreakEven | B42: Base | C42: Utilização necessária no break-even | D42: =BreakEven!$D$16 | E42: 0.131843 | F42: =D42-E42 | G42: =IF(ABS(F42)<0.01,"OK","DIVERGE")
A43: RiscoLaboral | B43: Base | C43: Passivo contingente total | D43: =RiscoLaboral!$D$14 | E43: 77064.75 | F43: =D43-E43 | G43: =IF(ABS(F43)<0.01,"OK","DIVERGE")
A44: Espaco | B44: Base | C44: Payback da opção A (2 gabinetes) | D44: =Espaco!$C$28 | E44: 1.733365 | F44: =D44-E44 | G44: =IF(ABS(F44)<0.01,"OK","DIVERGE")
A45: Tesouraria | B45: Base | C45: Total a desembolsar no arranque | D45: =Tesouraria!$C$9 | E45: 61410 | F45: =D45-E45 | G45: =IF(ABS(F45)<0.01,"OK","DIVERGE")
A46: Tesouraria | B46: Base | C46: Necessidade máxima de tesouraria | D46: =Tesouraria!$C$28 | E46: 62330.929 | F46: =D46-E46 | G46: =IF(ABS(F46)<0.01,"OK","DIVERGE")
A47: Tesouraria | B47: Base | C47: Total de dinheiro necessário antes de abrir | D47: =Tesouraria!$C$36 | E47: 67305.929 | F47: =D47-E47 | G47: =IF(ABS(F47)<0.01,"OK","DIVERGE")
A49: Estado do bloco 2 | D49: =IF(COUNTIF($G$36:$G$47,"DIVERGE")=0,"TODAS AS VERIFICAÇÕES OK","HÁ DIVERGÊNCIAS")
A50: Cobertura da validação | D50: 32 verificações sobre 18 folhas. Sem verificação independente permanecem apenas as folhas de apresentação (Comparativo e Conjuge), que só agregam valores já verificados nas folhas de origem.

Sheet RiscoLaboral
A1: M1 — Requalificação laboral: passivo contingente
A2: A ata identificou o risco e ninguém lhe pôs um número. Este é o número. Se a relação com os fisioterapeutas for requalificada como contrato de trabalho, a clínica passa a dever contribuições retroativas sobre tudo o que lhes pagou, com juros e coima. É o único risco deste projeto capaz de destruir o plano inteiro de uma vez.
A4: Rubrica | B4: Ref. | C4: Baixo | D4: Base | E4: Alto | F4: Nota / norma
A5: Exposição
A6: Honorários anuais pagos aos colaboradores | B6: HONOR | C6: =Inputs!$C$44 | D6: =Inputs!$D$44 | E6: =Inputs!$E$44 | F6: Só existe exposição no modelo de prestação de serviços. Na cedência de sala o fluxo é o inverso e o risco é outro — o de a cedência ser requalificada como prestação de serviços.
A7: Anos de exposição retroativa | B7: ANOS | C7: =Parametros!$C$16 | D7: =Parametros!$C$16 | E7: =Parametros!$C$16 | F7: Prazo de prescrição das contribuições. A inspeção não olha só para o ano corrente.
A8: Base de incidência retroativa | B8: BASE | C8: =$C$6*$C$7 | D8: =$D$6*$D$7 | E8: =$E$6*$E$7 | F8: Assume honorários constantes ao longo do período. Se crescerem, a exposição cresce com eles.
A9: Contribuições devidas em caso de requalificação
A10: Contribuições a cargo da entidade | B10: TSU_E | C10: =$C$8*Parametros!$C$14 | D10: =$D$8*Parametros!$C$14 | E10: =$E$8*Parametros!$C$14 | F10: Art. 53.º Cód. Contributivo. É a parcela que a clínica nunca pagou e passa a dever.
A11: Contribuições a cargo do trabalhador, não retidas | B11: TSU_T | C11: =$C$8*Parametros!$C$15 | D11: =$D$8*Parametros!$C$15 | E11: =$E$8*Parametros!$C$15 | F11: A entidade é responsável pela entrega. Na prática, é dívida da clínica.
A12: Juros de mora estimados | B12: JUROS | C12: =($C$10+$C$11)*Parametros!$C$17*$C$7/2 | D12: =($D$10+$D$11)*Parametros!$C$17*$D$7/2 | E12: =($E$10+$E$11)*Parametros!$C$17*$E$7/2 | F12: Aproximação: metade do período médio de mora sobre o total em dívida. Ordem de grandeza, não liquidação.
A13: Coima estimada | B13: COIMA | C13: =$C$10*Parametros!$C$18 | D13: =$D$10*Parametros!$C$18 | E13: =$E$10*Parametros!$C$18 | F13: ESTIMATIVA GROSSEIRA, a 50% das contribuições da entidade. A moldura das contraordenações por falta de comunicação de admissão e de pagamento de contribuições tem de ser confirmada pela Fiscalidade ou por advogado. Ver R1-38.
A14: PASSIVO CONTINGENTE TOTAL | B14: PASSIVO | C14: =$C$10+$C$11+$C$12+$C$13 | D14: =$D$10+$D$11+$D$12+$D$13 | E14: =$E$10+$E$11+$E$12+$E$13
A15: Dimensão do risco
A16: Resultado líquido anual da via de referência (via 2) | B16: LIQ_REF | C16: =V2_ENI_ContOrg!$C$33 | D16: =V2_ENI_ContOrg!$D$33 | E16: =V2_ENI_ContOrg!$E$33
A17: ANOS DE RESULTADO LÍQUIDO QUE O PASSIVO CONSOME | B17: ANOS_RES | C17: =IF($C$16<=0,"n/a",$C$14/$C$16) | D17: =IF($D$16<=0,"n/a",$D$14/$D$16) | E17: =IF($E$16<=0,"n/a",$E$14/$E$16) | F17: É esta a frase a dizer à cliente, e não a percentagem: quantos anos de trabalho pago desaparecem se isto correr mal.
A18: Passivo em % do investimento inicial | B18: VS_INV | C18: =IF((Inputs!$C$27+Inputs!$C$28+Inputs!$C$29+Inputs!$C$30)<=0,0,$C$14/(Inputs!$C$27+Inputs!$C$28+Inputs!$C$29+Inputs!$C$30)) | D18: =IF((Inputs!$D$27+Inputs!$D$28+Inputs!$D$29+Inputs!$D$30)<=0,0,$D$14/(Inputs!$D$27+Inputs!$D$28+Inputs!$D$29+Inputs!$D$30)) | E18: =IF((Inputs!$E$27+Inputs!$E$28+Inputs!$E$29+Inputs!$E$30)<=0,0,$E$14/(Inputs!$E$27+Inputs!$E$28+Inputs!$E$29+Inputs!$E$30))
A20: Indícios de laboralidade — art. 12.º n.º 1 do Código do Trabalho
A21: A presunção de contrato de trabalho opera quando se verifiquem ALGUMAS destas características. Não é preciso que se verifiquem todas. Marcar 1 onde se aplica.
A22: a) O local de trabalho pertence ao beneficiário da atividade ou é por ele determinado | C22: 1 | F22: ESTRUTURALMENTE PRESENTE numa clínica. O fisioterapeuta trabalha no espaço da Dra. Júlia. Não é evitável.
A23: b) Os equipamentos e instrumentos de trabalho pertencem ao beneficiário da atividade | C23: 1 | F23: ESTRUTURALMENTE PRESENTE se o equipamento clínico for da clínica. Evitável apenas se o profissional usar material próprio, o que raramente acontece.
A24: c) O prestador observa horas de início e de termo determinadas pelo beneficiário | C24: 0 | F24: EVITÁVEL, e é a decisão mais importante. Se a marcação de consultas for feita pela clínica com horário imposto, este indício verifica-se.
A25: d) É paga, com certa periodicidade, uma quantia certa ao prestador | C25: 0 | F25: EVITÁVEL. Honorários variáveis em função das sessões efetivamente realizadas afastam-no; um valor fixo mensal verifica-o.
A26: e) O prestador desempenha funções de direção ou chefia na estrutura da empresa | C26: 0 | F26: Improvável nesta fase.
A28: N.º de indícios verificados (de 5) | C28: =SUM($C$22:$C$26)
A29: LEITURA | C29: =IF($C$28>=3,"RISCO ELEVADO — presunção provável",IF($C$28=2,"RISCO ESTRUTURAL — os dois indícios inevitáveis já se verificam","RISCO CONTIDO"))
A31: O que este quadro mostra, e é o essencial: numa clínica, os indícios a) e b) verificam-se desde o primeiro dia e não são evitáveis — o profissional trabalha no espaço e com o equipamento da clínica. A margem de manobra está inteiramente em c) e d), ou seja, no horário e na forma de remuneração. É aí que a blindagem contratual e, sobretudo, a prática diária têm de trabalhar. Um contrato bem redigido que seja desmentido pelo funcionamento real não protege ninguém. A presunção é ilidível, mas inverte o ónus da prova: passa a caber à clínica demonstrar que não há contrato de trabalho. A redação dos contratos e o parecer laboral estão fora do nosso âmbito; identificar e quantificar o risco, não.

Sheet Tesouraria
A1: M1 — Tesouraria do ano 1 e necessidade de fundo de maneio
A2: Um negócio pode ser rentável e mesmo assim ficar sem dinheiro. O investimento paga-se todo no início, a receita sobe devagar, e há pagamentos que chegam em bloco. Esta folha responde à única pergunta que importa antes de assinar seja o que for: quanto dinheiro é preciso ter na mão para chegar ao fim do primeiro ano.
A4: Fundos necessários no arranque
A5: Investimento em obras, equipamento e software | B5: INV | C5: =Inputs!$D$27+Inputs!$D$28+Inputs!$D$29+Inputs!$D$30
A6: IVA irrecuperável sobre o investimento | B6: IVA_IRR | C6: =IVA!$D$10 | D6: Sai da conta e não volta: a fisioterapia é isenta sem direito à dedução.
A7: Caução do arrendamento (meses de renda) | B7: MESES_CAUC | C7: 3 | D7: Rubrica que quase sempre se esquece no plano de investimento. Confirmar com a proposta de arrendamento.
A8: Caução do arrendamento | B8: CAUCAO | C8: =$C$7*Inputs!$D$19/12
A9: TOTAL A DESEMBOLSAR NO ARRANQUE | B9: ARRANQUE | C9: =$C$5+$C$6+$C$8
A11: Ano 1, mês a mês
A12: Rubrica | B12: Ref. | C12: Mês 1 | D12: Mês 2 | E12: Mês 3 | F12: Mês 4 | G12: Mês 5 | H12: Mês 6 | I12: Mês 7 | J12: Mês 8 | K12: Mês 9 | L12: Mês 10 | M12: Mês 11 | N12: Mês 12 | O12: Ano 1 | P12: Nota
A13: Taxa de ocupação dos gabinetes | B13: OCUP | C13: 0.15 | D13: 0.2 | E13: 0.25 | F13: 0.3 | G13: 0.33 | H13: 0.36 | I13: 0.39 | J13: 0.41 | K13: 0.43 | L13: 0.44 | M13: 0.45 | N13: 0.45 | P13: RAMPA DE ARRANQUE. É a fila de inputs mais importante desta folha e a que ninguém quer preencher com honestidade. Uma clínica nova não abre à ocupação de cruzeiro.
A14: Consultas do mês | B14: CONS | C14: =(Operacao!$D$21/12)*C$13 | D14: =(Operacao!$D$21/12)*D$13 | E14: =(Operacao!$D$21/12)*E$13 | F14: =(Operacao!$D$21/12)*F$13 | G14: =(Operacao!$D$21/12)*G$13 | H14: =(Operacao!$D$21/12)*H$13 | I14: =(Operacao!$D$21/12)*I$13 | J14: =(Operacao!$D$21/12)*J$13 | ... N14: =(Operacao!$D$21/12)*N$13 | O14: =SUM(C14:N14)
A15: Faturação do mês | B15: FAT | C15: =C$14*BreakEven!$D$14 | D15: =D$14*BreakEven!$D$14 | E15: =E$14*BreakEven!$D$14 | F15: =F$14*BreakEven!$D$14 | G15: =G$14*BreakEven!$D$14 | H15: =H$14*BreakEven!$D$14 | I15: =I$14*BreakEven!$D$14 | J15: =J$14*BreakEven!$D$14 | ... N15: =N$14*BreakEven!$D$14 | O15: =SUM(C15:N15)
A16: % recebida no próprio mês | B16: PCT_PRONTO | C16: 0.85 | D16: 0.85 | E16: 0.85 | F16: 0.85 | G16: 0.85 | H16: 0.85 | I16: 0.85 | J16: 0.85 | K16: 0.85 | L16: 0.85 | M16: 0.85 | N16: 0.85 | P16: Consultas particulares pagam-se na hora; subsistemas e seguros pagam a 30 dias ou mais.
A17: Recebimentos | B17: REC | C17: =C$15*C$16 | D17: =D$15*D$16+C$15*(1-C$16) | E17: =E$15*E$16+D$15*(1-D$16) | F17: =F$15*F$16+E$15*(1-E$16) | G17: =G$15*G$16+F$15*(1-F$16) | H17: =H$15*H$16+G$15*(1-G$16) | I17: =I$15*I$16+H$15*(1-H$16) | J17: =J$15*J$16+I$15*(1-I$16) | K17: =K$15*K$16+J$15*(1-J$16) | ... N17: =N$15*N$16+M$15*(1-M$16) | O17: =SUM(C17:N17) | P17: O desfasamento entre faturar e receber é dinheiro que falta em caixa.
A18: Custos variáveis (consumíveis e colaboradores) | B18: CV | C18: =C$15*(1-BreakEven!$D$9) | D18: =D$15*(1-BreakEven!$D$9) | E18: =E$15*(1-BreakEven!$D$9) | F18: =F$15*(1-BreakEven!$D$9) | G18: =G$15*(1-BreakEven!$D$9) | H18: =H$15*(1-BreakEven!$D$9) | I18: =I$15*(1-BreakEven!$D$9) | J18: =J$15*(1-BreakEven!$D$9) | ... N18: =N$15*(1-BreakEven!$D$9) | O18: =SUM(C18:N18)
A19: Custos fixos | B19: CF | C19: =BreakEven!$D$10/12 | D19: =BreakEven!$D$10/12 | E19: =BreakEven!$D$10/12 | F19: =BreakEven!$D$10/12 | G19: =BreakEven!$D$10/12 | H19: =BreakEven!$D$10/12 | I19: =BreakEven!$D$10/12 | J19: =BreakEven!$D$10/12 | ... N19: =BreakEven!$D$10/12 | O19: =SUM(C19:N19) | P19: Renda, condomínio, seguros, software e outros. Pagam-se haja ou não doentes.
A20: Segurança Social | B20: SS | C20: =V2_ENI_ContOrg!$D$13/12 | D20: =V2_ENI_ContOrg!$D$13/12 | E20: =V2_ENI_ContOrg!$D$13/12 | F20: =V2_ENI_ContOrg!$D$13/12 | G20: =V2_ENI_ContOrg!$D$13/12 | H20: =V2_ENI_ContOrg!$D$13/12 | I20: =V2_ENI_ContOrg!$D$13/12 | J20: =V2_ENI_ContOrg!$D$13/12 | ... N20: =V2_ENI_ContOrg!$D$13/12 | O20: =SUM(C20:N20) | P20: Aproximação de cruzeiro. No primeiro ano a base é a declarada, não o lucro do próprio ano. Ver R1-40.
A21: IRS — pagamentos por conta | B21: IRS_PC | C21: 0 | D21: 0 | E21: 0 | F21: 0 | G21: 0 | H21: 0 | I21: 0 | J21: 0 | K21: 0 | L21: 0 | M21: 0 | N21: 0 | O21: =SUM(C21:N21) | P21: A PREENCHER, e é uma armadilha clássica: no ano 1 os pagamentos por conta são calculados sobre o rendimento do ano ANTERIOR, no regime antigo. Paga-se IRS do passado enquanto se está a investir no futuro. Vencem em julho, setembro e dezembro — meses 7, 9 e 12.
A22: Investimento e caução | B22: INV_M | C22: =$C$9 | D22: 0 | E22: 0 | F22: 0 | G22: 0 | H22: 0 | I22: 0 | J22: 0 | K22: 0 | L22: 0 | M22: 0 | N22: 0 | O22: =SUM(C22:N22) | P22: Todo no mês 1. Se a empreitada for faseada, repartir.
A23: SALDO DO MÊS | B23: SALDO | C23: =C$17-C$18-C$19-C$20-C$21-C$22 | D23: =D$17-D$18-D$19-D$20-D$21-D$22 | E23: =E$17-E$18-E$19-E$20-E$21-E$22 | F23: =F$17-F$18-F$19-F$20-F$21-F$22 | G23: =G$17-G$18-G$19-G$20-G$21-G$22 | H23: =H$17-H$18-H$19-H$20-H$21-H$22 | I23: =I$17-I$18-I$19-I$20-I$21-I$22 | J23: =J$17-J$18-J$19-J$20-J$21-J$22 | ... N23: =N$17-N$18-N$19-N$20-N$21-N$22 | O23: =SUM(C23:N23)
A24: SALDO ACUMULADO | B24: ACUM | C24: =C$23 | D24: =C$24+D$23 | E24: =D$24+E$23 | F24: =E$24+F$23 | G24: =F$24+G$23 | H24: =G$24+H$23 | I24: =H$24+I$23 | J24: =I$24+J$23 | K24: =J$24+K$23 | ... N24: =M$24+N$23 | P24: É esta a linha que decide se o projeto sobrevive ao primeiro ano.
A25: Marcador do ponto mais baixo | B25: MARC_MIN | C25: =IF(C$24=MIN($C$24:$N$24),1,0) | D25: =IF(D$24=MIN($C$24:$N$24),2,0) | E25: =IF(E$24=MIN($C$24:$N$24),3,0) | F25: =IF(F$24=MIN($C$24:$N$24),4,0) | G25: =IF(G$24=MIN($C$24:$N$24),5,0) | H25: =IF(H$24=MIN($C$24:$N$24),6,0) | I25: =IF(I$24=MIN($C$24:$N$24),7,0) | J25: =IF(J$24=MIN($C$24:$N$24),8,0) | K25: =IF(K$24=MIN($C$24:$N$24),9,0) | L25: =IF(L$24=MIN($C$24:$N$24),10,0) | M25: =IF(M$24=MIN($C$24:$N$24),11,0) | N25: =IF(N$24=MIN($C$24:$N$24),12,0)
A26: Marcador de recuperação | B26: MARC | C26: 0 | D26: =IF(AND(D$24>=0,C$24<0),2,0) | E26: =IF(AND(E$24>=0,D$24<0),3,0) | F26: =IF(AND(F$24>=0,E$24<0),4,0) | G26: =IF(AND(G$24>=0,F$24<0),5,0) | H26: =IF(AND(H$24>=0,G$24<0),6,0) | I26: =IF(AND(I$24>=0,H$24<0),7,0) | J26: =IF(AND(J$24>=0,I$24<0),8,0) | K26: =IF(AND(K$24>=0,J$24<0),9,0) | L26: =IF(AND(L$24>=0,K$24<0),10,0) | M26: =IF(AND(M$24>=0,L$24<0),11,0) | N26: =IF(AND(N$24>=0,M$24<0),12,0)
A28: NECESSIDADE MÁXIMA DE TESOURARIA | C28: =-MIN($C$24:$N$24) | E28: O ponto mais fundo do saldo acumulado. JÁ INCLUI o investimento e a caução, porque eles saem da mesma conta bancária — não somar outra vez.
A29: da qual, investimento e caução | C29: =$C$9 | E29: Desembolso de uma só vez, no arranque.
A30: da qual, cobertura do défice operacional | C30: =-MIN($C$24:$N$24)-$C$9 | E30: O que a operação consome enquanto a receita não chega para os custos. É a parte que quase ninguém orça, e é a que apanha quem abre pela primeira vez.
A31: Mês em que o saldo acumulado atinge o ponto mais baixo | C31: =MAX($C$25:$N$25)
A32: Mês em que o saldo acumulado volta a ser positivo | C32: =IF(MAX($C$26:$N$26)=0,"Não recupera dentro do ano 1",MAX($C$26:$N$26)) | E32: Se não recuperar dentro do ano 1, o fundo de maneio tem de cobrir também o ano 2.
A33: Margem de segurança (meses de custos fixos) | C33: 3 | E33: A PREENCHER. Nenhuma projeção acerta. Três meses é uma convenção prudente para quem não tem outra fonte de rendimento.
A35: Margem de segurança, em euros | C35: =$C$33*BreakEven!$D$10/12
A36: TOTAL DE DINHEIRO NECESSÁRIO ANTES DE ABRIR | C36: =$C$28+$C$35 | E36: Investimento, caução e fundo de maneio. É este o número a dizer à cliente antes de qualquer conversa sobre estrutura fiscal. Se ela não o tiver ou não o conseguir financiar, a discussão sobre ENI ou sociedade é prematura.
A38: Visão a três anos
A39: Rubrica | B39: Ref. | C39: Ano 1 | D39: Ano 2 | E39: Ano 3 | F39: Nota
A40: Taxa de ocupação média do ano | B40: OCUP | C40: =AVERAGE($C$13:$N$13) | D40: 0.52 | E40: 0.58 | F40: Ano 1 é a média da rampa. Anos 2 e 3 a preencher — e a justificar com o plano de captação de doentes, que não existe e é o pressuposto silencioso de tudo isto (R1-41).
A41: Faturação | B41: FAT | C41: =Operacao!$D$21*$C$40*BreakEven!$D$14 | D41: =Operacao!$D$21*$D$40*BreakEven!$D$14 | E41: =Operacao!$D$21*$E$40*BreakEven!$D$14
A42: Custos variáveis | B42: CV | C42: =$C$41*(1-BreakEven!$D$9) | D42: =$D$41*(1-BreakEven!$D$9) | E42: =$E$41*(1-BreakEven!$D$9)
A43: Custos fixos | B43: CF | C43: =BreakEven!$D$10 | D43: =BreakEven!$D$10 | E43: =BreakEven!$D$10
A44: Resultado operacional | B44: RES | C44: =$C$41-$C$42-$C$43 | D44: =$D$41-$D$42-$D$43 | E44: =$E$41-$E$42-$E$43
A45: Impostos e contribuições estimados | B45: CARGA | C45: =MAX(0,$C$44)*V2_ENI_ContOrg!$D$30 | D45: =MAX(0,$D$44)*V2_ENI_ContOrg!$D$30 | E45: =MAX(0,$E$44)*V2_ENI_ContOrg!$D$30 | F45: Aplica a taxa de esforço da via 2 no cenário Base. Aproximação: a taxa real varia com o nível de rendimento. Ver R1-33.
A46: Resultado líquido | B46: LIQ | C46: =$C$44-$C$45 | D46: =$D$44-$D$45 | E46: =$E$44-$E$45
A47: Caixa acumulada desde o arranque | B47: CX | C47: =$C$46-$C$9 | D47: =$C$47+$D$46 | E47: =$D$47+$E$46 | F47: Inclui o desembolso inicial. O ano em que esta linha passa a positiva é o payback real.
A49: Esta visão a três anos assume custos fixos constantes e preço constante. Não é uma projeção financeira completa — é o suficiente para responder a «quando é que recupero o que meti» e a «o ano 1 é sustentável». Uma projeção completa exigiria inflação de custos, renovação de equipamento e evolução da tabela de preços, e nenhuma dessas coisas está informada. Registado em R1-42.

Sheet Alertas
A1: M1 — Alertas
A2: Um modelo pode ter a fórmula certa, a fiscalidade certa e um pressuposto empresarial errado. Esta folha existe para apanhar o terceiro caso. Enquanto houver um alerta ATIVO com consequência bloqueante, nenhum número deste ficheiro pode ser citado no relatório, no deck ou perante a cliente.
A4: Interruptores manuais — a equipa liga e desliga
A5: Atividade do cônjuge confirmada fora da tabela do art. 151.º CIRS? (1 = sim / 0 = não) | B5: 0 | D5: R1-14 e N1-01. Enquanto for 0, a via 4 não é apresentável.
A6: Qualificação da cedência de sala fixada pela Fiscalidade? (1 = sim / 0 = não) | B6: 0 | D6: N1-04. Enquanto for 0, o modelo 2 tem consequências fiscais assumidas, não determinadas.
A7: Financiamento do investimento identificado? (1 = sim / 0 = não) | B7: 0 | D7: Obras, equipamento e IVA irrecuperável têm de sair de algum lado.
A9: Alerta | B9: Valor avaliado | C9: Estado | D9: Consequência se ativo | E9: Referência
A10: Parâmetros fiscais por validar para 2026 | B10: =SUM(Parametros!$F$6:$F$50) | C10: =IF(B10>0,"ATIVO","—") | D10: BLOQUEANTE. Os números podem estar certos na aritmética e errados na lei. Nenhum valor sai do ficheiro enquanto este alerta estiver ativo. | E10: R1, secção C · P0 da spec
A11: Inputs da cliente por confirmar | B11: =SUM(Inputs!$J$6:$J$40) | C11: =IF(B11>0,"ATIVO","—") | D11: BLOQUEANTE para o relatório. Os valores em uso são placeholders de teste do motor. | E11: R1, secção A · brief, secção 4
A12: Utilização dos gabinetes acima de 100% | B12: =Operacao!$D$26 | C12: =IF(B12>Parametros!$C$20,"ATIVO","—") | D12: A projeção é impossível: não há gabinetes para as consultas previstas. Corrigir a projeção ou o número de gabinetes antes de qualquer outra coisa. | E12: Folha Operacao
A13: Utilização dos gabinetes acima de 85% | B13: =Operacao!$D$26 | C13: =IF(AND(B13>Parametros!$C$21,B13<=Parametros!$C$20),"ATIVO","—") | D13: Operacionalmente muito exigente: sem folga para faltas, férias ou variação de procura. | E13: Folha Operacao
A14: Utilização subaproveitada, abaixo de 30% | B14: =Operacao!$D$26 | C14: =IF(B14<Parametros!$C$22,"ATIVO","—") | D14: O espaço está sobredimensionado para a procura projetada. Rever a opção de espaço. | E14: Folhas Operacao e Espaco
A15: Receita projetada abaixo do break-even operacional | B15: =BreakEven!$D$13 | C15: =IF(B15<0,"ATIVO","—") | D15: A clínica não cobre os custos fixos com a faturação projetada. A discussão de estrutura fiscal é secundária face a isto. | E15: Folha BreakEven
A16: Margem de contribuição nula ou negativa | B16: =BreakEven!$D$9 | C16: =IF(B16<=0,"ATIVO","—") | D16: Cada consulta adicional destrói valor. Rever a % de honorários ou o preço. | E16: Folha BreakEven
A17: Utilização necessária para o break-even acima de 100% | B17: =BreakEven!$D$16 | C17: =IF(B17>1,"ATIVO","—") | D17: O espaço não consegue cobrir os próprios custos fixos nem a lotação máxima. O espaço está errado, não a estrutura. | E17: Folhas BreakEven e Espaco
A18: Premissa da atividade do cônjuge por verificar | B18: =1-$B$5 | C18: =IF(B18=1,"ATIVO","—") | D18: BLOQUEANTE para a via 4. Se a atividade do cônjuge constar da tabela do art. 151.º CIRS, a entrada dele não afasta a transparência com percentagem nenhuma. | E18: R1-14 · N1, secção 4.1
A19: Qualificação da cedência de sala por fixar | B19: =1-$B$6 | C19: =IF(B19=1,"ATIVO","—") | D19: O modelo 2 corre com consequências fiscais assumidas. A qualificação depende da configuração contratual e operacional concreta, não do nome do modelo. | E19: N1-04 · R1-31
A20: Investimento sem financiamento identificado | B20: =1-$B$7 | C20: =IF(B20=1,"ATIVO","—") | D20: O plano assume que o investimento é feito. Se não houver origem de fundos, o cenário não é executável. | E20: Folha Espaco · P1, fase 3
A21: IVA dependente de pro rata ou afetação real | B21: =Inputs!$D$47 | C21: =IF(B21>0,"ATIVO","—") | D21: A dedução de IVA deixa de ser zero e passa a depender de um método e de segregação documental permanente. Confirmar o método antes de contar com o valor. | E21: Folha IVA · N1, secção 8
A22: Recálculo independente com divergências | B22: =IF(AND(Validacao!$D$30="TODAS AS VERIFICAÇÕES OK",Validacao!$D$49="TODAS AS VERIFICAÇÕES OK"),0,1) | C22: =IF(B22=1,"ATIVO","—") | D22: BLOQUEANTE. As duas implementações do modelo discordam. Uma delas está errada. | E22: Folha Validacao
A24: TOTAL DE ALERTAS ATIVOS | B24: =COUNTIF($C$10:$C$22,"ATIVO")
A25: O FICHEIRO PODE PRODUZIR NÚMEROS CITÁVEIS? | B25: =IF(COUNTIF($C$10:$C$22,"ATIVO")=0,"SIM","NÃO — resolver os alertas ativos")
A27: Esta folha não substitui a Validacao. A Validacao verifica que as duas implementações do modelo concordam; esta verifica que o resultado faz sentido como negócio. São perguntas diferentes e um modelo pode passar numa e falhar na outra.

Sheet Conjuge
A1: M1 — Entrada do cônjuge: custo de complexidade
A2: A hipótese foi levantada na reunião e ficou em análise, nem descartada nem recomendada. Esta folha põe de um lado tudo o que a entrada do cônjuge dá e do outro tudo o que custa, para que a decisão não se tome pela metade que é mais fácil de calcular.
A4: Rubrica | B4: Ref. | C4: Baixo | D4: Base | E4: Alto | F4: Nota
A5: A premissa de que tudo depende
A6: Toda esta folha assume que a atividade do cônjuge NÃO consta da tabela do art. 151.º CIRS. Se constar — por enquadramento como desportista ou pelo código residual — a entrada dele não afasta a transparência fiscal com percentagem de capital nenhuma, e tudo o que está abaixo passa a ser custo sem contrapartida. A premissa nunca foi verificada.
A7: Premissa verificada? (1 = sim / 0 = não) | B7: PREMISSA | C7: =Alertas!$B$5 | D7: =Alertas!$B$5 | E7: =Alertas!$B$5 | F7: Interruptor na folha Alertas. Ver R1-14 e N1-01.
A8: O que a entrada do cônjuge dá
A9: IVA recuperável atribuível à entrada do cônjuge | B9: G_IVA | C9: =IVA!$C$21 | D9: =IVA!$D$21 | E9: =IVA!$E$21 | F9: Zero enquanto o cônjuge não faturar DENTRO da sociedade. Deter capital não dá IVA nenhum: são duas decisões diferentes.
A10: Diferencial de líquido para a sócia, via 4 face à via 3 | B10: G_ESTR | C10: =V4_Soc_NaoTransparente!$C$47-V3_Soc_Transparente!$C$39 | D10: =V4_Soc_NaoTransparente!$D$47-V3_Soc_Transparente!$D$39 | E10: =V4_Soc_NaoTransparente!$E$47-V3_Soc_Transparente!$E$39 | F10: Negativo significa que afastar a transparência custa dinheiro à sócia nas condições atuais de distribuição. Depende inteiramente da alavanca POL_DIST.
A11: Total dos ganhos anuais | B11: G_TOT | C11: =$C$9+$C$10 | D11: =$D$9+$D$10 | E11: =$E$9+$E$10 | F11: O ganho de IVA é de uma só vez, no ano do investimento; o diferencial de estrutura é recorrente. Somá-los na mesma linha é uma simplificação — ler as duas linhas acima.
A12: O que a entrada do cônjuge custa
A13: Quota de lucros atribuída ao cônjuge, por ano | B13: C_QUOTA | C13: =V4_Soc_NaoTransparente!$C$46 | D13: =V4_Soc_NaoTransparente!$D$46 | E13: =V4_Soc_NaoTransparente!$E$46 | F13: Dentro do agregado é uma transferência, não uma perda. Fora dele — divórcio, sucessão — é definitiva. O relatório tem de dizer as duas coisas.
A14: Custo administrativo anual de sujeito passivo misto | B14: C_ADM | C14: 0 | D14: 0 | E14: 0 | F14: A PREENCHER com a estimativa do contabilista: segregação documental, pro rata ou afetação real, regularizações anuais, obrigações declarativas adicionais. Não é zero.
A15: Custo de constituição e de alterações societárias | B15: C_CONST | C15: 0 | D15: 0 | E15: 0 | F15: A PREENCHER. Custo único.
A16: Total dos custos anuais | B16: C_TOT | C16: =$C$13+$C$14+$C$15 | D16: =$D$13+$D$14+$D$15 | E16: =$E$13+$E$14+$E$15
A17: Saldo
A18: SALDO ANUAL DA OPERAÇÃO, NA ESFERA DA SÓCIA | B18: SALDO | C18: =$C$11-$C$16 | D18: =$D$11-$D$16 | E18: =$E$11-$E$16
A19: SALDO ANUAL NA ESFERA DO AGREGADO | B19: SALDO_AGR | C19: =$C$11-$C$14-$C$15 | D19: =$D$11-$D$14-$D$15 | E19: =$E$11-$E$14-$E$15 | F19: Exclui a quota de lucros do cônjuge, que dentro do agregado não sai. É a leitura mais favorável possível à operação.
A20: Leitura | B20: VEREDITO | C20: =IF($C$7=0,"NÃO DECIDÍVEL — premissa por verificar",IF($C$18>0,"Favorável na esfera da sócia",IF($C$19>0,"Favorável apenas na ótica do agregado, não na da sócia","Desfavorável nas condições atuais"))) | D20: =IF($D$7=0,"NÃO DECIDÍVEL — premissa por verificar",IF($D$18>0,"Favorável na esfera da sócia",IF($D$19>0,"Favorável apenas na ótica do agregado, não na da sócia","Desfavorável nas condições atuais"))) | E20: =IF($E$7=0,"NÃO DECIDÍVEL — premissa por verificar",IF($E$18>0,"Favorável na esfera da sócia",IF($E$19>0,"Favorável apenas na ótica do agregado, não na da sócia","Desfavorável nas condições atuais")))
A22: O que esta folha não quantifica, e tem de ser dito por palavras no capítulo 7: a perda de controlo qualificado, já que uma participação superior a 25% dá capacidade de bloqueio das deliberações que exijam maioria de três quartos; o efeito em caso de divórcio ou sucessão; e o risco de o desenho ser lido como artificial ao abrigo do art. 38.º n.º 2 da LGT se a participação não tiver substância económica real. Nenhuma destas três coisas tem preço, e todas podem ser mais caras do que o saldo acima.
